Workbook

Sheet Summary
A1: Mellox AI: pricing and cost model v2 (OpenRouter model stack)
A2: Built from your model-migration spec and prices checked 2026-09-25. USD per month unless marked.
A4: How to use
A5: Blue = input, black = formula, green = link to another tab, yellow = the levers that move the answer. Swap a tier model on Inputs, a price on Vendor Prices or a plan limit on Plans and every tab updates. Video provider mode (split / openrouter / kie) and the Post for Me price are on Inputs.
A7: Plan | B7: Price | C7: Annual price | D7: Credits | E7: Video credits | F7: Pro messages | G7: Cost to serve (typical) | H7: Margin typical / worst
A8: Free | B8: =Plans!$C$6 -> 0 | C8: =Plans!$C$7 -> 0 | D8: =Plans!$C$10 -> 50 | E8: =Plans!$C$11 -> 0 | F8: =Plans!$C$12 -> 0 | G8: =Plans!$C$54 -> 0.91778372 | H8: =IF(Plans!$C$6=0,"n/a",TEXT(Plans!$C$61,"0%")&" / "&TEXT(Plans!$C$63,"0%")) -> n/a
A9: Starter | B9: =Plans!$D$6 -> 49 | C9: =Plans!$D$7 -> 40.8317 | D9: =Plans!$D$10 -> 2000 | E9: =Plans!$D$11 -> 4 | F9: =Plans!$D$12 -> 30 | G9: =Plans!$D$54 -> 11.928008 | H9: =IF(Plans!$D$6=0,"n/a",TEXT(Plans!$D$61,"0%")&" / "&TEXT(Plans!$D$63,"0%")) -> 67% / 43%
A10: Growth | B10: =Plans!$E$6 -> 149 | C10: =Plans!$E$7 -> 124.1617 | D10: =Plans!$E$10 -> 6000 | E10: =Plans!$E$11 -> 12 | F10: =Plans!$E$12 -> 150 | G10: =Plans!$E$54 -> 37.46599 | H10: =IF(Plans!$E$6=0,"n/a",TEXT(Plans!$E$61,"0%")&" / "&TEXT(Plans!$E$63,"0%")) -> 67% / 44%
A11: Agency | B11: =Plans!$F$6 -> 449 | C11: =Plans!$F$7 -> 374.1517 | D11: =Plans!$F$10 -> 18000 | E11: =Plans!$F$11 -> 40 | F11: =Plans!$F$12 -> 400 | G11: =Plans!$F$54 -> 115.94285 | H11: =IF(Plans!$F$6=0,"n/a",TEXT(Plans!$F$61,"0%")&" / "&TEXT(Plans!$F$63,"0%")) -> 67% / 45%
A12: Scale | B12: =Plans!$G$6 -> 1199 | C12: =Plans!$G$7 -> 999.1267 | D12: =Plans!$G$10 -> 50000 | E12: =Plans!$G$11 -> 100 | F12: =Plans!$G$12 -> 1200 | G12: =Plans!$G$54 -> 351.54697 | H12: =IF(Plans!$G$6=0,"n/a",TEXT(Plans!$G$61,"0%")&" / "&TEXT(Plans!$G$63,"0%")) -> 63% / 42%
A14: Key number | B14: Value
A15: Blended cost per Mellox credit | B15: =Inputs!$B$37 -> 0.0020341557
A16: Margin on credits at face value | B16: ='Credit Menu'!$K$41 -> 0.79658443
A17: Cost per video credit, OpenRouter | B17: ='Video Credits'!$K$20 -> 0.80883908
A18: Cost per video credit, KIE | B18: ='Video Credits'!$K$21 -> 0.39138333
A19: Chat message: Mellox Flash / Pro | B19: =TEXT('Unit Costs'!$AB$19,"$0.0000")&" / "&TEXT('Unit Costs'!$AB$20,"$0.0000") -> $0.0089 / $0.0482
A20: Brand DNA scan | B20: ='Unit Costs'!$AB$24 -> 0.23438541
A21: Premium article | B21: ='Unit Costs'!$AB$31 -> 0.19315557
A22: Image post | B22: ='Unit Costs'!$AB$28 -> 0.066162415
A23: One tracked prompt, 3 engines | B23: ='Unit Costs'!$AB$50 -> 0.015917312
A24: Standard 8s video on OpenRouter | B24: ='Video Credits'!F7 -> 0.844
A25: Fixed costs at launch | B25: ='Fixed Costs'!$C$25 -> 284.46667
A26: Break-even month (active scenario) | B26: =Projection!$B$55 -> 8
A27: MRR at month 12 / 24 | B27: =TEXT(Projection!$B$57,"$#,##0")&" / "&TEXT(Projection!$B$58,"$#,##0") -> $8,600 / $31,226
A29: Top risks (details on Risks & Fixes)
A30: [High] KIE carries Veo and Grok for now. If KIE goes away, Standard Veo 3.1 Fast 8s goes from $0.30 to $0.84 and Draft from $0.15 to $0.42.
A31: [High] Grok Imagine on OpenRouter costs $0.14/s (about $0.90 for 6s) versus $0.12 on KIE. If variation ever falls back to it, it costs more than a Standard video.
A32: [Medium] Social posting moved to Post for Me: $10 for 1,000 posts, unlimited accounts. Posts are now unlimited on every plan, Free included, and never use credits. A spam or bot account on Free could post thousands of times.
A33: [High] GEO probes: GPT-5.6 Luna and Gemini 3.8 Flash answer from memory (no web search), so they do not show what ChatGPT or Gemini users actually see. Google AI Overviews are not tracked at all, although the product promises them.
A34: [High] Premium routes now cost 2-9x more: Brand DNA $0.08 -> $0.24, articles $0.02 -> $0.20, Coach $0.10 -> $0.20, Market Brain $0.12 -> $0.25, GEO fix $0.10 -> $0.29.
A35: [Medium] Every free signup triggers an Opus Brand DNA scan + Brand Kit analysis: about $0.34 each, paid upfront even if the user never returns.

Sheet Inputs
A1: Global inputs, model tiers and levers
A2: Blue = typed input, green = from Vendor Prices, yellow = levers that move the answer most.
A4: Lever | B4: Value | C4: Notes / source
A5: USD to PKR rate | B5: ='Vendor Prices'!$G$58 -> 277.09
A6: Credit face value (USD per Mellox credit) | B6: 0.01 | C6: Same unit as the backlink ledger (100 credits per $)
A7: OpenRouter credit fee | B7: ='Vendor Prices'!$G$53 -> 0.055 | C7: Now charged on text, images and video
A8: Anthropic tokenizer factor (Opus family) | B8: 1.15 | C8: New Claude tokenizer counts 1.0-1.35x tokens
A9: PREMIUM tier model | B9: anthropic/claude-opus-5.5 | C9: task-models.ts PREMIUM
A10: WORKHORSE tier model | B10: google/gemini-3.8-flash | C10: task-models.ts WORKHORSE
A11: ECONOMY tier model | B11: google/gemini-3.1-flash-lite | C11: task-models.ts ECONOMY
A12: PREMIUM fallback | B12: google/gemini-3.8-flash | C12: Spec: falls back to WORKHORSE (effort high)
A13: WORKHORSE fallback | B13: openai/gpt-5.6-terra
A14: ECONOMY fallback | B14: openai/gpt-5.6-luna
A15: Share of calls answered by the fallback model | B15: 0.03 | C15: Watch in metering: answering model is now recorded
A16: Payment processor % (Paddle) | B16: ='Vendor Prices'!$G$54 -> 0.05
A17: Payment fixed fee per transaction | B17: ='Vendor Prices'!$G$55 -> 0.5
A18: Payout FX spread | B18: ='Vendor Prices'!$G$56 -> 0.02
A19: Pakistan IT export tax | B19: ='Vendor Prices'!$G$57 -> 0.0025
A20: Image re-roll factor | B20: 1.3 | C20: Users re-roll ~30% of images
A21: Typical use of included credits | B21: 0.5
A22: Typical use of included video credits | B22: 0.6 | C22: Video allowances get used more than general credits
A23: Typical use of included Mellox Pro messages | B23: 0.4
A24: Weeks per month | B24: 4.33
A25: Days per month | B25: 30
A26: Post for Me cost per published post | B26: =INDEX('Vendor Prices'!$G$5:$G$58,MATCH("postforme-starter",'Vendor Prices'!$A$5:$A$58,0))/INDEX('Vendor Prices'!$F$5:$F$58,MATCH("postforme-starter",'Vendor Prices'!$A$5:$A$58,0)) -> 0.01 | C26: Plan price / posts included. A post to 3 networks counts as 3 (assumed)
A27: Share of KIE renders that fall back to OpenRouter | B27: 0.05 | C27: KIE outage or refusal; fallback is billed at OpenRouter prices
A28: GEO crawl compute per page | B28: ='Vendor Prices'!$G$47 -> 0.0003
A29: Tavily $ per credit | B29: ='Vendor Prices'!$G$37 -> 0.008
A30: Video provider mode (split / openrouter / kie) | B30: split | C30: split = KIE for Veo (Standard, Draft) and Grok (Variation), OpenRouter for Premium, Cinematic, Long take and Studio
A31: Annual billing discount (2 months free) | B31: 0.1667 | C31: Pay 10 months, get 12
A32: Share of customers on annual | B32: 0.3
A33: Target margin: text and research credits | B33: 0.8
A34: Target margin: image credits | B34: 0.75
A35: Target margin: video credits (in packs) | B35: 0.6 | C35: Video market is price-competitive
A36: Backlink margin multiplier (recommended) | B36: 1.75
A37: Blended COGS per general credit | B37: ='Credit Menu'!$K$40 -> 0.0020341557 | C37: From Credit Menu mix
A38: Blended COGS per video credit | B38: ='Video Credits'!$K$19 -> 0.44614618 | C38: From Video Credits mix, active provider
A40: Reasoning tokens per call (estimate; calibrate from metering)
A41: Tier | B41: low | C41: medium | D41: high
A42: PREMIUM | B42: 800 | C42: 3000 | D42: 8000
A43: WORKHORSE | B43: 500 | C43: 1800 | D43: 4000
A44: ECONOMY | B44: 200 | C44: 800 | D44: 1500
A45: Reasoning tokens bill at the output price and count against max_tokens. Opus 5.5 always thinks; Gemini 3.8 Flash thinks unless effort is set low.

Sheet Plans
A1: Plans v2: allowances and unit economics per customer (monthly, USD)
A2: Blue = plan design inputs. Typical = realistic usage. Worst = every allowance maxed at once. Video is its own allowance.
A4: Line | B4: Unit | C4: Free | D4: Starter | E4: Growth | F4: Agency | G4: Scale | H4: Notes
A5: PLAN DESIGN (inputs)
A6: List price, monthly billing | B6: $ / month | C6: 0 | D6: 49 | E6: 149 | F6: 449 | G6: 1199 | H6: v1 draft was $49 / $149 / $399 / $999
A7: Price on annual billing | B7: $ / month | C7: =C6*(1-Inputs!$B$31) -> 0 | D7: =D6*(1-Inputs!$B$31) -> 40.8317 | E7: =E6*(1-Inputs!$B$31) -> 124.1617 | F7: =F6*(1-Inputs!$B$31) -> 374.1517 | G7: =G6*(1-Inputs!$B$31) -> 999.1267
A8: Brands (client workspaces) | B8: count | C8: 1 | D8: 1 | E8: 3 | F8: 10 | G8: 30 | H8: Extra brand add-on $39
A9: Seats | B9: users | C9: 1 | D9: 2 | E9: 5 | F9: 9999 | G9: 9999 | H9: 9999 = unlimited
A10: Mellox credits (non-video AI work) | B10: credits / month | C10: 50 | D10: 2000 | E10: 6000 | F10: 18000 | G10: 50000 | H10: Free = 100 one-time, modeled as 50/month
A11: Video credits (1 VC = one 8s Standard video) | B11: VC / month | C11: 0 | D11: 4 | E11: 12 | F11: 40 | G11: 100 | H11: Separate from credits; packs for more
A12: Mellox Pro (Opus 5.5) chat messages | B12: messages / month | C12: 0 | D12: 30 | E12: 150 | F12: 400 | G12: 1200 | H12: Then 25 credits per message
A13: Mellox Flash chat fair use | B13: messages / month | C13: 30 | D13: 800 | E13: 2000 | F13: 5000 | G13: 12000 | H13: Then 2 credits per message
A14: Mellox Flash chat, typical | B14: messages / month | C14: 20 | D14: 250 | E14: 700 | F14: 2000 | G14: 6000
A15: Tracked AI-visibility prompts (weekly) | B15: prompts | C15: 5 | D15: 25 | E15: 100 | F15: 300 | G15: 1000 | H15: Pooled across brands
A16: Engine: Perplexity (Sonar) | B16: 1 = on | C16: 0 | D16: 1 | E16: 1 | F16: 1 | G16: 1
A17: Engine: 'ChatGPT' (GPT-5.6 Luna) | B17: 1 = on | C17: 1 | D17: 1 | E17: 1 | F17: 1 | G17: 1 | H17: No web search: see Risks
A18: Engine: Gemini (3.8 Flash) | B18: 1 = on | C18: 1 | D18: 1 | E18: 1 | F18: 1 | G18: 1 | H18: No web search: see Risks
A19: Engine: Google AI Overviews (DataForSEO) - add-on | B19: 1 = on | C19: 0 | D19: 0 | E19: 0 | F19: 0 | G19: 0 | H19: $15 add-on per 100 prompts
A20: Checks per prompt per engine | B20: per month | C20: =Inputs!$B$24 -> 4.33 | D20: =Inputs!$B$24 -> 4.33 | E20: =Inputs!$B$24 -> 4.33 | F20: =Inputs!$B$24 -> 4.33 | G20: =Inputs!$B$24 -> 4.33 | H20: Weekly; daily is an add-on
A21: Site scans | B21: per month | C21: 1 | D21: 4 | E21: 10 | F21: 30 | G21: 90
A22: Max pages per scan | B22: pages | C22: 25 | D22: 50 | E22: 150 | F22: 300 | G22: 500
A23: Competitors tracked | B23: count | C23: 0 | D23: 3 | E23: 10 | F23: 30 | G23: 90
A24: Update sweeps per competitor | B24: per month | C24: 0 | D24: 4.33 | E24: 8 | F24: 8 | G24: 8 | H24: About twice a week when active
A25: Market Brain: brands refreshed weekly | B25: count | C25: 0 | D25: 1 | E25: 3 | F25: 10 | G25: 30 | H25: Weekly for every brand on the plan
A26: Market Brain: brands refreshed daily | B26: count | C26: 0 | D26: 0 | E26: 0 | F26: 0 | G26: 0 | H26: Daily is a $29/brand add-on (Opus refresh = $0.25)
A27: Weekly auto Coach briefing (brands) | B27: count | C27: 0 | D27: 1 | E27: 1 | F27: 3 | G27: 10 | H27: The Monday email that brings people back
A28: Social posts a month, typical (each network counts) | B28: posts | C28: 30 | D28: 150 | E28: 450 | F28: 1500 | G28: 4500 | H28: Unlimited on every plan, never uses credits
A29: Social posts a month, fair-use cap (shown as unlimited) | B29: posts | C29: 100 | D29: 500 | E29: 1500 | F29: 5000 | G29: 15000 | H29: Fair-use cap (about 500 posts per brand); worst case uses it
A30: Proof Engine experiments open | B30: count | C30: 0 | D30: 1 | E30: 3 | F30: 15 | G30: 50
A31: Video renders at once | B31: count | C31: 0 | D31: 1 | E31: 2 | F31: 4 | G31: 8 | H31: UGC_MAX_CONCURRENT_RENDERS
A32: Publishing available | B32: 1 = yes | C32: 1 | D32: 1 | E32: 1 | F32: 1 | G32: 1 | H32: Free plan publishes too (unlimited posts)
A33: Background load vs a paid brand | B33: x | C33: 0.25 | D33: 1 | E33: 1 | F33: 1 | G33: 1 | H33: Free brands run no agents or Market Brain
A35: MONTHLY COST TO SERVE (formulas)
A36: Cost of 1 prompt across enabled engines | B36: $ | C36: =C16*'Unit Costs'!$AB$47+C17*'Unit Costs'!$AB$48+C18*'Unit Costs'!$AB$49+C19*'Unit Costs'!$AB$52 -> 0.0098510625 | D36: =D16*'Unit Costs'!$AB$47+D17*'Unit Costs'!$AB$48+D18*'Unit Costs'!$AB$49+D19*'Unit Costs'!$AB$52 -> 0.015917312 | E36: =E16*'Unit Costs'!$AB$47+E17*'Unit Costs'!$AB$48+E18*'Unit Costs'!$AB$49+E19*'Unit Costs'!$AB$52 -> 0.015917312 | F36: =F16*'Unit Costs'!$AB$47+F17*'Unit Costs'!$AB$48+F18*'Unit Costs'!$AB$49+F19*'Unit Costs'!$AB$52 -> 0.015917312 | G36: =G16*'Unit Costs'!$AB$47+G17*'Unit Costs'!$AB$48+G18*'Unit Costs'!$AB$49+G19*'Unit Costs'!$AB$52 -> 0.015917312
A37: AI-visibility prompt tracking | B37: $ | C37: =C15*C36*C20 -> 0.2132755 | D37: =D15*D36*D20 -> 1.7230491 | E37: =E15*E36*E20 -> 6.8921963 | F37: =F15*F36*F20 -> 20.676589 | G37: =G15*G36*G20 -> 68.921963
A38: Site scans | B38: $ | C38: =C21*(C22*Inputs!$B$28+5*Inputs!$B$29) -> 0.0475 | D38: =D21*(D22*Inputs!$B$28+5*Inputs!$B$29) -> 0.22 | E38: =E21*(E22*Inputs!$B$28+5*Inputs!$B$29) -> 0.85 | F38: =F21*(F22*Inputs!$B$28+5*Inputs!$B$29) -> 3.9 | G38: =G21*(G22*Inputs!$B$28+5*Inputs!$B$29) -> 17.1
A39: Competitor tracking | B39: $ | C39: =C23*C24*'Unit Costs'!$AB$43 -> 0 | D39: =D23*D24*'Unit Costs'!$AB$43 -> 0.23889867 | E39: =E23*E24*'Unit Costs'!$AB$43 -> 1.4712774 | F39: =F23*F24*'Unit Costs'!$AB$43 -> 4.4138322 | G39: =G23*G24*'Unit Costs'!$AB$43 -> 13.241497
A40: Market Brain | B40: $ | C40: =(C26*Inputs!$B$25+C25*Inputs!$B$24)*'Unit Costs'!$AB$40 -> 0 | D40: =(D26*Inputs!$B$25+D25*Inputs!$B$24)*'Unit Costs'!$AB$40 -> 1.0540924 | E40: =(E26*Inputs!$B$25+E25*Inputs!$B$24)*'Unit Costs'!$AB$40 -> 3.1622771 | F40: =(F26*Inputs!$B$25+F25*Inputs!$B$24)*'Unit Costs'!$AB$40 -> 10.540924 | G40: =(G26*Inputs!$B$25+G25*Inputs!$B$24)*'Unit Costs'!$AB$40 -> 31.622771
A41: Weekly Coach briefings | B41: $ | C41: =C27*Inputs!$B$24*'Unit Costs'!$AB$38 -> 0 | D41: =D27*Inputs!$B$24*'Unit Costs'!$AB$38 -> 0.84828714 | E41: =E27*Inputs!$B$24*'Unit Costs'!$AB$38 -> 0.84828714 | F41: =F27*Inputs!$B$24*'Unit Costs'!$AB$38 -> 2.5448614 | G41: =G27*Inputs!$B$24*'Unit Costs'!$AB$38 -> 8.4828714
A42: Publishing (typical posts) | B42: $ | C42: =C32*C28*Inputs!$B$26 -> 0.3 | D42: =D32*D28*Inputs!$B$26 -> 1.5 | E42: =E32*E28*Inputs!$B$26 -> 4.5 | F42: =F32*F28*Inputs!$B$26 -> 15 | G42: =G32*G28*Inputs!$B$26 -> 45
A43: Publishing (fair-use cap reached) | B43: $ | C43: =C32*C29*Inputs!$B$26 -> 1 | D43: =D32*D29*Inputs!$B$26 -> 5 | E43: =E32*E29*Inputs!$B$26 -> 15 | F43: =F32*F29*Inputs!$B$26 -> 50 | G43: =G32*G29*Inputs!$B$26 -> 150
A44: Background jobs + storage | B44: $ | C44: =C8*'Unit Costs'!$AB$60*C33 -> 0.1 | D44: =D8*'Unit Costs'!$AB$60*D33 -> 0.4 | E44: =E8*'Unit Costs'!$AB$60*E33 -> 1.2 | F44: =F8*'Unit Costs'!$AB$60*F33 -> 4 | G44: =G8*'Unit Costs'!$AB$60*G33 -> 12
A45: Onboarding (Brand DNA + Brand Kit, over 12 months) | B45: $ | C45: =C8*('Unit Costs'!$AB$24+'Unit Costs'!$AB$25+'Unit Costs'!$AB$26)/12 -> 0.027553172 | D45: =D8*('Unit Costs'!$AB$24+'Unit Costs'!$AB$25+'Unit Costs'!$AB$26)/12 -> 0.027553172 | E45: =E8*('Unit Costs'!$AB$24+'Unit Costs'!$AB$25+'Unit Costs'!$AB$26)/12 -> 0.082659517 | F45: =F8*('Unit Costs'!$AB$24+'Unit Costs'!$AB$25+'Unit Costs'!$AB$26)/12 -> 0.27553172 | G45: =G8*('Unit Costs'!$AB$24+'Unit Costs'!$AB$25+'Unit Costs'!$AB$26)/12 -> 0.82659517
A46: Mellox Flash chat (typical) | B46: $ | C46: =C14*'Unit Costs'!$AB$19 -> 0.17860115 | D46: =D14*'Unit Costs'!$AB$19 -> 2.2325144 | E46: =E14*'Unit Costs'!$AB$19 -> 6.2510403 | F46: =F14*'Unit Costs'!$AB$19 -> 17.860115 | G46: =G14*'Unit Costs'!$AB$19 -> 53.580345
A47: Mellox Flash chat (cap reached) | B47: $ | C47: =C13*'Unit Costs'!$AB$19 -> 0.26790173 | D47: =D13*'Unit Costs'!$AB$19 -> 7.144046 | E47: =E13*'Unit Costs'!$AB$19 -> 17.860115 | F47: =F13*'Unit Costs'!$AB$19 -> 44.650288 | G47: =G13*'Unit Costs'!$AB$19 -> 107.16069
A48: Mellox Pro chat (typical use of allowance) | B48: $ | C48: =C12*Inputs!$B$23*'Unit Costs'!$AB$20 -> 0 | D48: =D12*Inputs!$B$23*'Unit Costs'!$AB$20 -> 0.5787066 | E48: =E12*Inputs!$B$23*'Unit Costs'!$AB$20 -> 2.893533 | F48: =F12*Inputs!$B$23*'Unit Costs'!$AB$20 -> 7.716088 | G48: =G12*Inputs!$B$23*'Unit Costs'!$AB$20 -> 23.148264
A49: Mellox Pro chat (allowance used up) | B49: $ | C49: =C12*'Unit Costs'!$AB$20 -> 0 | D49: =D12*'Unit Costs'!$AB$20 -> 1.4467665 | E49: =E12*'Unit Costs'!$AB$20 -> 7.2338325 | F49: =F12*'Unit Costs'!$AB$20 -> 19.29022 | G49: =G12*'Unit Costs'!$AB$20 -> 57.87066
A50: Included credits (typical use) | B50: $ | C50: =C10*Inputs!$B$21*Inputs!$B$37 -> 0.050853891 | D50: =D10*Inputs!$B$21*Inputs!$B$37 -> 2.0341557 | E50: =E10*Inputs!$B$21*Inputs!$B$37 -> 6.102467 | F50: =F10*Inputs!$B$21*Inputs!$B$37 -> 18.307401 | G50: =G10*Inputs!$B$21*Inputs!$B$37 -> 50.853891
A51: Included credits (all spent) | B51: $ | C51: =C10*Inputs!$B$37 -> 0.10170778 | D51: =D10*Inputs!$B$37 -> 4.0683113 | E51: =E10*Inputs!$B$37 -> 12.204934 | F51: =F10*Inputs!$B$37 -> 36.614802 | G51: =G10*Inputs!$B$37 -> 101.70778
A52: Video credits (typical use) | B52: $ | C52: =C11*Inputs!$B$22*Inputs!$B$38 -> 0 | D52: =D11*Inputs!$B$22*Inputs!$B$38 -> 1.0707508 | E52: =E11*Inputs!$B$22*Inputs!$B$38 -> 3.2122525 | F52: =F11*Inputs!$B$22*Inputs!$B$38 -> 10.707508 | G52: =G11*Inputs!$B$22*Inputs!$B$38 -> 26.768771
A53: Video credits (all spent) | B53: $ | C53: =C11*Inputs!$B$38 -> 0 | D53: =D11*Inputs!$B$38 -> 1.7845847 | E53: =E11*Inputs!$B$38 -> 5.3537542 | F53: =F11*Inputs!$B$38 -> 17.845847 | G53: =G11*Inputs!$B$38 -> 44.614618
A54: COST TO SERVE: typical | B54: $ | C54: =C37+C38+C39+C40+C41+C44+C45+C42+C46+C48+C50+C52 -> 0.91778372 | D54: =D37+D38+D39+D40+D41+D44+D45+D42+D46+D48+D50+D52 -> 11.928008 | E54: =E37+E38+E39+E40+E41+E44+E45+E42+E46+E48+E50+E52 -> 37.46599 | F54: =F37+F38+F39+F40+F41+F44+F45+F42+F46+F48+F50+F52 -> 115.94285 | G54: =G37+G38+G39+G40+G41+G44+G45+G42+G46+G48+G50+G52 -> 351.54697
A55: COST TO SERVE: worst case | B55: $ | C55: =C37+C38+C39+C40+C41+C44+C45+C43+C47+C49+C51+C53 -> 1.7579382 | D55: =D37+D38+D39+D40+D41+D44+D45+D43+D47+D49+D51+D53 -> 23.955589 | E55: =E37+E38+E39+E40+E41+E44+E45+E43+E47+E49+E51+E53 -> 72.159333 | F55: =F37+F38+F39+F40+F41+F44+F45+F43+F47+F49+F51+F53 -> 214.75289 | G55: =G37+G38+G39+G40+G41+G44+G45+G43+G47+G49+G51+G53 -> 613.54945
A57: MARGIN: MONTHLY BILLING
A58: Payment processing (Paddle) | B58: $ | C58: =IF(C6=0,0,C6*Inputs!$B$16+Inputs!$B$17) -> 0 | D58: =IF(D6=0,0,D6*Inputs!$B$16+Inputs!$B$17) -> 2.95 | E58: =IF(E6=0,0,E6*Inputs!$B$16+Inputs!$B$17) -> 7.95 | F58: =IF(F6=0,0,F6*Inputs!$B$16+Inputs!$B$17) -> 22.95 | G58: =IF(G6=0,0,G6*Inputs!$B$16+Inputs!$B$17) -> 60.45
A59: FX payout + export tax | B59: $ | C59: =C6*(Inputs!$B$18+Inputs!$B$19) -> 0 | D59: =D6*(Inputs!$B$18+Inputs!$B$19) -> 1.1025 | E59: =E6*(Inputs!$B$18+Inputs!$B$19) -> 3.3525 | F59: =F6*(Inputs!$B$18+Inputs!$B$19) -> 10.1025 | G59: =G6*(Inputs!$B$18+Inputs!$B$19) -> 26.9775
A60: Contribution: typical | B60: $ | C60: =C6-C54-C58-C59 -> -0.91778372 | D60: =D6-D54-D58-D59 -> 33.019492 | E60: =E6-E54-E58-E59 -> 100.23151 | F60: =F6-F54-F58-F59 -> 300.00465 | G60: =G6-G54-G58-G59 -> 760.02553
A61: Gross margin: typical | B61: % | C61: =IF(C6=0,"n/a",C60/C6) -> n/a | D61: =IF(D6=0,"n/a",D60/D6) -> 0.67386719 | E61: =IF(E6=0,"n/a",E60/E6) -> 0.6726947 | F61: =IF(F6=0,"n/a",F60/F6) -> 0.6681618 | G61: =IF(G6=0,"n/a",G60/G6) -> 0.63388285
A62: Contribution: worst case | B62: $ | C62: =C6-C55-C58-C59 -> -1.7579382 | D62: =D6-D55-D58-D59 -> 20.991911 | E62: =E6-E55-E58-E59 -> 65.538167 | F62: =F6-F55-F58-F59 -> 201.19461 | G62: =G6-G55-G58-G59 -> 498.02305
A63: Gross margin: worst case | B63: % | C63: =IF(C6=0,"n/a",C62/C6) -> n/a | D63: =IF(D6=0,"n/a",D62/D6) -> 0.42840635 | E63: =IF(E6=0,"n/a",E62/E6) -> 0.43985347 | F63: =IF(F6=0,"n/a",F62/F6) -> 0.44809489 | G63: =IF(G6=0,"n/a",G62/G6) -> 0.41536535
A65: MARGIN: ANNUAL BILLING
A66: Contribution: typical | B66: $ / month | C66: =IF(C7=0,-C54,C7-C54-(C7*12*Inputs!$B$16+Inputs!$B$17)/12-C7*(Inputs!$B$18+Inputs!$B$19)) -> -0.91778372 | D66: =IF(D7=0,-D54,D7-D54-(D7*12*Inputs!$B$16+Inputs!$B$17)/12-D7*(Inputs!$B$18+Inputs!$B$19)) -> 25.901727 | E66: =IF(E7=0,-E54,E7-E54-(E7*12*Inputs!$B$16+Inputs!$B$17)/12-E7*(Inputs!$B$18+Inputs!$B$19)) -> 77.65232 | F66: =IF(F7=0,-F54,F7-F54-(F7*12*Inputs!$B$16+Inputs!$B$17)/12-F7*(Inputs!$B$18+Inputs!$B$19)) -> 231.04118 | G66: =IF(G7=0,-G54,G7-G54-(G7*12*Inputs!$B$16+Inputs!$B$17)/12-G7*(Inputs!$B$18+Inputs!$B$19)) -> 575.10138
A67: Gross margin: typical | B67: % | C67: =IF(C7=0,"n/a",C66/C7) -> n/a | D67: =IF(D7=0,"n/a",D66/D7) -> 0.63435339 | E67: =IF(E7=0,"n/a",E66/E7) -> 0.62541283 | F67: =IF(F7=0,"n/a",F66/F7) -> 0.61750671 | G67: =IF(G7=0,"n/a",G66/G7) -> 0.57560405
A69: GUARDRAILS FOR src/server/plans.ts
A70: Safety ceiling: monthlyUsd (all metered spend) | B70: $ / month | C70: =ROUNDUP(C55*1.25,0) -> 3 | D70: =ROUNDUP(D55*1.25,0) -> 30 | E70: =ROUNDUP(E55*1.25,0) -> 91 | F70: =ROUNDUP(F55*1.25,0) -> 269 | G70: =ROUNDUP(G55*1.25,0) -> 767 | H70: Per billing account; add purchased credits/VC on top
A71: Safety ceiling: dailyUsd | B71: $ / day | C71: =MAX(1,ROUNDUP(C70/8,0)) -> 1 | D71: =MAX(1,ROUNDUP(D70/8,0)) -> 4 | E71: =MAX(1,ROUNDUP(E70/8,0)) -> 12 | F71: =MAX(1,ROUNDUP(F70/8,0)) -> 34 | G71: =MAX(1,ROUNDUP(G70/8,0)) -> 96
A72: Typical cost to serve per brand | B72: $ | C72: =C54/C8 -> 0.91778372 | D72: =D54/D8 -> 11.928008 | E72: =E54/E8 -> 12.488663 | F72: =F54/F8 -> 11.594285 | G72: =G54/G8 -> 11.718232
A73: Price per brand | B73: $ | C73: =C6/C8 -> 0 | D73: =D6/D8 -> 49 | E73: =E6/E8 -> 49.666667 | F73: =F6/F8 -> 44.9 | G73: =G6/G8 -> 39.966667

Sheet Feature Matrix
A1: What each plan includes, by module
A2: Included = no extra charge. Credits = paid from the monthly Mellox credits. VC = paid from Video Credits.
A4: Module | B4: Feature | C4: Free | D4: Starter | E4: Growth | F4: Agency | G4: Scale | H4: How it is metered
A5: Brand & onboarding | B5: Brand DNA scan (Opus 5.5) | C5: 1 brand | D5: 1 brand | E5: 3 brands | F5: 10 brands | G5: 30 brands | H5: First scan per brand included; re-scan 125 credits
B6: Brand Kit: visual + voice analysis | C6: - | D6: Yes | E6: Yes | F6: Yes | G6: Yes | H6: Included at onboarding; re-run 45 credits
B7: Assistant memory | C7: Yes | D7: Yes | E7: Yes | F7: Yes | G7: Yes | H7: Included
A8: Mellox Assistant | B8: Mellox Flash chat (Gemini 3.8 Flash) | C8: 30 messages | D8: 800 / month | E8: 2,000 | F8: 5,000 | G8: 12,000 | H8: Fair use, then 2 credits per message
B9: Mellox Pro chat (Claude Opus 5.5) | C9: - | D9: 30 / month | E9: 150 | F9: 400 pooled | G9: 1,200 pooled | H9: Then 25 credits per message
B10: Live web research in chat | C10: - | D10: Yes | E10: Yes | F10: Yes | G10: Yes | H10: Included
B11: File and image understanding | C11: 3 files | D11: Yes | E11: Yes | F11: Yes | G11: Yes | H11: 4 credits per file
A12: Studio | B12: Social posts, image posts, carousels, ads, scripts | C12: - | D12: Yes | E12: Yes | F12: Yes | G12: Yes | H12: Credits (7-30)
B13: Premium articles, GEO-grounded (Opus 5.5) | C13: - | D13: Yes | E13: Yes | F13: Yes | G13: Yes | H13: 100-140 credits
B14: Premium images and image edits | C14: - | D14: Yes | E14: Yes | F14: Yes | G14: Yes | H14: Credits (15-40)
B15: Campaign plans | C15: - | D15: - | E15: Yes | F15: Yes | G15: Yes | H15: 55 credits
B16: Content calendar and scheduling | C16: Yes | D16: Yes | E16: Yes | F16: Yes | G16: Yes | H16: Included
B17: Approval workflows | C17: - | D17: - | E17: Yes | F17: Yes | G17: Yes | H17: Included
A18: UGC video ads | B18: UGC concepts, hooks and scripts | C18: - | D18: Yes | E18: Yes | F18: Yes | G18: Yes | H18: 25 credits
B19: Video credits per month | C19: - | D19: 4 | E19: 12 | F19: 40 pooled | G19: 100 pooled | H19: Video Packs for more; never paid with general credits
B20: Draft and Standard video, 720p | C20: - | D20: Yes | E20: Yes | F20: Yes | G20: Yes | H20: 0.5 / 1 VC
B21: 1080p, Premium and Long-take video | C21: - | D21: - | E21: Yes | F21: Yes | G21: Yes | H21: 0.75-2 VC
B22: Cinematic multi-shot video | C22: - | D22: - | E22: - | F22: Yes | G22: Yes | H22: 2 VC
B23: Renders at the same time | C23: - | D23: 1 | E23: 2 | F23: 4 | G23: 8 | H23: Concurrency limit
A24: AI Visibility | B24: Tracked prompts, checked weekly | C24: 5 | D24: 25 | E24: 100 | F24: 300 pooled | G24: 1,000 pooled | H24: +100 prompts $39; daily tracking add-on
B25: Answer engines | C25: ChatGPT, Gemini | D25: + Perplexity | E25: 3 engines | F25: 3 engines | G25: 3 engines | H25: Google AI Overviews add-on $15 / 100 prompts
B26: Site scans per month (max pages) | C26: 1 (25) | D26: 4 (50) | E26: 10 (150) | F26: 30 (300) | G26: 90 (500) | H26: Extra scan 35 credits per 100 pages
B27: Findings, scores, readiness dashboard | C27: Yes | D27: Yes | E27: Yes | F27: Yes | G27: Yes | H27: Included
B28: GEO fix proposals | C28: View findings | D28: Yes | E28: Yes | F28: Yes | G28: Yes | H28: 150 credits per finding
B29: CMS fixes (WordPress, Webflow) | C29: - | D29: - | E29: Yes | F29: Yes | G29: Yes | H29: 55 credits
B30: GitHub PR fixes + GEO Engineer agent | C30: - | D30: - | E30: - | F30: Yes | G30: Yes | H30: 800 credits per run
B31: Verification rescans after fixes | C31: - | D31: Yes | E31: Yes | F31: Yes | G31: Yes | H31: Included
B32: Proof Engine experiments open | C32: - | D32: 1 | E32: 3 | F32: 15 | G32: 50 | H32: 70 credits each
A33: Intelligence | B33: Weekly Marketing Coach briefing (auto) | C33: - | D33: 1 brand | E33: 1 brand | F33: 3 brands | G33: 10 brands | H33: On-demand briefing 100 credits
B34: Market Brain market updates | C34: - | D34: Weekly, 1 brand | E34: Weekly, 3 | F34: Weekly, 10 | G34: Weekly, 30 | H34: Daily add-on $29 per brand
B35: Competitors tracked | C35: - | D35: 3 | E35: 10 | F35: 30 | G35: 90 | H35: Discovery 25 credits
B36: Competitor intelligence reports | C36: - | D36: Yes | E36: Yes | F36: Yes | G36: Yes | H36: 30 credits
B37: GA4 and Search Console insights | C37: - | D37: Yes | E37: Yes | F37: Yes | G37: Yes | H37: Included
A38: Distribution | B38: Social publishing (all networks, unlimited accounts) | C38: Unlimited posts | D38: Unlimited | E38: Unlimited | F38: Unlimited | G38: Unlimited | H38: Never uses credits; fair use
B39: WordPress and Webflow publishing | C39: - | D39: Yes | E39: Yes | F39: Yes | G39: Yes | H39: Included
B40: Backlink marketplace | C40: - | D40: - | E40: Yes | F40: Yes | G40: Yes | H40: Provider price x 1.75
A41: Team & agency | B41: Seats | C41: 1 | D41: 2 | E41: 5 | F41: Unlimited | G41: Unlimited | H41: +$15 per seat
B42: Client portal and share links | C42: - | D42: - | E42: Yes | F42: Yes | G42: Yes | H42: Included
B43: Agency command center, white-label | C43: - | D43: - | E43: - | F43: Yes | G43: Yes | H43: Included; white-label domain $49
B44: Pooled credits and VC across brands | C44: - | D44: - | E44: Yes | F44: Yes | G44: Yes | H44: Included
B45: SSO, API access, SLA | C45: - | D45: - | E45: - | F45: - | G45: Yes | H45: Included
A46: Retention | B46: Credit and VC rollover | C46: - | D46: - | E46: Annual plans | F46: Annual plans | G46: Annual plans | H46: Up to 1 month of allowance
B47: Pause plan instead of cancel ($9 / month) | C47: - | D47: Yes | E47: Yes | F47: Yes | G47: Yes | H47: Keeps data + 10 weekly prompts
A48: Support | B48: Support | C48: Community | D48: Email | E48: Email, 24 h | F48: Priority + onboarding call | G48: Dedicated manager

Sheet Credit Menu
A1: Mellox Credits: price list for non-video AI work (1 credit = $0.01)
A2: Video is NOT paid with these credits: it has its own Video Credits (next tab). Blue = credits charged. Status flags anything below target margin.
A4: Action (what the customer sees) | B4: Unit | C4: COGS ($) | D4: Credits | E4: List price ($) | F4: Margin | G4: Target | H4: Status | I4: Credits for target | J4: Expected share of use | K4: COGS per credit ($) | L4: Unit cost ID | M4: Change vs v1 (credits)
A5: Social post set (up to 3 platforms) | B5: per job | C5: ='Unit Costs'!$AB$27 -> 0.022781479 | D5: 12 | E5: =D5*Inputs!$B$6 -> 0.12 | F5: =IF(E5=0,"included",1-C5/E5) -> 0.81015434 | G5: =Inputs!$B$33 -> 0.8 | H5: =IF(D5=0,"Included (fair use)",IF(F5>=G5-0.025,"OK","RAISE")) -> OK | I5: =ROUNDUP(C5/(1-G5)/Inputs!$B$6,0) -> 12 | J5: 0.12 | K5: =IF(D5=0,0,C5/D5) -> 0.0018984566 | L5: post_set | M5: 8
A6: Image post (copy + image) | B6: per job | C6: ='Unit Costs'!$AB$28 -> 0.066162415 | D6: 30 | E6: =D6*Inputs!$B$6 -> 0.3 | F6: =IF(E6=0,"included",1-C6/E6) -> 0.77945862 | G6: =Inputs!$B$34 -> 0.75 | H6: =IF(D6=0,"Included (fair use)",IF(F6>=G6-0.025,"OK","RAISE")) -> OK | I6: =ROUNDUP(C6/(1-G6)/Inputs!$B$6,0) -> 27 | J6: 0.16 | K6: =IF(D6=0,0,C6/D6) -> 0.0022054138 | L6: image_post | M6: 20
A7: Carousel | B7: per job | C7: ='Unit Costs'!$AB$29 -> 0.059909562 | D7: 30 | E7: =D7*Inputs!$B$6 -> 0.3 | F7: =IF(E7=0,"included",1-C7/E7) -> 0.80030146 | G7: =Inputs!$B$34 -> 0.75 | H7: =IF(D7=0,"Included (fair use)",IF(F7>=G7-0.025,"OK","RAISE")) -> OK | I7: =ROUNDUP(C7/(1-G7)/Inputs!$B$6,0) -> 24 | J7: 0.04 | K7: =IF(D7=0,0,C7/D7) -> 0.0019969854 | L7: carousel | M7: 20
A8: Ad set (copy + image) | B8: per job | C8: ='Unit Costs'!$AB$30 -> 0.058053923 | D8: 30 | E8: =D8*Inputs!$B$6 -> 0.3 | F8: =IF(E8=0,"included",1-C8/E8) -> 0.80648692 | G8: =Inputs!$B$34 -> 0.75 | H8: =IF(D8=0,"Included (fair use)",IF(F8>=G8-0.025,"OK","RAISE")) -> OK | I8: =ROUNDUP(C8/(1-G8)/Inputs!$B$6,0) -> 24 | J8: 0.05 | K8: =IF(D8=0,0,C8/D8) -> 0.0019351308 | L8: ad_set | M8: 20
A9: Premium article (~1,200 words, GEO-grounded) | B9: per article | C9: ='Unit Costs'!$AB$31 -> 0.19315557 | D9: 100 | E9: =D9*Inputs!$B$6 -> 1 | F9: =IF(E9=0,"included",1-C9/E9) -> 0.80684443 | G9: =Inputs!$B$33 -> 0.8 | H9: =IF(D9=0,"Included (fair use)",IF(F9>=G9-0.025,"OK","RAISE")) -> OK | I9: =ROUNDUP(C9/(1-G9)/Inputs!$B$6,0) -> 97 | J9: 0.06 | K9: =IF(D9=0,0,C9/D9) -> 0.0019315557 | L9: article | M9: 15
A10: Long-form article (~2,500 words) | B10: per article | C10: ='Unit Costs'!$AB$32 -> 0.27341737 | D10: 140 | E10: =D10*Inputs!$B$6 -> 1.4 | F10: =IF(E10=0,"included",1-C10/E10) -> 0.80470188 | G10: =Inputs!$B$33 -> 0.8 | H10: =IF(D10=0,"Included (fair use)",IF(F10>=G10-0.025,"OK","RAISE")) -> OK | I10: =ROUNDUP(C10/(1-G10)/Inputs!$B$6,0) -> 137 | J10: 0.02 | K10: =IF(D10=0,0,C10/D10) -> 0.0019529812 | L10: article_long | M10: 25
A11: Standard article (proposed WORKHORSE tier) | B11: per article | C11: ='Unit Costs'!$AB$33 -> 0.031421909 | D11: 20 | E11: =D11*Inputs!$B$6 -> 0.2 | F11: =IF(E11=0,"included",1-C11/E11) -> 0.84289045 | G11: =Inputs!$B$33 -> 0.8 | H11: =IF(D11=0,"Included (fair use)",IF(F11>=G11-0.025,"OK","RAISE")) -> OK | I11: =ROUNDUP(C11/(1-G11)/Inputs!$B$6,0) -> 16 | J11: 0 | K11: =IF(D11=0,0,C11/D11) -> 0.0015710955 | L11: article_std | M11: new
A12: Video script | B12: per script | C12: ='Unit Costs'!$AB$34 -> 0.020813277 | D12: 10 | E12: =D12*Inputs!$B$6 -> 0.1 | F12: =IF(E12=0,"included",1-C12/E12) -> 0.79186723 | G12: =Inputs!$B$33 -> 0.8 | H12: =IF(D12=0,"Included (fair use)",IF(F12>=G12-0.025,"OK","RAISE")) -> OK | I12: =ROUNDUP(C12/(1-G12)/Inputs!$B$6,0) -> 11 | J12: 0.02 | K12: =IF(D12=0,0,C12/D12) -> 0.0020813277 | L12: script | M12: 6
A13: Content ideas batch | B13: per batch | C13: ='Unit Costs'!$AB$35 -> 0.014282062 | D13: 7 | E13: =D13*Inputs!$B$6 -> 0.07 | F13: =IF(E13=0,"included",1-C13/E13) -> 0.79597054 | G13: =Inputs!$B$33 -> 0.8 | H13: =IF(D13=0,"Included (fair use)",IF(F13>=G13-0.025,"OK","RAISE")) -> OK | I13: =ROUNDUP(C13/(1-G13)/Inputs!$B$6,0) -> 8 | J13: 0.02 | K13: =IF(D13=0,0,C13/D13) -> 0.0020402946 | L13: ideas | M13: new
A14: Multi-platform variants (5 platforms) | B14: per job | C14: ='Unit Costs'!$AB$36 -> 0.018933821 | D14: 10 | E14: =D14*Inputs!$B$6 -> 0.1 | F14: =IF(E14=0,"included",1-C14/E14) -> 0.81066179 | G14: =Inputs!$B$33 -> 0.8 | H14: =IF(D14=0,"Included (fair use)",IF(F14>=G14-0.025,"OK","RAISE")) -> OK | I14: =ROUNDUP(C14/(1-G14)/Inputs!$B$6,0) -> 10 | J14: 0.02 | K14: =IF(D14=0,0,C14/D14) -> 0.0018933821 | L14: social_multi | M14: new
A15: Standard image | B15: per image | C15: ='Unit Costs'!$AB$16 -> 0.036783699 | D15: 15 | E15: =D15*Inputs!$B$6 -> 0.15 | F15: =IF(E15=0,"included",1-C15/E15) -> 0.75477534 | G15: =Inputs!$B$34 -> 0.75 | H15: =IF(D15=0,"Included (fair use)",IF(F15>=G15-0.025,"OK","RAISE")) -> OK | I15: =ROUNDUP(C15/(1-G15)/Inputs!$B$6,0) -> 15 | J15: 0.05 | K15: =IF(D15=0,0,C15/D15) -> 0.0024522466 | L15: img_std | M15: 12
A16: Premium image | B16: per image | C16: ='Unit Costs'!$AB$17 -> 0.086157699 | D16: 40 | E16: =D16*Inputs!$B$6 -> 0.4 | F16: =IF(E16=0,"included",1-C16/E16) -> 0.78460575 | G16: =Inputs!$B$34 -> 0.75 | H16: =IF(D16=0,"Included (fair use)",IF(F16>=G16-0.025,"OK","RAISE")) -> OK | I16: =ROUNDUP(C16/(1-G16)/Inputs!$B$6,0) -> 35 | J16: 0.03 | K16: =IF(D16=0,0,C16/D16) -> 0.0021539425 | L16: img_prem | M16: 30
A17: Image edit (up to 2 references) | B17: per edit | C17: ='Unit Costs'!$AB$18 -> 0.050239153 | D17: 20 | E17: =D17*Inputs!$B$6 -> 0.2 | F17: =IF(E17=0,"included",1-C17/E17) -> 0.74880424 | G17: =Inputs!$B$34 -> 0.75 | H17: =IF(D17=0,"Included (fair use)",IF(F17>=G17-0.025,"OK","RAISE")) -> OK | I17: =ROUNDUP(C17/(1-G17)/Inputs!$B$6,0) -> 21 | J17: 0.02 | K17: =IF(D17=0,0,C17/D17) -> 0.0025119576 | L17: img_edit | M17: new
A18: Campaign plan | B18: per plan | C18: ='Unit Costs'!$AB$37 -> 0.10645082 | D18: 55 | E18: =D18*Inputs!$B$6 -> 0.55 | F18: =IF(E18=0,"included",1-C18/E18) -> 0.80645306 | G18: =Inputs!$B$33 -> 0.8 | H18: =IF(D18=0,"Included (fair use)",IF(F18>=G18-0.025,"OK","RAISE")) -> OK | I18: =ROUNDUP(C18/(1-G18)/Inputs!$B$6,0) -> 54 | J18: 0.02 | K18: =IF(D18=0,0,C18/D18) -> 0.0019354694 | L18: campaign | M18: 20
A19: Brand DNA re-scan (first scan per brand free) | B19: per scan | C19: ='Unit Costs'!$AB$24 -> 0.23438541 | D19: 125 | E19: =D19*Inputs!$B$6 -> 1.25 | F19: =IF(E19=0,"included",1-C19/E19) -> 0.81249167 | G19: =Inputs!$B$33 -> 0.8 | H19: =IF(D19=0,"Included (fair use)",IF(F19>=G19-0.025,"OK","RAISE")) -> OK | I19: =ROUNDUP(C19/(1-G19)/Inputs!$B$6,0) -> 118 | J19: 0.01 | K19: =IF(D19=0,0,C19/D19) -> 0.0018750833 | L19: brand_dna | M19: 40
A20: Brand voice re-analysis | B20: per run | C20: ='Unit Costs'!$AB$25 -> 0.082795081 | D20: 45 | E20: =D20*Inputs!$B$6 -> 0.45 | F20: =IF(E20=0,"included",1-C20/E20) -> 0.81601093 | G20: =Inputs!$B$33 -> 0.8 | H20: =IF(D20=0,"Included (fair use)",IF(F20>=G20-0.025,"OK","RAISE")) -> OK | I20: =ROUNDUP(C20/(1-G20)/Inputs!$B$6,0) -> 42 | J20: 0.005 | K20: =IF(D20=0,0,C20/D20) -> 0.0018398907 | L20: brand_writing | M20: new
A21: File / image extraction | B21: per file | C21: ='Unit Costs'!$AB$23 -> 0.0077876935 | D21: 4 | E21: =D21*Inputs!$B$6 -> 0.04 | F21: =IF(E21=0,"included",1-C21/E21) -> 0.80530766 | G21: =Inputs!$B$33 -> 0.8 | H21: =IF(D21=0,"Included (fair use)",IF(F21>=G21-0.025,"OK","RAISE")) -> OK | I21: =ROUNDUP(C21/(1-G21)/Inputs!$B$6,0) -> 4 | J21: 0.01 | K21: =IF(D21=0,0,C21/D21) -> 0.0019469234 | L21: file_extract | M21: 10
A22: Marketing Coach briefing (on demand) | B22: per briefing | C22: ='Unit Costs'!$AB$38 -> 0.19590927 | D22: 100 | E22: =D22*Inputs!$B$6 -> 1 | F22: =IF(E22=0,"included",1-C22/E22) -> 0.80409073 | G22: =Inputs!$B$33 -> 0.8 | H22: =IF(D22=0,"Included (fair use)",IF(F22>=G22-0.025,"OK","RAISE")) -> OK | I22: =ROUNDUP(C22/(1-G22)/Inputs!$B$6,0) -> 98 | J22: 0.04 | K22: =IF(D22=0,0,C22/D22) -> 0.0019590927 | L22: coach | M22: 50
A23: Deep strategy (Coach, high effort) | B23: per run | C23: ='Unit Costs'!$AB$39 -> 0.37474665 | D23: 200 | E23: =D23*Inputs!$B$6 -> 2 | F23: =IF(E23=0,"included",1-C23/E23) -> 0.81262668 | G23: =Inputs!$B$33 -> 0.8 | H23: =IF(D23=0,"Included (fair use)",IF(F23>=G23-0.025,"OK","RAISE")) -> OK | I23: =ROUNDUP(C23/(1-G23)/Inputs!$B$6,0) -> 188 | J23: 0.02 | K23: =IF(D23=0,0,C23/D23) -> 0.0018737332 | L23: coach_deep | M23: 150
A24: Market Brain manual refresh | B24: per refresh | C24: ='Unit Costs'!$AB$40 -> 0.24343934 | D24: 125 | E24: =D24*Inputs!$B$6 -> 1.25 | F24: =IF(E24=0,"included",1-C24/E24) -> 0.80524853 | G24: =Inputs!$B$33 -> 0.8 | H24: =IF(D24=0,"Included (fair use)",IF(F24>=G24-0.025,"OK","RAISE")) -> OK | I24: =ROUNDUP(C24/(1-G24)/Inputs!$B$6,0) -> 122 | J24: 0.02 | K24: =IF(D24=0,0,C24/D24) -> 0.0019475147 | L24: market_brain | M24: 60
A25: Competitor discovery | B25: per run | C25: ='Unit Costs'!$AB$41 -> 0.051391164 | D25: 25 | E25: =D25*Inputs!$B$6 -> 0.25 | F25: =IF(E25=0,"included",1-C25/E25) -> 0.79443535 | G25: =Inputs!$B$33 -> 0.8 | H25: =IF(D25=0,"Included (fair use)",IF(F25>=G25-0.025,"OK","RAISE")) -> OK | I25: =ROUNDUP(C25/(1-G25)/Inputs!$B$6,0) -> 26 | J25: 0.01 | K25: =IF(D25=0,0,C25/D25) -> 0.0020556465 | L25: comp_disc | M25: 40
A26: Competitor profile | B26: per competitor | C26: ='Unit Costs'!$AB$42 -> 0.030697469 | D26: 15 | E26: =D26*Inputs!$B$6 -> 0.15 | F26: =IF(E26=0,"included",1-C26/E26) -> 0.79535021 | G26: =Inputs!$B$33 -> 0.8 | H26: =IF(D26=0,"Included (fair use)",IF(F26>=G26-0.025,"OK","RAISE")) -> OK | I26: =ROUNDUP(C26/(1-G26)/Inputs!$B$6,0) -> 16 | J26: 0.01 | K26: =IF(D26=0,0,C26/D26) -> 0.0020464979 | L26: comp_profile | M26: 25
A27: Competitor intelligence report | B27: per report | C27: ='Unit Costs'!$AB$44 -> 0.056768828 | D27: 30 | E27: =D27*Inputs!$B$6 -> 0.3 | F27: =IF(E27=0,"included",1-C27/E27) -> 0.81077058 | G27: =Inputs!$B$33 -> 0.8 | H27: =IF(D27=0,"Included (fair use)",IF(F27>=G27-0.025,"OK","RAISE")) -> OK | I27: =ROUNDUP(C27/(1-G27)/Inputs!$B$6,0) -> 29 | J27: 0.01 | K27: =IF(D27=0,0,C27/D27) -> 0.0018922942 | L27: comp_intel | M27: 50
A28: Analytics insight refresh (on demand) | B28: per refresh | C28: ='Unit Costs'!$AB$45 -> 0.01680615 | D28: 8 | E28: =D28*Inputs!$B$6 -> 0.08 | F28: =IF(E28=0,"included",1-C28/E28) -> 0.78992312 | G28: =Inputs!$B$33 -> 0.8 | H28: =IF(D28=0,"Included (fair use)",IF(F28>=G28-0.025,"OK","RAISE")) -> OK | I28: =ROUNDUP(C28/(1-G28)/Inputs!$B$6,0) -> 9 | J28: 0.01 | K28: =IF(D28=0,0,C28/D28) -> 0.0021007687 | L28: insights | M28: new
A29: Extra site scan | B29: per 100 pages | C29: ='Unit Costs'!$AB$46 -> 0.07 | D29: 35 | E29: =D29*Inputs!$B$6 -> 0.35 | F29: =IF(E29=0,"included",1-C29/E29) -> 0.8 | G29: =Inputs!$B$33 -> 0.8 | H29: =IF(D29=0,"Included (fair use)",IF(F29>=G29-0.025,"OK","RAISE")) -> OK | I29: =ROUNDUP(C29/(1-G29)/Inputs!$B$6,0) -> 35 | J29: 0.01 | K29: =IF(D29=0,0,C29/D29) -> 0.002 | L29: site_scan | M29: 35
A30: Extra prompt check (3 engines) | B30: per prompt | C30: ='Unit Costs'!$AB$50 -> 0.015917312 | D30: 8 | E30: =D30*Inputs!$B$6 -> 0.08 | F30: =IF(E30=0,"included",1-C30/E30) -> 0.80103359 | G30: =Inputs!$B$33 -> 0.8 | H30: =IF(D30=0,"Included (fair use)",IF(F30>=G30-0.025,"OK","RAISE")) -> OK | I30: =ROUNDUP(C30/(1-G30)/Inputs!$B$6,0) -> 8 | J30: 0.02 | K30: =IF(D30=0,0,C30/D30) -> 0.0019896641 | L30: probe_set | M30: new
A31: GEO fix proposal | B31: per finding | C31: ='Unit Costs'!$AB$53 -> 0.28623442 | D31: 150 | E31: =D31*Inputs!$B$6 -> 1.5 | F31: =IF(E31=0,"included",1-C31/E31) -> 0.80917705 | G31: =Inputs!$B$33 -> 0.8 | H31: =IF(D31=0,"Included (fair use)",IF(F31>=G31-0.025,"OK","RAISE")) -> OK | I31: =ROUNDUP(C31/(1-G31)/Inputs!$B$6,0) -> 144 | J31: 0.06 | K31: =IF(D31=0,0,C31/D31) -> 0.0019082295 | L31: geo_fix | M31: 50
A32: GEO CMS fix (WordPress / Webflow) | B32: per fix | C32: ='Unit Costs'!$AB$54 -> 0.10706053 | D32: 55 | E32: =D32*Inputs!$B$6 -> 0.55 | F32: =IF(E32=0,"included",1-C32/E32) -> 0.80534449 | G32: =Inputs!$B$33 -> 0.8 | H32: =IF(D32=0,"Included (fair use)",IF(F32>=G32-0.025,"OK","RAISE")) -> OK | I32: =ROUNDUP(C32/(1-G32)/Inputs!$B$6,0) -> 54 | J32: 0.03 | K32: =IF(D32=0,0,C32/D32) -> 0.0019465551 | L32: geo_cms | M32: 60
A33: GEO Engineer agent run (GitHub PR) | B33: per run | C33: ='Unit Costs'!$AB$55 -> 1.6 | D33: 800 | E33: =D33*Inputs!$B$6 -> 8 | F33: =IF(E33=0,"included",1-C33/E33) -> 0.8 | G33: =Inputs!$B$33 -> 0.8 | H33: =IF(D33=0,"Included (fair use)",IF(F33>=G33-0.025,"OK","RAISE")) -> OK | I33: =ROUNDUP(C33/(1-G33)/Inputs!$B$6,0) -> 800 | J33: 0.03 | K33: =IF(D33=0,0,C33/D33) -> 0.002 | L33: geo_agent | M33: 400
A34: Proof Engine experiment | B34: per experiment | C34: ='Unit Costs'!$AB$56 -> 0.14362084 | D34: 70 | E34: =D34*Inputs!$B$6 -> 0.7 | F34: =IF(E34=0,"included",1-C34/E34) -> 0.79482737 | G34: =Inputs!$B$33 -> 0.8 | H34: =IF(D34=0,"Included (fair use)",IF(F34>=G34-0.025,"OK","RAISE")) -> OK | I34: =ROUNDUP(C34/(1-G34)/Inputs!$B$6,0) -> 72 | J34: 0.01 | K34: =IF(D34=0,0,C34/D34) -> 0.0020517263 | L34: experiment | M34: 80
A35: UGC concept pack (scripts and hooks) | B35: per product | C35: ='Unit Costs'!$AB$57 -> 0.051274582 | D35: 25 | E35: =D35*Inputs!$B$6 -> 0.25 | F35: =IF(E35=0,"included",1-C35/E35) -> 0.79490167 | G35: =Inputs!$B$33 -> 0.8 | H35: =IF(D35=0,"Included (fair use)",IF(F35>=G35-0.025,"OK","RAISE")) -> OK | I35: =ROUNDUP(C35/(1-G35)/Inputs!$B$6,0) -> 26 | J35: 0.03 | K35: =IF(D35=0,0,C35/D35) -> 0.0020509833 | L35: ugc_concepts | M35: 50
A36: Mellox Pro message (after the plan allowance) | B36: per message | C36: ='Unit Costs'!$AB$20 -> 0.04822555 | D36: 25 | E36: =D36*Inputs!$B$6 -> 0.25 | F36: =IF(E36=0,"included",1-C36/E36) -> 0.8070978 | G36: =Inputs!$B$33 -> 0.8 | H36: =IF(D36=0,"Included (fair use)",IF(F36>=G36-0.025,"OK","RAISE")) -> OK | I36: =ROUNDUP(C36/(1-G36)/Inputs!$B$6,0) -> 25 | J36: 0.035 | K36: =IF(D36=0,0,C36/D36) -> 0.001929022 | L36: chat_pro | M36: new
A37: Chat with Mellox Flash | B37: per message | C37: ='Unit Costs'!$AB$19 -> 0.0089300575 | D37: 0 | E37: =D37*Inputs!$B$6 -> 0 | F37: =IF(E37=0,"included",1-C37/E37) -> included | G37: =Inputs!$B$33 -> 0.8 | H37: =IF(D37=0,"Included (fair use)",IF(F37>=G37-0.025,"OK","RAISE")) -> Included (fair use) | I37: =ROUNDUP(C37/(1-G37)/Inputs!$B$6,0) -> 5 | J37: 0 | K37: =IF(D37=0,0,C37/D37) -> 0 | L37: chat_flash | M37: 0
A38: Backlink research (10 sites) | B38: per search | C38: ='Unit Costs'!$AB$58 -> 0.030085699 | D38: 0 | E38: =D38*Inputs!$B$6 -> 0 | F38: =IF(E38=0,"included",1-C38/E38) -> included | G38: =Inputs!$B$33 -> 0.8 | H38: =IF(D38=0,"Included (fair use)",IF(F38>=G38-0.025,"OK","RAISE")) -> Included (fair use) | I38: =ROUNDUP(C38/(1-G38)/Inputs!$B$6,0) -> 16 | J38: 0 | K38: =IF(D38=0,0,C38/D38) -> 0 | L38: link_research | M38: 0
A40: Blended COGS per credit (weighted by expected use) | K40: =SUMPRODUCT(J5:J38,K5:K38)/SUM(J5:J38) -> 0.0020341557
A41: Blended margin at face value | K41: =1-K40/Inputs!$B$6 -> 0.79658443
A42: Check: shares sum to | J42: =SUM(J5:J38) -> 1

Sheet Video Credits
A1: Video Credits: a separate allowance so video can never drain the plan
A2: 1 Video Credit (VC) = one 8-second Standard video. KIE runs Veo and Grok for now; OpenRouter runs the rest and is the fallback. Mode is on Inputs.
A4: Option (what the customer sees) | B4: UGC key | C4: Seconds | D4: Resolution | E4: OpenRouter model | F4: OpenRouter cost ($, incl. fee) | G4: KIE model | H4: KIE cost ($) | I4: Cost, active provider ($) | J4: Video credits charged | K4: Cost per VC ($) | L4: Expected share of VC use | M4: Plans that can use it | N4: Provider now (split mode)
A5: Draft (Veo 3.1 Lite) 720p | B5: draft | C5: 8 | D5: 720p | E5: google/veo-3.1-lite | F5: =C5*'Vendor Prices'!$G$17*(1+Inputs!$B$7) -> 0.422 | G5: veo3_lite | H5: ='Vendor Prices'!$G$29 -> 0.15 | I5: =IF(OR(Inputs!$B$30="kie",AND(Inputs!$B$30="split",N5="kie")),(1-Inputs!$B$27)*H5+Inputs!$B$27*F5,F5) -> 0.1636 | J5: 0.5 | K5: =I5/J5 -> 0.3272 | L5: 0.14 | M5: All paid plans | N5: kie
A6: Draft (Veo 3.1 Lite) 1080p | B6: draft | C6: 8 | D6: 1080p | E6: google/veo-3.1-lite | F6: =C6*'Vendor Prices'!$G$18*(1+Inputs!$B$7) -> 0.6752 | G6: veo3_lite | H6: ='Vendor Prices'!$G$30 -> 0.175 | I6: =IF(OR(Inputs!$B$30="kie",AND(Inputs!$B$30="split",N6="kie")),(1-Inputs!$B$27)*H6+Inputs!$B$27*F6,F6) -> 0.20001 | J6: 0.75 | K6: =I6/J6 -> 0.26668 | L6: 0.03 | M6: Growth+ | N6: kie
A7: Standard (Veo 3.1 Fast) 720p | B7: standard | C7: 8 | D7: 720p | E7: google/veo-3.1-fast | F7: =C7*'Vendor Prices'!$G$15*(1+Inputs!$B$7) -> 0.844 | G7: veo3_fast | H7: ='Vendor Prices'!$G$27 -> 0.3 | I7: =IF(OR(Inputs!$B$30="kie",AND(Inputs!$B$30="split",N7="kie")),(1-Inputs!$B$27)*H7+Inputs!$B$27*F7,F7) -> 0.3272 | J7: 1 | K7: =I7/J7 -> 0.3272 | L7: 0.4 | M7: All paid plans | N7: kie
A8: Standard (Veo 3.1 Fast) 1080p | B8: standard | C8: 8 | D8: 1080p | E8: google/veo-3.1-fast | F8: =C8*'Vendor Prices'!$G$16*(1+Inputs!$B$7) -> 1.0128 | G8: veo3_fast | H8: ='Vendor Prices'!$G$28 -> 0.325 | I8: =IF(OR(Inputs!$B$30="kie",AND(Inputs!$B$30="split",N8="kie")),(1-Inputs!$B$27)*H8+Inputs!$B$27*F8,F8) -> 0.35939 | J8: 1.25 | K8: =I8/J8 -> 0.287512 | L8: 0.1 | M8: Growth+ | N8: kie
A9: Premium (Hailuo 3 / Gemini Omni), 8s, 2 photos | B9: premium | C9: 8 | D9: 2K / 1080p | E9: minimax/hailuo-3 | F9: =(C9*'Vendor Prices'!$G$19+2*'Vendor Prices'!$G$20)*(1+Inputs!$B$7) -> 1.1816 | G9: gemini-omni-flash-1-1 | H9: =C9*'Vendor Prices'!$G$35 -> 0.8 | I9: =IF(OR(Inputs!$B$30="kie",AND(Inputs!$B$30="split",N9="kie")),(1-Inputs!$B$27)*H9+Inputs!$B$27*F9,F9) -> 1.1816 | J9: 1.5 | K9: =I9/J9 -> 0.78773333 | L9: 0.1 | M9: Growth+ | N9: openrouter
A10: Premium, 10s, 2 photos | B10: premium | C10: 10 | D10: 2K / 1080p | E10: minimax/hailuo-3 | F10: =(C10*'Vendor Prices'!$G$19+2*'Vendor Prices'!$G$20)*(1+Inputs!$B$7) -> 1.4559 | G10: gemini-omni-flash-1-1 | H10: =C10*'Vendor Prices'!$G$35 -> 1 | I10: =IF(OR(Inputs!$B$30="kie",AND(Inputs!$B$30="split",N10="kie")),(1-Inputs!$B$27)*H10+Inputs!$B$27*F10,F10) -> 1.4559 | J10: 2 | K10: =I10/J10 -> 0.72795 | L10: 0.04 | M10: Growth+ | N10: openrouter
A11: Cinematic (Hailuo 3 / MiniMax H3), 10s | B11: cinematic | C11: 10 | D11: 2K | E11: minimax/hailuo-3 | F11: =(C11*'Vendor Prices'!$G$19+2*'Vendor Prices'!$G$20)*(1+Inputs!$B$7) -> 1.4559 | G11: minimax-h3 | H11: =C11*'Vendor Prices'!$G$36 -> 0.5 | I11: =IF(OR(Inputs!$B$30="kie",AND(Inputs!$B$30="split",N11="kie")),(1-Inputs!$B$27)*H11+Inputs!$B$27*F11,F11) -> 1.4559 | J11: 2 | K11: =I11/J11 -> 0.72795 | L11: 0.04 | M11: Agency+ | N11: openrouter
A12: Long take (Seedance 2.0 Fast), 12s 720p | B12: long | C12: 12 | D12: 720p | E12: bytedance/seedance-2.0-fast | F12: =C12*'Vendor Prices'!$G$22*(1+Inputs!$B$7) -> 1.1485152 | G12: seedance-2-fast | H12: =C12*'Vendor Prices'!$G$32 -> 1.488 | I12: =IF(OR(Inputs!$B$30="kie",AND(Inputs!$B$30="split",N12="kie")),(1-Inputs!$B$27)*H12+Inputs!$B$27*F12,F12) -> 1.1485152 | J12: 1.5 | K12: =I12/J12 -> 0.7656768 | L12: 0.05 | M12: Growth+ | N12: openrouter
A13: Long take, 15s 720p | B13: long | C13: 15 | D13: 720p | E13: bytedance/seedance-2.0-fast | F13: =C13*'Vendor Prices'!$G$22*(1+Inputs!$B$7) -> 1.435644 | G13: seedance-2-fast | H13: =C13*'Vendor Prices'!$G$32 -> 1.86 | I13: =IF(OR(Inputs!$B$30="kie",AND(Inputs!$B$30="split",N13="kie")),(1-Inputs!$B$27)*H13+Inputs!$B$27*F13,F13) -> 1.435644 | J13: 2 | K13: =I13/J13 -> 0.717822 | L13: 0.03 | M13: Growth+ | N13: openrouter
A14: Long take, 15s 480p | B14: long | C14: 15 | D14: 480p | E14: bytedance/seedance-2.0-fast | F14: =C14*'Vendor Prices'!$G$21*(1+Inputs!$B$7) -> 0.63856249 | G14: seedance-2-fast | H14: =C14*'Vendor Prices'!$G$31 -> 0.8775 | I14: =IF(OR(Inputs!$B$30="kie",AND(Inputs!$B$30="split",N14="kie")),(1-Inputs!$B$27)*H14+Inputs!$B$27*F14,F14) -> 0.63856249 | J14: 1 | K14: =I14/J14 -> 0.63856249 | L14: 0.02 | M14: Growth+ | N14: openrouter
A15: Variation (Grok Imagine on KIE), 6s 720p | B15: variation | C15: 6 | D15: 720p | E15: google/veo-3.1-lite (fallback) | F15: =C15*'Vendor Prices'!$G$17*(1+Inputs!$B$7) -> 0.3165 | G15: grok-imagine | H15: ='Vendor Prices'!$G$34 -> 0.12 | I15: =IF(OR(Inputs!$B$30="kie",AND(Inputs!$B$30="split",N15="kie")),(1-Inputs!$B$27)*H15+Inputs!$B$27*F15,F15) -> 0.129825 | J15: 0.5 | K15: =I15/J15 -> 0.25965 | L15: 0.02 | M15: All paid plans | N15: kie
A16: Variation, 6s 480p | B16: variation | C16: 6 | D16: 480p | E16: google/veo-3.1-lite (fallback) | F16: =C16*'Vendor Prices'!$G$17*(1+Inputs!$B$7) -> 0.3165 | G16: grok-imagine | H16: ='Vendor Prices'!$G$33 -> 0.06 | I16: =IF(OR(Inputs!$B$30="kie",AND(Inputs!$B$30="split",N16="kie")),(1-Inputs!$B$27)*H16+Inputs!$B$27*F16,F16) -> 0.072825 | J16: 0.5 | K16: =I16/J16 -> 0.14565 | L16: 0.01 | M16: All paid plans | N16: kie
A17: Studio video 6s (premium key) | B17: premium | C17: 6 | D17: 2K / 1080p | E17: minimax/hailuo-3 | F17: =C17*'Vendor Prices'!$G$19*(1+Inputs!$B$7) -> 0.8229 | G17: gemini-omni-flash-1-1 | H17: =C17*'Vendor Prices'!$G$35 -> 0.6 | I17: =IF(OR(Inputs!$B$30="kie",AND(Inputs!$B$30="split",N17="kie")),(1-Inputs!$B$27)*H17+Inputs!$B$27*F17,F17) -> 0.8229 | J17: 1 | K17: =I17/J17 -> 0.8229 | L17: 0.02 | M17: All paid plans | N17: openrouter
A19: Blended cost per Video Credit (active mode) | K19: =SUMPRODUCT(K5:K17,L5:L17)/SUM(L5:L17) -> 0.44614618
A20: Same on OpenRouter | K20: =SUMPRODUCT(F5:F17/J5:J17,L5:L17)/SUM(L5:L17) -> 0.80883908
A21: Same on KIE | K21: =SUMPRODUCT(H5:H17/J5:J17,L5:L17)/SUM(L5:L17) -> 0.39138333
A22: Check: shares sum to | L22: =SUM(L5:L17) -> 1
A24: Rules that keep video under control
A25: 1. Video spends Video Credits only. General credits can never buy video, so a user cannot burn the whole plan on renders.
A26: 2. Each plan includes a monthly VC allowance; unused VC do not roll over on monthly plans (1 month rollover on annual).
A27: 3. Extra VC come from Video Packs (Add-ons & Packs tab) at a 55-65% margin. Packs never expire.
A28: 4. Hold VC when a render starts, capture on success, release on failure (the UGC reservation already works this way).
A29: 5. Always show the VC price on the Generate button and route 'auto' to Standard unless the brief truly needs Premium.
A30: 6. Keep UGC_MAX_CONCURRENT_RENDERS per plan: Starter 1, Growth 2, Agency 4, Scale 8.

Sheet Add-ons & Packs
A1: Add-ons, credit packs and video packs
A2: Expansion revenue. Every item clears its margin target on its own.
A4: Add-on (monthly) | B4: Price ($) | C4: What's inside | D4: Cost to serve ($) | E4: Margin | F4: Notes
A5: Extra brand (Growth, Agency, Scale) | B5: 39 | C5: 1 workspace, 30 prompts, 1,500 credits, 3 VC, weekly Market Brain, unlimited posts | D5: =30*Plans!$E$36*Inputs!$B$24+1500*Inputs!$B$21*Inputs!$B$37+3*Inputs!$B$22*Inputs!$B$38+150*Inputs!$B$26+Inputs!$B$24*'Unit Costs'!$AB$40+'Unit Costs'!$AB$60+('Unit Costs'!$AB$24+'Unit Costs'!$AB$25+'Unit Costs'!$AB$26)/12+200*'Unit Costs'!$AB$19 -> 9.1639958 | E5: =1-(D5+B5*(Inputs!$B$16+Inputs!$B$18+Inputs!$B$19))/B5 -> 0.69252575
A6: +100 tracked prompts, weekly | B6: 39 | C6: 100 prompts on the plan's engines | D6: =100*Plans!$E$36*Inputs!$B$24 -> 6.8921963 | E6: =1-(D6+B6*(Inputs!$B$16+Inputs!$B$18+Inputs!$B$19))/B6 -> 0.75077702
A7: Daily tracking, per 100 prompts | B7: 149 | C7: Moves 100 prompts from weekly to daily | D7: =100*Plans!$E$36*(Inputs!$B$25-Inputs!$B$24) -> 40.859741 | E7: =1-(D7+B7*(Inputs!$B$16+Inputs!$B$18+Inputs!$B$19))/B7 -> 0.65327355 | F7: 7x the checks
A8: Google AI Overviews engine, per 100 prompts | B8: 15 | C8: Real AI Overview capture via DataForSEO | D8: =100*'Unit Costs'!$AB$52*Inputs!$B$24 -> 0.82739264 | E8: =1-(D8+B8*(Inputs!$B$16+Inputs!$B$18+Inputs!$B$19))/B8 -> 0.87234049 | F8: Closes the Google gap in the probe set
A9: Daily Market Brain, per brand | B9: 29 | C9: Market Brain refresh every day instead of weekly | D9: =(Inputs!$B$25-Inputs!$B$24)*'Unit Costs'!$AB$40 -> 6.2490879 | E9: =1-(D9+B9*(Inputs!$B$16+Inputs!$B$18+Inputs!$B$19))/B9 -> 0.71201421 | F9: Opus refresh costs $0.25
A10: +200 Mellox Pro messages | B10: 29 | C10: Extra Claude Opus 5.5 chat | D10: =200*0.8*'Unit Costs'!$AB$20 -> 7.716088 | E10: =1-(D10+B10*(Inputs!$B$16+Inputs!$B$18+Inputs!$B$19))/B10 -> 0.661428 | F10: Assumes 80% of a bought pack is used
A11: Extra seat (Starter, Growth) | B11: 15 | C11: One more teammate | D11: =100*'Unit Costs'!$AB$19 -> 0.89300575 | E11: =1-(D11+B11*(Inputs!$B$16+Inputs!$B$18+Inputs!$B$19))/B11 -> 0.86796628
A12: White-label domain (Agency, Scale) | B12: 49 | C12: Client portal on the agency's domain | D12: =2 -> 2 | E12: =1-(D12+B12*(Inputs!$B$16+Inputs!$B$18+Inputs!$B$19))/B12 -> 0.88668367
A14: Credit pack (never expires) | B14: Price ($) | C14: Bonus (AI only) | D14: Credits | E14: Fees ($) | F14: COGS if fully used ($) | G14: Margin
A15: $25 credit pack | B15: 25 | C15: 0 | D15: =B15/Inputs!$B$6*(1+C15) -> 2500 | E15: =B15*(Inputs!$B$16+Inputs!$B$18+Inputs!$B$19)+Inputs!$B$17 -> 2.3125 | F15: =D15*Inputs!$B$37 -> 5.0853891 | G15: =(B15-E15-F15)/B15 -> 0.70408443
A16: $100 credit pack | B16: 100 | C16: 0.05 | D16: =B16/Inputs!$B$6*(1+C16) -> 10500 | E16: =B16*(Inputs!$B$16+Inputs!$B$18+Inputs!$B$19)+Inputs!$B$17 -> 7.75 | F16: =D16*Inputs!$B$37 -> 21.358634 | G16: =(B16-E16-F16)/B16 -> 0.70891366
A17: $250 credit pack | B17: 250 | C17: 0.1 | D17: =B17/Inputs!$B$6*(1+C17) -> 27500 | E17: =B17*(Inputs!$B$16+Inputs!$B$18+Inputs!$B$19)+Inputs!$B$17 -> 18.625 | F17: =D17*Inputs!$B$37 -> 55.939281 | G17: =(B17-E17-F17)/B17 -> 0.70174288
A18: $500 credit pack | B18: 500 | C18: 0.15 | D18: =B18/Inputs!$B$6*(1+C18) -> 57500 | E18: =B18*(Inputs!$B$16+Inputs!$B$18+Inputs!$B$19)+Inputs!$B$17 -> 36.75 | F18: =D18*Inputs!$B$37 -> 116.96395 | G18: =(B18-E18-F18)/B18 -> 0.6925721
A20: Video pack (never expires) | B20: Price ($) | C20: Video credits | D20: Price per VC ($) | E20: Fees ($) | F20: COGS, active provider ($) | G20: Margin | H20: COGS on KIE ($) | I20: Margin if KIE
A21: 10 video credits | B21: 29 | C21: 10 | D21: =B21/C21 -> 2.9 | E21: =B21*(Inputs!$B$16+Inputs!$B$18+Inputs!$B$19)+Inputs!$B$17 -> 2.6025 | F21: =C21*Inputs!$B$38 -> 4.4614618 | G21: =(B21-E21-F21)/B21 -> 0.75641511 | H21: =C21*'Video Credits'!$K$21 -> 3.9138333 | I21: =(B21-E21-H21)/B21 -> 0.77529885
A22: 30 video credits | B22: 79 | C22: 30 | D22: =B22/C22 -> 2.6333333 | E22: =B22*(Inputs!$B$16+Inputs!$B$18+Inputs!$B$19)+Inputs!$B$17 -> 6.2275 | F22: =C22*Inputs!$B$38 -> 13.384385 | G22: =(B22-E22-F22)/B22 -> 0.75174828 | H22: =C22*'Video Credits'!$K$21 -> 11.7415 | I22: =(B22-E22-H22)/B22 -> 0.7725443
A23: 100 video credits | B23: 249 | C23: 100 | D23: =B23/C23 -> 2.49 | E23: =B23*(Inputs!$B$16+Inputs!$B$18+Inputs!$B$19)+Inputs!$B$17 -> 18.5525 | F23: =C23*Inputs!$B$38 -> 44.614618 | G23: =(B23-E23-F23)/B23 -> 0.74631679 | H23: =C23*'Video Credits'!$K$21 -> 39.138333 | I23: =(B23-E23-H23)/B23 -> 0.76830991
A25: Average margin on packs (used for top-up revenue in the projection) | G25: =AVERAGE(G15:G18,G21:G23) -> 0.72311332

Sheet Retention & Growth
A1: Retention and growth: what keeps customers paying and upgrading
A2: Levers are built into the plans; the table below turns churn and CAC assumptions into LTV and payback.
A4: Lever | B4: How it works | C4: Cost to Mellox | D4: Expected effect (assumption) | E4: Where it lives
A5: Weekly auto Coach briefing | B5: A Monday email and in-app briefing per brand: what changed, what to post, what to fix | C5: ~$0.87 per brand per month | D5: Biggest habit driver; brings users back weekly | E5: Plans: coach_auto; coach.briefing
A6: Weekly AI-visibility report | B6: Email showing prompt wins/losses and competitor citations | C6: Included in prompt tracking | D6: Shows value even in quiet weeks | E6: geo scans + probes
A7: Separate video allowance | B7: Video never drains the credits people use for posts and articles | C7: None (protects margin) | D7: Fewer 'I ran out on day 3' cancellations | E7: Video Credits tab
A8: Rollover on annual plans | B8: Unused credits and VC roll over up to one month | C8: Small (less breakage) | D8: Pushes annual billing; lowers churn | E8: Credit ledger: expire job
A9: Pause instead of cancel | B9: $9/month keeps data, brands and 10 weekly prompts | C9: ~$1 per month | D9: Saves an estimated 20-30% of would-be cancellations | E9: Billing flow
A10: 80% usage nudges | B10: In-app + email at 80% of credits, VC or Pro messages with 1-click packs or upgrade | C10: None | D10: Converts heavy users to packs or the next plan | E10: budget.ts warn state
A11: Founding-customer offer | B11: First 50 paying customers: 30% off for 12 months, annual | C11: Discount only | D11: Early logos, case studies, cash upfront | E11: Paddle coupon
A12: Referral credits | B12: Both sides get 1,000 credits + 2 VC | C12: ~$3.80 per referral | D12: Cheapest acquisition channel for SMBs | E12: Credit ledger: grant
A13: Agency partner program | B13: 20% recurring commission for 12 months to agencies and consultants who resell | C13: 20% of revenue | D13: Channel into the agency segment | E13: Paddle affiliates
A14: 14-day Growth trial (card required) | B14: 500 credits, 2 VC, 20 Pro messages, 3 brands | C14: Up to ~$5 per trial | D14: Higher conversion than an open free tier | E14: Plans + Paddle trial
A15: Free plan as a lead magnet | B15: 5 prompts, 1 scan, 30 messages, 100 one-time credits | C15: ~$0.95 / month + $0.34 onboarding | D15: Top of funnel; upgrade when competitors show up in answers | E15: Plans: Free
A17: Unit economics per customer | B17: Starter | C17: Growth | D17: Agency | E17: Scale | F17: Notes
A18: Subscription revenue after annual discounts | B18: =Plans!$D$6*(1-Inputs!$B$32*Inputs!$B$31) -> 46.54951 | C18: =Plans!$E$6*(1-Inputs!$B$32*Inputs!$B$31) -> 141.54851 | D18: =Plans!$F$6*(1-Inputs!$B$32*Inputs!$B$31) -> 426.54551 | E18: =Plans!$G$6*(1-Inputs!$B$32*Inputs!$B$31) -> 1139.038
A19: Expansion revenue (add-ons, packs) as % of subscription | B19: 0.05 | C19: 0.12 | D19: 0.2 | E19: 0.15
A20: ARPA per month | B20: =B18*(1+B19) -> 48.876986 | C20: =C18*(1+C19) -> 158.53433 | D20: =D18*(1+D19) -> 511.85461 | E20: =E18*(1+E19) -> 1309.8937
A21: Cost to serve (typical) + fees | B21: =Plans!$D$54+B20*(Inputs!$B$16+Inputs!$B$18+Inputs!$B$19)+Inputs!$B$17+B18*B19*0.35 -> 16.786206 | C21: =Plans!$E$54+C20*(Inputs!$B$16+Inputs!$B$18+Inputs!$B$19)+Inputs!$B$17+C18*C19*0.35 -> 55.404767 | D21: =Plans!$F$54+D20*(Inputs!$B$16+Inputs!$B$18+Inputs!$B$19)+Inputs!$B$17+D18*D19*0.35 -> 183.4105 | E21: =Plans!$G$54+E20*(Inputs!$B$16+Inputs!$B$18+Inputs!$B$19)+Inputs!$B$17+E18*E19*0.35 -> 506.81376 | F21: Expansion revenue carries ~35% cost
A22: Contribution per month | B22: =B20-B21 -> 32.09078 | C22: =C20-C21 -> 103.12956 | D22: =D20-D21 -> 328.44412 | E22: =E20-E21 -> 803.07995
A23: Monthly churn without the levers | B23: 0.07 | C23: 0.05 | D23: 0.04 | E23: 0.025
A24: Churn reduction from the levers (points) | B24: 0.015 | C24: 0.012 | D24: 0.01 | E24: 0.005
A25: Monthly churn with the levers | B25: =MAX(0.005,B23-B24) -> 0.055 | C25: =MAX(0.005,C23-C24) -> 0.038 | D25: =MAX(0.005,D23-D24) -> 0.03 | E25: =MAX(0.005,E23-E24) -> 0.02
A26: Average lifetime without levers (months) | B26: =1/B23 -> 14.285714 | C26: =1/C23 -> 20 | D26: =1/D23 -> 25 | E26: =1/E23 -> 40
A27: Average lifetime with levers (months) | B27: =1/B25 -> 18.181818 | C27: =1/C25 -> 26.315789 | D27: =1/D25 -> 33.333333 | E27: =1/E25 -> 50
A28: Lifetime contribution (LTV) without levers | B28: =B22*B26 -> 458.43971 | C28: =C22*C26 -> 2062.5913 | D28: =D22*D26 -> 8211.1029 | E28: =E22*E26 -> 32123.198
A29: Lifetime contribution (LTV) with levers | B29: =B22*B27 -> 583.46872 | C29: =C22*C27 -> 2713.9359 | D29: =D22*D27 -> 10948.137 | E29: =E22*E27 -> 40153.998
A30: Acquisition cost (CAC) | B30: 60 | C30: 150 | D30: 450 | E30: 1500 | F30: Agency and Scale need founder-led sales
A31: CAC payback (months) | B31: =B30/B22 -> 1.8696959 | C31: =C30/C22 -> 1.4544811 | D31: =D30/D22 -> 1.3700961 | E31: =E30/E22 -> 1.867809
A32: LTV : CAC (with levers) | B32: =B29/B30 -> 9.7244787 | C32: =C29/C30 -> 18.092906 | D32: =D29/D30 -> 24.329194 | E32: =E29/E30 -> 26.769332 | F32: Healthy SaaS is 3x or more

Sheet Unit Costs
A1: Cost of every AI task on the new model stack (USD, expected case)
A2: Tier column uses PREMIUM / WORKHORSE / ECONOMY from Inputs, or a model key. Reasoning tokens come from the Inputs table unless overridden. Includes 3% fallback traffic and the 5.5% OpenRouter fee.
A4: ID | B4: Area | C4: Action | D4: Route label (task-models.ts) | E4: Tier / model | F4: Effort | G4: Input tokens / call | H4: Answer tokens / call | I4: Calls per action | J4: Cached input share | K4: Reasoning override | L4: Tavily credits | M4: Other cost key | N4: Other qty | O4: Fixed adder ($) | P4: Model resolved | Q4: Reasoning tokens | R4: In $/1M | S4: Out $/1M | T4: Cache $/1M | U4: Token factor | V4: Primary LLM ($) | W4: Fallback model | X4: Fallback LLM ($) | Y4: LLM blended ($) | Z4: Search ($) | AA4: Other ($) | AB4: Expected COGS ($) | AC4: Worst multiplier | AD4: Worst COGS ($) | AE4: Assumptions
A5: c_naturalize | B5: Component | C5: Caption naturalize pass | D5: studio.naturalize | E5: WORKHORSE | F5: low | G5: 1500 | H5: 500 | I5: 1 | J5: 0 | L5: 0 | P5: =IF(E5="PREMIUM",Inputs!$B$9,IF(E5="WORKHORSE",Inputs!$B$10,IF(E5="ECONOMY",Inputs!$B$11,E5))) -> google/gemini-3.8-flash | Q5: =IF(K5<>"",K5,IF(F5="",0,IFERROR(INDEX(Inputs!$B$42:$D$44,MATCH(E5,Inputs!$A$42:$A$44,0),IF(F5="low",1,IF(F5="medium",2,3))),0))) -> 500 | R5: =IF(P5="",0,INDEX('Vendor Prices'!$G$5:$G$58,MATCH(P5,'Vendor Prices'!$A$5:$A$58,0))) -> 0.75 | S5: =IF(P5="",0,INDEX('Vendor Prices'!$H$5:$H$58,MATCH(P5,'Vendor Prices'!$A$5:$A$58,0))) -> 3.75 | T5: =IF(P5="",0,IF(INDEX('Vendor Prices'!$I$5:$I$58,MATCH(P5,'Vendor Prices'!$A$5:$A$58,0))=0,R5,INDEX('Vendor Prices'!$I$5:$I$58,MATCH(P5,'Vendor Prices'!$A$5:$A$58,0)))) -> 0.1875 | U5: =IF(LEFT(P5,10)="anthropic/",Inputs!$B$8,1) -> 1 | V5: =IF(P5="",0,I5*(G5*U5*((1-J5)*R5+J5*T5)+(H5+Q5)*U5*S5)/1000000*(1+Inputs!$B$7)) -> 0.005143125 | W5: =IF(E5="PREMIUM",Inputs!$B$12,IF(E5="WORKHORSE",Inputs!$B$13,IF(E5="ECONOMY",Inputs!$B$14,""))) -> openai/gpt-5.6-terra | X5: =IF(W5="",V5,I5*(G5*((1-J5)*INDEX('Vendor Prices'!$G$5:$G$58,MATCH(W5,'Vendor Prices'!$A$5:$A$58,0))+J5*INDEX('Vendor Prices'!$I$5:$I$58,MATCH(W5,'Vendor Prices'!$A$5:$A$58,0)))+(H5+Q5)*INDEX('Vendor Prices'!$H$5:$H$58,MATCH(W5,'Vendor Prices'!$A$5:$A$58,0)))/1000000*(1+Inputs!$B$7)) -> 0.015825 | Y5: =(1-Inputs!$B$15)*V5+Inputs!$B$15*X5 -> 0.0054635813 | Z5: =L5*Inputs!$B$29 -> 0 | AA5: =IF(M5="",0,N5*INDEX('Vendor Prices'!$G$5:$G$58,MATCH(M5,'Vendor Prices'!$A$5:$A$58,0))*(1+INDEX('Vendor Prices'!$J$5:$J$58,MATCH(M5,'Vendor Prices'!$A$5:$A$58,0))*Inputs!$B$7)) -> 0 | AB5: =Y5+Z5+AA5+O5 -> 0.0054635813 | AC5: 1.5 | AD5: =AB5*AC5 -> 0.0081953719 | AE5: Runs on ~30% of caption jobs
A6: c_summary | B6: Component | C6: Chat history summary | D6: chat.history-summary | E6: ECONOMY | F6: low | G6: 6000 | H6: 600 | I6: 1 | J6: 0 | L6: 0 | P6: =IF(E6="PREMIUM",Inputs!$B$9,IF(E6="WORKHORSE",Inputs!$B$10,IF(E6="ECONOMY",Inputs!$B$11,E6))) -> google/gemini-3.1-flash-lite | Q6: =IF(K6<>"",K6,IF(F6="",0,IFERROR(INDEX(Inputs!$B$42:$D$44,MATCH(E6,Inputs!$A$42:$A$44,0),IF(F6="low",1,IF(F6="medium",2,3))),0))) -> 200 | R6: =IF(P6="",0,INDEX('Vendor Prices'!$G$5:$G$58,MATCH(P6,'Vendor Prices'!$A$5:$A$58,0))) -> 0.25 | S6: =IF(P6="",0,INDEX('Vendor Prices'!$H$5:$H$58,MATCH(P6,'Vendor Prices'!$A$5:$A$58,0))) -> 1.5 | T6: =IF(P6="",0,IF(INDEX('Vendor Prices'!$I$5:$I$58,MATCH(P6,'Vendor Prices'!$A$5:$A$58,0))=0,R6,INDEX('Vendor Prices'!$I$5:$I$58,MATCH(P6,'Vendor Prices'!$A$5:$A$58,0)))) -> 0.0625 | U6: =IF(LEFT(P6,10)="anthropic/",Inputs!$B$8,1) -> 1 | V6: =IF(P6="",0,I6*(G6*U6*((1-J6)*R6+J6*T6)+(H6+Q6)*U6*S6)/1000000*(1+Inputs!$B$7)) -> 0.0028485 | W6: =IF(E6="PREMIUM",Inputs!$B$12,IF(E6="WORKHORSE",Inputs!$B$13,IF(E6="ECONOMY",Inputs!$B$14,""))) -> openai/gpt-5.6-luna | X6: =IF(W6="",V6,I6*(G6*((1-J6)*INDEX('Vendor Prices'!$G$5:$G$58,MATCH(W6,'Vendor Prices'!$A$5:$A$58,0))+J6*INDEX('Vendor Prices'!$I$5:$I$58,MATCH(W6,'Vendor Prices'!$A$5:$A$58,0)))+(H6+Q6)*INDEX('Vendor Prices'!$H$5:$H$58,MATCH(W6,'Vendor Prices'!$A$5:$A$58,0)))/1000000*(1+Inputs!$B$7)) -> 0.0022788 | Y6: =(1-Inputs!$B$15)*V6+Inputs!$B$15*X6 -> 0.002831409 | Z6: =L6*Inputs!$B$29 -> 0 | AA6: =IF(M6="",0,N6*INDEX('Vendor Prices'!$G$5:$G$58,MATCH(M6,'Vendor Prices'!$A$5:$A$58,0))*(1+INDEX('Vendor Prices'!$J$5:$J$58,MATCH(M6,'Vendor Prices'!$A$5:$A$58,0))*Inputs!$B$7)) -> 0 | AB6: =Y6+Z6+AA6+O6 -> 0.002831409 | AC6: 1.5 | AD6: =AB6*AC6 -> 0.0042471135 | AE6: Every 8 turns
A7: c_moderation | B7: Component | C7: Image moderation | D7: guardrails.image-moderation | E7: ECONOMY | F7: low | G7: 1500 | H7: 100 | I7: 1 | J7: 0 | L7: 0 | P7: =IF(E7="PREMIUM",Inputs!$B$9,IF(E7="WORKHORSE",Inputs!$B$10,IF(E7="ECONOMY",Inputs!$B$11,E7))) -> google/gemini-3.1-flash-lite | Q7: =IF(K7<>"",K7,IF(F7="",0,IFERROR(INDEX(Inputs!$B$42:$D$44,MATCH(E7,Inputs!$A$42:$A$44,0),IF(F7="low",1,IF(F7="medium",2,3))),0))) -> 200 | R7: =IF(P7="",0,INDEX('Vendor Prices'!$G$5:$G$58,MATCH(P7,'Vendor Prices'!$A$5:$A$58,0))) -> 0.25 | S7: =IF(P7="",0,INDEX('Vendor Prices'!$H$5:$H$58,MATCH(P7,'Vendor Prices'!$A$5:$A$58,0))) -> 1.5 | T7: =IF(P7="",0,IF(INDEX('Vendor Prices'!$I$5:$I$58,MATCH(P7,'Vendor Prices'!$A$5:$A$58,0))=0,R7,INDEX('Vendor Prices'!$I$5:$I$58,MATCH(P7,'Vendor Prices'!$A$5:$A$58,0)))) -> 0.0625 | U7: =IF(LEFT(P7,10)="anthropic/",Inputs!$B$8,1) -> 1 | V7: =IF(P7="",0,I7*(G7*U7*((1-J7)*R7+J7*T7)+(H7+Q7)*U7*S7)/1000000*(1+Inputs!$B$7)) -> 0.000870375 | W7: =IF(E7="PREMIUM",Inputs!$B$12,IF(E7="WORKHORSE",Inputs!$B$13,IF(E7="ECONOMY",Inputs!$B$14,""))) -> openai/gpt-5.6-luna | X7: =IF(W7="",V7,I7*(G7*((1-J7)*INDEX('Vendor Prices'!$G$5:$G$58,MATCH(W7,'Vendor Prices'!$A$5:$A$58,0))+J7*INDEX('Vendor Prices'!$I$5:$I$58,MATCH(W7,'Vendor Prices'!$A$5:$A$58,0)))+(H7+Q7)*INDEX('Vendor Prices'!$H$5:$H$58,MATCH(W7,'Vendor Prices'!$A$5:$A$58,0)))/1000000*(1+Inputs!$B$7)) -> 0.0006963 | Y7: =(1-Inputs!$B$15)*V7+Inputs!$B$15*X7 -> 0.00086515275 | Z7: =L7*Inputs!$B$29 -> 0 | AA7: =IF(M7="",0,N7*INDEX('Vendor Prices'!$G$5:$G$58,MATCH(M7,'Vendor Prices'!$A$5:$A$58,0))*(1+INDEX('Vendor Prices'!$J$5:$J$58,MATCH(M7,'Vendor Prices'!$A$5:$A$58,0))*Inputs!$B$7)) -> 0 | AB7: =Y7+Z7+AA7+O7 -> 0.00086515275 | AC7: 1.5 | AD7: =AB7*AC7 -> 0.0012977291
A8: c_file_escal | B8: Component | C8: File extract escalation | D8: file-extract (escalated) | E8: WORKHORSE | F8: low | G8: 8000 | H8: 1500 | I8: 1 | J8: 0 | L8: 0 | P8: =IF(E8="PREMIUM",Inputs!$B$9,IF(E8="WORKHORSE",Inputs!$B$10,IF(E8="ECONOMY",Inputs!$B$11,E8))) -> google/gemini-3.8-flash | Q8: =IF(K8<>"",K8,IF(F8="",0,IFERROR(INDEX(Inputs!$B$42:$D$44,MATCH(E8,Inputs!$A$42:$A$44,0),IF(F8="low",1,IF(F8="medium",2,3))),0))) -> 500 | R8: =IF(P8="",0,INDEX('Vendor Prices'!$G$5:$G$58,MATCH(P8,'Vendor Prices'!$A$5:$A$58,0))) -> 0.75 | S8: =IF(P8="",0,INDEX('Vendor Prices'!$H$5:$H$58,MATCH(P8,'Vendor Prices'!$A$5:$A$58,0))) -> 3.75 | T8: =IF(P8="",0,IF(INDEX('Vendor Prices'!$I$5:$I$58,MATCH(P8,'Vendor Prices'!$A$5:$A$58,0))=0,R8,INDEX('Vendor Prices'!$I$5:$I$58,MATCH(P8,'Vendor Prices'!$A$5:$A$58,0)))) -> 0.1875 | U8: =IF(LEFT(P8,10)="anthropic/",Inputs!$B$8,1) -> 1 | V8: =IF(P8="",0,I8*(G8*U8*((1-J8)*R8+J8*T8)+(H8+Q8)*U8*S8)/1000000*(1+Inputs!$B$7)) -> 0.0142425 | W8: =IF(E8="PREMIUM",Inputs!$B$12,IF(E8="WORKHORSE",Inputs!$B$13,IF(E8="ECONOMY",Inputs!$B$14,""))) -> openai/gpt-5.6-terra | X8: =IF(W8="",V8,I8*(G8*((1-J8)*INDEX('Vendor Prices'!$G$5:$G$58,MATCH(W8,'Vendor Prices'!$A$5:$A$58,0))+J8*INDEX('Vendor Prices'!$I$5:$I$58,MATCH(W8,'Vendor Prices'!$A$5:$A$58,0)))+(H8+Q8)*INDEX('Vendor Prices'!$H$5:$H$58,MATCH(W8,'Vendor Prices'!$A$5:$A$58,0)))/1000000*(1+Inputs!$B$7)) -> 0.0422 | Y8: =(1-Inputs!$B$15)*V8+Inputs!$B$15*X8 -> 0.015081225 | Z8: =L8*Inputs!$B$29 -> 0 | AA8: =IF(M8="",0,N8*INDEX('Vendor Prices'!$G$5:$G$58,MATCH(M8,'Vendor Prices'!$A$5:$A$58,0))*(1+INDEX('Vendor Prices'!$J$5:$J$58,MATCH(M8,'Vendor Prices'!$A$5:$A$58,0))*Inputs!$B$7)) -> 0 | AB8: =Y8+Z8+AA8+O8 -> 0.015081225 | AC8: 1.5 | AD8: =AB8*AC8 -> 0.022621837 | AE8: ~20% of reads are thin and escalate
A9: c_coach_research | B9: Component | C9: Coach research synthesis | D9: coach.research | E9: WORKHORSE | F9: low | G9: 3000 | H9: 800 | I9: 1 | J9: 0 | L9: 0 | P9: =IF(E9="PREMIUM",Inputs!$B$9,IF(E9="WORKHORSE",Inputs!$B$10,IF(E9="ECONOMY",Inputs!$B$11,E9))) -> google/gemini-3.8-flash | Q9: =IF(K9<>"",K9,IF(F9="",0,IFERROR(INDEX(Inputs!$B$42:$D$44,MATCH(E9,Inputs!$A$42:$A$44,0),IF(F9="low",1,IF(F9="medium",2,3))),0))) -> 500 | R9: =IF(P9="",0,INDEX('Vendor Prices'!$G$5:$G$58,MATCH(P9,'Vendor Prices'!$A$5:$A$58,0))) -> 0.75 | S9: =IF(P9="",0,INDEX('Vendor Prices'!$H$5:$H$58,MATCH(P9,'Vendor Prices'!$A$5:$A$58,0))) -> 3.75 | T9: =IF(P9="",0,IF(INDEX('Vendor Prices'!$I$5:$I$58,MATCH(P9,'Vendor Prices'!$A$5:$A$58,0))=0,R9,INDEX('Vendor Prices'!$I$5:$I$58,MATCH(P9,'Vendor Prices'!$A$5:$A$58,0)))) -> 0.1875 | U9: =IF(LEFT(P9,10)="anthropic/",Inputs!$B$8,1) -> 1 | V9: =IF(P9="",0,I9*(G9*U9*((1-J9)*R9+J9*T9)+(H9+Q9)*U9*S9)/1000000*(1+Inputs!$B$7)) -> 0.007516875 | W9: =IF(E9="PREMIUM",Inputs!$B$12,IF(E9="WORKHORSE",Inputs!$B$13,IF(E9="ECONOMY",Inputs!$B$14,""))) -> openai/gpt-5.6-terra | X9: =IF(W9="",V9,I9*(G9*((1-J9)*INDEX('Vendor Prices'!$G$5:$G$58,MATCH(W9,'Vendor Prices'!$A$5:$A$58,0))+J9*INDEX('Vendor Prices'!$I$5:$I$58,MATCH(W9,'Vendor Prices'!$A$5:$A$58,0)))+(H9+Q9)*INDEX('Vendor Prices'!$H$5:$H$58,MATCH(W9,'Vendor Prices'!$A$5:$A$58,0)))/1000000*(1+Inputs!$B$7)) -> 0.022788 | Y9: =(1-Inputs!$B$15)*V9+Inputs!$B$15*X9 -> 0.0079750088 | Z9: =L9*Inputs!$B$29 -> 0 | AA9: =IF(M9="",0,N9*INDEX('Vendor Prices'!$G$5:$G$58,MATCH(M9,'Vendor Prices'!$A$5:$A$58,0))*(1+INDEX('Vendor Prices'!$J$5:$J$58,MATCH(M9,'Vendor Prices'!$A$5:$A$58,0))*Inputs!$B$7)) -> 0 | AB9: =Y9+Z9+AA9+O9 -> 0.0079750088 | AC9: 1.5 | AD9: =AB9*AC9 -> 0.011962513
A10: c_cms_retry | B10: Component | C10: GEO CMS fix retry on PREMIUM | D10: geo.cms.fix (retry) | E10: PREMIUM | F10: medium | G10: 8000 | H10: 4000 | I10: 1 | J10: 0 | L10: 0 | P10: =IF(E10="PREMIUM",Inputs!$B$9,IF(E10="WORKHORSE",Inputs!$B$10,IF(E10="ECONOMY",Inputs!$B$11,E10))) -> anthropic/claude-opus-5.5 | Q10: =IF(K10<>"",K10,IF(F10="",0,IFERROR(INDEX(Inputs!$B$42:$D$44,MATCH(E10,Inputs!$A$42:$A$44,0),IF(F10="low",1,IF(F10="medium",2,3))),0))) -> 3000 | R10: =IF(P10="",0,INDEX('Vendor Prices'!$G$5:$G$58,MATCH(P10,'Vendor Prices'!$A$5:$A$58,0))) -> 4 | S10: =IF(P10="",0,INDEX('Vendor Prices'!$H$5:$H$58,MATCH(P10,'Vendor Prices'!$A$5:$A$58,0))) -> 20 | T10: =IF(P10="",0,IF(INDEX('Vendor Prices'!$I$5:$I$58,MATCH(P10,'Vendor Prices'!$A$5:$A$58,0))=0,R10,INDEX('Vendor Prices'!$I$5:$I$58,MATCH(P10,'Vendor Prices'!$A$5:$A$58,0)))) -> 0.2 | U10: =IF(LEFT(P10,10)="anthropic/",Inputs!$B$8,1) -> 1.15 | V10: =IF(P10="",0,I10*(G10*U10*((1-J10)*R10+J10*T10)+(H10+Q10)*U10*S10)/1000000*(1+Inputs!$B$7)) -> 0.208679 | W10: =IF(E10="PREMIUM",Inputs!$B$12,IF(E10="WORKHORSE",Inputs!$B$13,IF(E10="ECONOMY",Inputs!$B$14,""))) -> google/gemini-3.8-flash | X10: =IF(W10="",V10,I10*(G10*((1-J10)*INDEX('Vendor Prices'!$G$5:$G$58,MATCH(W10,'Vendor Prices'!$A$5:$A$58,0))+J10*INDEX('Vendor Prices'!$I$5:$I$58,MATCH(W10,'Vendor Prices'!$A$5:$A$58,0)))+(H10+Q10)*INDEX('Vendor Prices'!$H$5:$H$58,MATCH(W10,'Vendor Prices'!$A$5:$A$58,0)))/1000000*(1+Inputs!$B$7)) -> 0.03402375 | Y10: =(1-Inputs!$B$15)*V10+Inputs!$B$15*X10 -> 0.20343934 | Z10: =L10*Inputs!$B$29 -> 0 | AA10: =IF(M10="",0,N10*INDEX('Vendor Prices'!$G$5:$G$58,MATCH(M10,'Vendor Prices'!$A$5:$A$58,0))*(1+INDEX('Vendor Prices'!$J$5:$J$58,MATCH(M10,'Vendor Prices'!$A$5:$A$58,0))*Inputs!$B$7)) -> 0 | AB10: =Y10+Z10+AA10+O10 -> 0.20343934 | AC10: 1.5 | AD10: =AB10*AC10 -> 0.30515901 | AE10: ~20% rejected by validation/grounding
A11: c_exp_values | B11: Component | C11: Experiment values | D11: experiments.values | E11: WORKHORSE | F11: medium | G11: 16000 | H11: 5000 | I11: 1 | J11: 0 | L11: 0 | P11: =IF(E11="PREMIUM",Inputs!$B$9,IF(E11="WORKHORSE",Inputs!$B$10,IF(E11="ECONOMY",Inputs!$B$11,E11))) -> google/gemini-3.8-flash | Q11: =IF(K11<>"",K11,IF(F11="",0,IFERROR(INDEX(Inputs!$B$42:$D$44,MATCH(E11,Inputs!$A$42:$A$44,0),IF(F11="low",1,IF(F11="medium",2,3))),0))) -> 1800 | R11: =IF(P11="",0,INDEX('Vendor Prices'!$G$5:$G$58,MATCH(P11,'Vendor Prices'!$A$5:$A$58,0))) -> 0.75 | S11: =IF(P11="",0,INDEX('Vendor Prices'!$H$5:$H$58,MATCH(P11,'Vendor Prices'!$A$5:$A$58,0))) -> 3.75 | T11: =IF(P11="",0,IF(INDEX('Vendor Prices'!$I$5:$I$58,MATCH(P11,'Vendor Prices'!$A$5:$A$58,0))=0,R11,INDEX('Vendor Prices'!$I$5:$I$58,MATCH(P11,'Vendor Prices'!$A$5:$A$58,0)))) -> 0.1875 | U11: =IF(LEFT(P11,10)="anthropic/",Inputs!$B$8,1) -> 1 | V11: =IF(P11="",0,I11*(G11*U11*((1-J11)*R11+J11*T11)+(H11+Q11)*U11*S11)/1000000*(1+Inputs!$B$7)) -> 0.0395625 | W11: =IF(E11="PREMIUM",Inputs!$B$12,IF(E11="WORKHORSE",Inputs!$B$13,IF(E11="ECONOMY",Inputs!$B$14,""))) -> openai/gpt-5.6-terra | X11: =IF(W11="",V11,I11*(G11*((1-J11)*INDEX('Vendor Prices'!$G$5:$G$58,MATCH(W11,'Vendor Prices'!$A$5:$A$58,0))+J11*INDEX('Vendor Prices'!$I$5:$I$58,MATCH(W11,'Vendor Prices'!$A$5:$A$58,0)))+(H11+Q11)*INDEX('Vendor Prices'!$H$5:$H$58,MATCH(W11,'Vendor Prices'!$A$5:$A$58,0)))/1000000*(1+Inputs!$B$7)) -> 0.119848 | Y11: =(1-Inputs!$B$15)*V11+Inputs!$B$15*X11 -> 0.041971065 | Z11: =L11*Inputs!$B$29 -> 0 | AA11: =IF(M11="",0,N11*INDEX('Vendor Prices'!$G$5:$G$58,MATCH(M11,'Vendor Prices'!$A$5:$A$58,0))*(1+INDEX('Vendor Prices'!$J$5:$J$58,MATCH(M11,'Vendor Prices'!$A$5:$A$58,0))*Inputs!$B$7)) -> 0 | AB11: =Y11+Z11+AA11+O11 -> 0.041971065 | AC11: 1.5 | AD11: =AB11*AC11 -> 0.062956598
A12: c_exp_analysis | B12: Component | C12: Experiment analysis/report | D12: experiments.* | E12: WORKHORSE | F12: low | G12: 4000 | H12: 1500 | I12: 1 | J12: 0 | L12: 0 | P12: =IF(E12="PREMIUM",Inputs!$B$9,IF(E12="WORKHORSE",Inputs!$B$10,IF(E12="ECONOMY",Inputs!$B$11,E12))) -> google/gemini-3.8-flash | Q12: =IF(K12<>"",K12,IF(F12="",0,IFERROR(INDEX(Inputs!$B$42:$D$44,MATCH(E12,Inputs!$A$42:$A$44,0),IF(F12="low",1,IF(F12="medium",2,3))),0))) -> 500 | R12: =IF(P12="",0,INDEX('Vendor Prices'!$G$5:$G$58,MATCH(P12,'Vendor Prices'!$A$5:$A$58,0))) -> 0.75 | S12: =IF(P12="",0,INDEX('Vendor Prices'!$H$5:$H$58,MATCH(P12,'Vendor Prices'!$A$5:$A$58,0))) -> 3.75 | T12: =IF(P12="",0,IF(INDEX('Vendor Prices'!$I$5:$I$58,MATCH(P12,'Vendor Prices'!$A$5:$A$58,0))=0,R12,INDEX('Vendor Prices'!$I$5:$I$58,MATCH(P12,'Vendor Prices'!$A$5:$A$58,0)))) -> 0.1875 | U12: =IF(LEFT(P12,10)="anthropic/",Inputs!$B$8,1) -> 1 | V12: =IF(P12="",0,I12*(G12*U12*((1-J12)*R12+J12*T12)+(H12+Q12)*U12*S12)/1000000*(1+Inputs!$B$7)) -> 0.0110775 | W12: =IF(E12="PREMIUM",Inputs!$B$12,IF(E12="WORKHORSE",Inputs!$B$13,IF(E12="ECONOMY",Inputs!$B$14,""))) -> openai/gpt-5.6-terra | X12: =IF(W12="",V12,I12*(G12*((1-J12)*INDEX('Vendor Prices'!$G$5:$G$58,MATCH(W12,'Vendor Prices'!$A$5:$A$58,0))+J12*INDEX('Vendor Prices'!$I$5:$I$58,MATCH(W12,'Vendor Prices'!$A$5:$A$58,0)))+(H12+Q12)*INDEX('Vendor Prices'!$H$5:$H$58,MATCH(W12,'Vendor Prices'!$A$5:$A$58,0)))/1000000*(1+Inputs!$B$7)) -> 0.03376 | Y12: =(1-Inputs!$B$15)*V12+Inputs!$B$15*X12 -> 0.011757975 | Z12: =L12*Inputs!$B$29 -> 0 | AA12: =IF(M12="",0,N12*INDEX('Vendor Prices'!$G$5:$G$58,MATCH(M12,'Vendor Prices'!$A$5:$A$58,0))*(1+INDEX('Vendor Prices'!$J$5:$J$58,MATCH(M12,'Vendor Prices'!$A$5:$A$58,0))*Inputs!$B$7)) -> 0 | AB12: =Y12+Z12+AA12+O12 -> 0.011757975 | AC12: 1.5 | AD12: =AB12*AC12 -> 0.017636962
A13: c_link_pick | B13: Component | C13: Link relevance pick | D13: links-relevance-pick | E13: WORKHORSE | F13: low | G13: 5000 | H13: 800 | I13: 1 | J13: 0 | L13: 0 | P13: =IF(E13="PREMIUM",Inputs!$B$9,IF(E13="WORKHORSE",Inputs!$B$10,IF(E13="ECONOMY",Inputs!$B$11,E13))) -> google/gemini-3.8-flash | Q13: =IF(K13<>"",K13,IF(F13="",0,IFERROR(INDEX(Inputs!$B$42:$D$44,MATCH(E13,Inputs!$A$42:$A$44,0),IF(F13="low",1,IF(F13="medium",2,3))),0))) -> 500 | R13: =IF(P13="",0,INDEX('Vendor Prices'!$G$5:$G$58,MATCH(P13,'Vendor Prices'!$A$5:$A$58,0))) -> 0.75 | S13: =IF(P13="",0,INDEX('Vendor Prices'!$H$5:$H$58,MATCH(P13,'Vendor Prices'!$A$5:$A$58,0))) -> 3.75 | T13: =IF(P13="",0,IF(INDEX('Vendor Prices'!$I$5:$I$58,MATCH(P13,'Vendor Prices'!$A$5:$A$58,0))=0,R13,INDEX('Vendor Prices'!$I$5:$I$58,MATCH(P13,'Vendor Prices'!$A$5:$A$58,0)))) -> 0.1875 | U13: =IF(LEFT(P13,10)="anthropic/",Inputs!$B$8,1) -> 1 | V13: =IF(P13="",0,I13*(G13*U13*((1-J13)*R13+J13*T13)+(H13+Q13)*U13*S13)/1000000*(1+Inputs!$B$7)) -> 0.009099375 | W13: =IF(E13="PREMIUM",Inputs!$B$12,IF(E13="WORKHORSE",Inputs!$B$13,IF(E13="ECONOMY",Inputs!$B$14,""))) -> openai/gpt-5.6-terra | X13: =IF(W13="",V13,I13*(G13*((1-J13)*INDEX('Vendor Prices'!$G$5:$G$58,MATCH(W13,'Vendor Prices'!$A$5:$A$58,0))+J13*INDEX('Vendor Prices'!$I$5:$I$58,MATCH(W13,'Vendor Prices'!$A$5:$A$58,0)))+(H13+Q13)*INDEX('Vendor Prices'!$H$5:$H$58,MATCH(W13,'Vendor Prices'!$A$5:$A$58,0)))/1000000*(1+Inputs!$B$7)) -> 0.027008 | Y13: =(1-Inputs!$B$15)*V13+Inputs!$B$15*X13 -> 0.0096366337 | Z13: =L13*Inputs!$B$29 -> 0 | AA13: =IF(M13="",0,N13*INDEX('Vendor Prices'!$G$5:$G$58,MATCH(M13,'Vendor Prices'!$A$5:$A$58,0))*(1+INDEX('Vendor Prices'!$J$5:$J$58,MATCH(M13,'Vendor Prices'!$A$5:$A$58,0))*Inputs!$B$7)) -> 0 | AB13: =Y13+Z13+AA13+O13 -> 0.0096366337 | AC13: 1.5 | AD13: =AB13*AC13 -> 0.014454951
A14: c_ugc_extract | B14: Component | C14: UGC product extract | D14: ugc.product.extract | E14: WORKHORSE | F14: low | G14: 6000 | H14: 2000 | I14: 1 | J14: 0 | L14: 0 | P14: =IF(E14="PREMIUM",Inputs!$B$9,IF(E14="WORKHORSE",Inputs!$B$10,IF(E14="ECONOMY",Inputs!$B$11,E14))) -> google/gemini-3.8-flash | Q14: =IF(K14<>"",K14,IF(F14="",0,IFERROR(INDEX(Inputs!$B$42:$D$44,MATCH(E14,Inputs!$A$42:$A$44,0),IF(F14="low",1,IF(F14="medium",2,3))),0))) -> 500 | R14: =IF(P14="",0,INDEX('Vendor Prices'!$G$5:$G$58,MATCH(P14,'Vendor Prices'!$A$5:$A$58,0))) -> 0.75 | S14: =IF(P14="",0,INDEX('Vendor Prices'!$H$5:$H$58,MATCH(P14,'Vendor Prices'!$A$5:$A$58,0))) -> 3.75 | T14: =IF(P14="",0,IF(INDEX('Vendor Prices'!$I$5:$I$58,MATCH(P14,'Vendor Prices'!$A$5:$A$58,0))=0,R14,INDEX('Vendor Prices'!$I$5:$I$58,MATCH(P14,'Vendor Prices'!$A$5:$A$58,0)))) -> 0.1875 | U14: =IF(LEFT(P14,10)="anthropic/",Inputs!$B$8,1) -> 1 | V14: =IF(P14="",0,I14*(G14*U14*((1-J14)*R14+J14*T14)+(H14+Q14)*U14*S14)/1000000*(1+Inputs!$B$7)) -> 0.014638125 | W14: =IF(E14="PREMIUM",Inputs!$B$12,IF(E14="WORKHORSE",Inputs!$B$13,IF(E14="ECONOMY",Inputs!$B$14,""))) -> openai/gpt-5.6-terra | X14: =IF(W14="",V14,I14*(G14*((1-J14)*INDEX('Vendor Prices'!$G$5:$G$58,MATCH(W14,'Vendor Prices'!$A$5:$A$58,0))+J14*INDEX('Vendor Prices'!$I$5:$I$58,MATCH(W14,'Vendor Prices'!$A$5:$A$58,0)))+(H14+Q14)*INDEX('Vendor Prices'!$H$5:$H$58,MATCH(W14,'Vendor Prices'!$A$5:$A$58,0)))/1000000*(1+Inputs!$B$7)) -> 0.04431 | Y14: =(1-Inputs!$B$15)*V14+Inputs!$B$15*X14 -> 0.015528281 | Z14: =L14*Inputs!$B$29 -> 0 | AA14: =IF(M14="",0,N14*INDEX('Vendor Prices'!$G$5:$G$58,MATCH(M14,'Vendor Prices'!$A$5:$A$58,0))*(1+INDEX('Vendor Prices'!$J$5:$J$58,MATCH(M14,'Vendor Prices'!$A$5:$A$58,0))*Inputs!$B$7)) -> 0 | AB14: =Y14+Z14+AA14+O14 -> 0.015528281 | AC14: 1.5 | AD14: =AB14*AC14 -> 0.023292422
A15: c_ugc_notes | B15: Component | C15: UGC notes | D15: ugc.notes | E15: WORKHORSE | F15: low | G15: 2000 | H15: 600 | I15: 1 | J15: 0 | L15: 0 | P15: =IF(E15="PREMIUM",Inputs!$B$9,IF(E15="WORKHORSE",Inputs!$B$10,IF(E15="ECONOMY",Inputs!$B$11,E15))) -> google/gemini-3.8-flash | Q15: =IF(K15<>"",K15,IF(F15="",0,IFERROR(INDEX(Inputs!$B$42:$D$44,MATCH(E15,Inputs!$A$42:$A$44,0),IF(F15="low",1,IF(F15="medium",2,3))),0))) -> 500 | R15: =IF(P15="",0,INDEX('Vendor Prices'!$G$5:$G$58,MATCH(P15,'Vendor Prices'!$A$5:$A$58,0))) -> 0.75 | S15: =IF(P15="",0,INDEX('Vendor Prices'!$H$5:$H$58,MATCH(P15,'Vendor Prices'!$A$5:$A$58,0))) -> 3.75 | T15: =IF(P15="",0,IF(INDEX('Vendor Prices'!$I$5:$I$58,MATCH(P15,'Vendor Prices'!$A$5:$A$58,0))=0,R15,INDEX('Vendor Prices'!$I$5:$I$58,MATCH(P15,'Vendor Prices'!$A$5:$A$58,0)))) -> 0.1875 | U15: =IF(LEFT(P15,10)="anthropic/",Inputs!$B$8,1) -> 1 | V15: =IF(P15="",0,I15*(G15*U15*((1-J15)*R15+J15*T15)+(H15+Q15)*U15*S15)/1000000*(1+Inputs!$B$7)) -> 0.005934375 | W15: =IF(E15="PREMIUM",Inputs!$B$12,IF(E15="WORKHORSE",Inputs!$B$13,IF(E15="ECONOMY",Inputs!$B$14,""))) -> openai/gpt-5.6-terra | X15: =IF(W15="",V15,I15*(G15*((1-J15)*INDEX('Vendor Prices'!$G$5:$G$58,MATCH(W15,'Vendor Prices'!$A$5:$A$58,0))+J15*INDEX('Vendor Prices'!$I$5:$I$58,MATCH(W15,'Vendor Prices'!$A$5:$A$58,0)))+(H15+Q15)*INDEX('Vendor Prices'!$H$5:$H$58,MATCH(W15,'Vendor Prices'!$A$5:$A$58,0)))/1000000*(1+Inputs!$B$7)) -> 0.018146 | Y15: =(1-Inputs!$B$15)*V15+Inputs!$B$15*X15 -> 0.0063007237 | Z15: =L15*Inputs!$B$29 -> 0 | AA15: =IF(M15="",0,N15*INDEX('Vendor Prices'!$G$5:$G$58,MATCH(M15,'Vendor Prices'!$A$5:$A$58,0))*(1+INDEX('Vendor Prices'!$J$5:$J$58,MATCH(M15,'Vendor Prices'!$A$5:$A$58,0))*Inputs!$B$7)) -> 0 | AB15: =Y15+Z15+AA15+O15 -> 0.0063007237 | AC15: 1.5 | AD15: =AB15*AC15 -> 0.0094510856
A16: img_std | B16: Image | C16: Standard image (GPT Image 2.5 Flare) | D16: /api/generate-image, Studio | G16: 0 | H16: 0 | I16: 1 | J16: 0 | L16: 0 | M16: img-flare | N16: =Inputs!$B$20 -> 1.3 | O16: =$AB$7*Inputs!$B$20 -> 0.0011246986 | P16: =IF(E16="PREMIUM",Inputs!$B$9,IF(E16="WORKHORSE",Inputs!$B$10,IF(E16="ECONOMY",Inputs!$B$11,E16))) -> 0 | Q16: =IF(K16<>"",K16,IF(F16="",0,IFERROR(INDEX(Inputs!$B$42:$D$44,MATCH(E16,Inputs!$A$42:$A$44,0),IF(F16="low",1,IF(F16="medium",2,3))),0))) -> 0 | R16: =IF(P16="",0,INDEX('Vendor Prices'!$G$5:$G$58,MATCH(P16,'Vendor Prices'!$A$5:$A$58,0))) -> 0 | S16: =IF(P16="",0,INDEX('Vendor Prices'!$H$5:$H$58,MATCH(P16,'Vendor Prices'!$A$5:$A$58,0))) -> 0 | T16: =IF(P16="",0,IF(INDEX('Vendor Prices'!$I$5:$I$58,MATCH(P16,'Vendor Prices'!$A$5:$A$58,0))=0,R16,INDEX('Vendor Prices'!$I$5:$I$58,MATCH(P16,'Vendor Prices'!$A$5:$A$58,0)))) -> 0 | U16: =IF(LEFT(P16,10)="anthropic/",Inputs!$B$8,1) -> 1 | V16: =IF(P16="",0,I16*(G16*U16*((1-J16)*R16+J16*T16)+(H16+Q16)*U16*S16)/1000000*(1+Inputs!$B$7)) -> 0 | W16: =IF(E16="PREMIUM",Inputs!$B$12,IF(E16="WORKHORSE",Inputs!$B$13,IF(E16="ECONOMY",Inputs!$B$14,""))) | X16: =IF(W16="",V16,I16*(G16*((1-J16)*INDEX('Vendor Prices'!$G$5:$G$58,MATCH(W16,'Vendor Prices'!$A$5:$A$58,0))+J16*INDEX('Vendor Prices'!$I$5:$I$58,MATCH(W16,'Vendor Prices'!$A$5:$A$58,0)))+(H16+Q16)*INDEX('Vendor Prices'!$H$5:$H$58,MATCH(W16,'Vendor Prices'!$A$5:$A$58,0)))/1000000*(1+Inputs!$B$7)) -> 0 | Y16: =(1-Inputs!$B$15)*V16+Inputs!$B$15*X16 -> 0 | Z16: =L16*Inputs!$B$29 -> 0 | AA16: =IF(M16="",0,N16*INDEX('Vendor Prices'!$G$5:$G$58,MATCH(M16,'Vendor Prices'!$A$5:$A$58,0))*(1+INDEX('Vendor Prices'!$J$5:$J$58,MATCH(M16,'Vendor Prices'!$A$5:$A$58,0))*Inputs!$B$7)) -> 0.035659 | AB16: =Y16+Z16+AA16+O16 -> 0.036783699 | AC16: 2 | AD16: =AB16*AC16 -> 0.073567397 | AE16: Incl. re-rolls and moderation
A17: img_prem | B17: Image | C17: Premium image (GPT Image 2.5 Sunburst) | D17: /api/generate-image | G17: 0 | H17: 0 | I17: 1 | J17: 0 | L17: 0 | M17: img-sunburst | N17: =Inputs!$B$20 -> 1.3 | O17: =$AB$7*Inputs!$B$20 -> 0.0011246986 | P17: =IF(E17="PREMIUM",Inputs!$B$9,IF(E17="WORKHORSE",Inputs!$B$10,IF(E17="ECONOMY",Inputs!$B$11,E17))) -> 0 | Q17: =IF(K17<>"",K17,IF(F17="",0,IFERROR(INDEX(Inputs!$B$42:$D$44,MATCH(E17,Inputs!$A$42:$A$44,0),IF(F17="low",1,IF(F17="medium",2,3))),0))) -> 0 | R17: =IF(P17="",0,INDEX('Vendor Prices'!$G$5:$G$58,MATCH(P17,'Vendor Prices'!$A$5:$A$58,0))) -> 0 | S17: =IF(P17="",0,INDEX('Vendor Prices'!$H$5:$H$58,MATCH(P17,'Vendor Prices'!$A$5:$A$58,0))) -> 0 | T17: =IF(P17="",0,IF(INDEX('Vendor Prices'!$I$5:$I$58,MATCH(P17,'Vendor Prices'!$A$5:$A$58,0))=0,R17,INDEX('Vendor Prices'!$I$5:$I$58,MATCH(P17,'Vendor Prices'!$A$5:$A$58,0)))) -> 0 | U17: =IF(LEFT(P17,10)="anthropic/",Inputs!$B$8,1) -> 1 | V17: =IF(P17="",0,I17*(G17*U17*((1-J17)*R17+J17*T17)+(H17+Q17)*U17*S17)/1000000*(1+Inputs!$B$7)) -> 0 | W17: =IF(E17="PREMIUM",Inputs!$B$12,IF(E17="WORKHORSE",Inputs!$B$13,IF(E17="ECONOMY",Inputs!$B$14,""))) | X17: =IF(W17="",V17,I17*(G17*((1-J17)*INDEX('Vendor Prices'!$G$5:$G$58,MATCH(W17,'Vendor Prices'!$A$5:$A$58,0))+J17*INDEX('Vendor Prices'!$I$5:$I$58,MATCH(W17,'Vendor Prices'!$A$5:$A$58,0)))+(H17+Q17)*INDEX('Vendor Prices'!$H$5:$H$58,MATCH(W17,'Vendor Prices'!$A$5:$A$58,0)))/1000000*(1+Inputs!$B$7)) -> 0 | Y17: =(1-Inputs!$B$15)*V17+Inputs!$B$15*X17 -> 0 | Z17: =L17*Inputs!$B$29 -> 0 | AA17: =IF(M17="",0,N17*INDEX('Vendor Prices'!$G$5:$G$58,MATCH(M17,'Vendor Prices'!$A$5:$A$58,0))*(1+INDEX('Vendor Prices'!$J$5:$J$58,MATCH(M17,'Vendor Prices'!$A$5:$A$58,0))*Inputs!$B$7)) -> 0.085033 | AB17: =Y17+Z17+AA17+O17 -> 0.086157699 | AC17: 1.5 | AD17: =AB17*AC17 -> 0.12923655
A18: img_edit | B18: Image | C18: Image edit with 2 references (Flare) | D18: /api/generate-image (edit) | G18: 0 | H18: 0 | I18: 1 | J18: 0 | L18: 0 | M18: img-flare | N18: 1 | O18: =2*'Vendor Prices'!$G$14*(1+Inputs!$B$7)+$AB$7 -> 0.022809153 | P18: =IF(E18="PREMIUM",Inputs!$B$9,IF(E18="WORKHORSE",Inputs!$B$10,IF(E18="ECONOMY",Inputs!$B$11,E18))) -> 0 | Q18: =IF(K18<>"",K18,IF(F18="",0,IFERROR(INDEX(Inputs!$B$42:$D$44,MATCH(E18,Inputs!$A$42:$A$44,0),IF(F18="low",1,IF(F18="medium",2,3))),0))) -> 0 | R18: =IF(P18="",0,INDEX('Vendor Prices'!$G$5:$G$58,MATCH(P18,'Vendor Prices'!$A$5:$A$58,0))) -> 0 | S18: =IF(P18="",0,INDEX('Vendor Prices'!$H$5:$H$58,MATCH(P18,'Vendor Prices'!$A$5:$A$58,0))) -> 0 | T18: =IF(P18="",0,IF(INDEX('Vendor Prices'!$I$5:$I$58,MATCH(P18,'Vendor Prices'!$A$5:$A$58,0))=0,R18,INDEX('Vendor Prices'!$I$5:$I$58,MATCH(P18,'Vendor Prices'!$A$5:$A$58,0)))) -> 0 | U18: =IF(LEFT(P18,10)="anthropic/",Inputs!$B$8,1) -> 1 | V18: =IF(P18="",0,I18*(G18*U18*((1-J18)*R18+J18*T18)+(H18+Q18)*U18*S18)/1000000*(1+Inputs!$B$7)) -> 0 | W18: =IF(E18="PREMIUM",Inputs!$B$12,IF(E18="WORKHORSE",Inputs!$B$13,IF(E18="ECONOMY",Inputs!$B$14,""))) | X18: =IF(W18="",V18,I18*(G18*((1-J18)*INDEX('Vendor Prices'!$G$5:$G$58,MATCH(W18,'Vendor Prices'!$A$5:$A$58,0))+J18*INDEX('Vendor Prices'!$I$5:$I$58,MATCH(W18,'Vendor Prices'!$A$5:$A$58,0)))+(H18+Q18)*INDEX('Vendor Prices'!$H$5:$H$58,MATCH(W18,'Vendor Prices'!$A$5:$A$58,0)))/1000000*(1+Inputs!$B$7)) -> 0 | Y18: =(1-Inputs!$B$15)*V18+Inputs!$B$15*X18 -> 0 | Z18: =L18*Inputs!$B$29 -> 0 | AA18: =IF(M18="",0,N18*INDEX('Vendor Prices'!$G$5:$G$58,MATCH(M18,'Vendor Prices'!$A$5:$A$58,0))*(1+INDEX('Vendor Prices'!$J$5:$J$58,MATCH(M18,'Vendor Prices'!$A$5:$A$58,0))*Inputs!$B$7)) -> 0.02743 | AB18: =Y18+Z18+AA18+O18 -> 0.050239153 | AC18: 1.8 | AD18: =AB18*AC18 -> 0.090430475
A19: chat_flash | B19: Assistant | C19: Chat message: Mellox Flash (default) | D19: chat (mellox-flash) | E19: WORKHORSE | F19: low | G19: 4500 | H19: 700 | I19: 1 | J19: 0.5 | L19: 0.15 | O19: =$AB$6/8 -> 0.00035392613 | P19: =IF(E19="PREMIUM",Inputs!$B$9,IF(E19="WORKHORSE",Inputs!$B$10,IF(E19="ECONOMY",Inputs!$B$11,E19))) -> google/gemini-3.8-flash | Q19: =IF(K19<>"",K19,IF(F19="",0,IFERROR(INDEX(Inputs!$B$42:$D$44,MATCH(E19,Inputs!$A$42:$A$44,0),IF(F19="low",1,IF(F19="medium",2,3))),0))) -> 500 | R19: =IF(P19="",0,INDEX('Vendor Prices'!$G$5:$G$58,MATCH(P19,'Vendor Prices'!$A$5:$A$58,0))) -> 0.75 | S19: =IF(P19="",0,INDEX('Vendor Prices'!$H$5:$H$58,MATCH(P19,'Vendor Prices'!$A$5:$A$58,0))) -> 3.75 | T19: =IF(P19="",0,IF(INDEX('Vendor Prices'!$I$5:$I$58,MATCH(P19,'Vendor Prices'!$A$5:$A$58,0))=0,R19,INDEX('Vendor Prices'!$I$5:$I$58,MATCH(P19,'Vendor Prices'!$A$5:$A$58,0)))) -> 0.1875 | U19: =IF(LEFT(P19,10)="anthropic/",Inputs!$B$8,1) -> 1 | V19: =IF(P19="",0,I19*(G19*U19*((1-J19)*R19+J19*T19)+(H19+Q19)*U19*S19)/1000000*(1+Inputs!$B$7)) -> 0.0069728906 | W19: =IF(E19="PREMIUM",Inputs!$B$12,IF(E19="WORKHORSE",Inputs!$B$13,IF(E19="ECONOMY",Inputs!$B$14,""))) -> openai/gpt-5.6-terra | X19: =IF(W19="",V19,I19*(G19*((1-J19)*INDEX('Vendor Prices'!$G$5:$G$58,MATCH(W19,'Vendor Prices'!$A$5:$A$58,0))+J19*INDEX('Vendor Prices'!$I$5:$I$58,MATCH(W19,'Vendor Prices'!$A$5:$A$58,0)))+(H19+Q19)*INDEX('Vendor Prices'!$H$5:$H$58,MATCH(W19,'Vendor Prices'!$A$5:$A$58,0)))/1000000*(1+Inputs!$B$7)) -> 0.02041425 | Y19: =(1-Inputs!$B$15)*V19+Inputs!$B$15*X19 -> 0.0073761314 | Z19: =L19*Inputs!$B$29 -> 0.0012 | AA19: =IF(M19="",0,N19*INDEX('Vendor Prices'!$G$5:$G$58,MATCH(M19,'Vendor Prices'!$A$5:$A$58,0))*(1+INDEX('Vendor Prices'!$J$5:$J$58,MATCH(M19,'Vendor Prices'!$A$5:$A$58,0))*Inputs!$B$7)) -> 0 | AB19: =Y19+Z19+AA19+O19 -> 0.0089300575 | AC19: 2 | AD19: =AB19*AC19 -> 0.017860115 | AE19: 15% of turns trigger web research
A20: chat_pro | B20: Assistant | C20: Chat message: Mellox Pro | D20: chat (mellox-pro) | E20: PREMIUM | F20: low | G20: 4500 | H20: 700 | I20: 1 | J20: 0.5 | L20: 0.15 | O20: =$AB$6/8 -> 0.00035392613 | P20: =IF(E20="PREMIUM",Inputs!$B$9,IF(E20="WORKHORSE",Inputs!$B$10,IF(E20="ECONOMY",Inputs!$B$11,E20))) -> anthropic/claude-opus-5.5 | Q20: =IF(K20<>"",K20,IF(F20="",0,IFERROR(INDEX(Inputs!$B$42:$D$44,MATCH(E20,Inputs!$A$42:$A$44,0),IF(F20="low",1,IF(F20="medium",2,3))),0))) -> 800 | R20: =IF(P20="",0,INDEX('Vendor Prices'!$G$5:$G$58,MATCH(P20,'Vendor Prices'!$A$5:$A$58,0))) -> 4 | S20: =IF(P20="",0,INDEX('Vendor Prices'!$H$5:$H$58,MATCH(P20,'Vendor Prices'!$A$5:$A$58,0))) -> 20 | T20: =IF(P20="",0,IF(INDEX('Vendor Prices'!$I$5:$I$58,MATCH(P20,'Vendor Prices'!$A$5:$A$58,0))=0,R20,INDEX('Vendor Prices'!$I$5:$I$58,MATCH(P20,'Vendor Prices'!$A$5:$A$58,0)))) -> 0.2 | U20: =IF(LEFT(P20,10)="anthropic/",Inputs!$B$8,1) -> 1.15 | V20: =IF(P20="",0,I20*(G20*U20*((1-J20)*R20+J20*T20)+(H20+Q20)*U20*S20)/1000000*(1+Inputs!$B$7)) -> 0.047862713 | W20: =IF(E20="PREMIUM",Inputs!$B$12,IF(E20="WORKHORSE",Inputs!$B$13,IF(E20="ECONOMY",Inputs!$B$14,""))) -> google/gemini-3.8-flash | X20: =IF(W20="",V20,I20*(G20*((1-J20)*INDEX('Vendor Prices'!$G$5:$G$58,MATCH(W20,'Vendor Prices'!$A$5:$A$58,0))+J20*INDEX('Vendor Prices'!$I$5:$I$58,MATCH(W20,'Vendor Prices'!$A$5:$A$58,0)))+(H20+Q20)*INDEX('Vendor Prices'!$H$5:$H$58,MATCH(W20,'Vendor Prices'!$A$5:$A$58,0)))/1000000*(1+Inputs!$B$7)) -> 0.0081597656 | Y20: =(1-Inputs!$B$15)*V20+Inputs!$B$15*X20 -> 0.046671624 | Z20: =L20*Inputs!$B$29 -> 0.0012 | AA20: =IF(M20="",0,N20*INDEX('Vendor Prices'!$G$5:$G$58,MATCH(M20,'Vendor Prices'!$A$5:$A$58,0))*(1+INDEX('Vendor Prices'!$J$5:$J$58,MATCH(M20,'Vendor Prices'!$A$5:$A$58,0))*Inputs!$B$7)) -> 0 | AB20: =Y20+Z20+AA20+O20 -> 0.04822555 | AC20: 2.5 | AD20: =AB20*AC20 -> 0.12056388 | AE20: Escalates to medium effort on strategy turns (worst case)
A21: clarify | B21: Assistant | C21: Clarify / intent tool call | D21: clarify | E21: WORKHORSE | F21: low | G21: 1500 | H21: 300 | I21: 1 | J21: 0 | L21: 0 | P21: =IF(E21="PREMIUM",Inputs!$B$9,IF(E21="WORKHORSE",Inputs!$B$10,IF(E21="ECONOMY",Inputs!$B$11,E21))) -> google/gemini-3.8-flash | Q21: =IF(K21<>"",K21,IF(F21="",0,IFERROR(INDEX(Inputs!$B$42:$D$44,MATCH(E21,Inputs!$A$42:$A$44,0),IF(F21="low",1,IF(F21="medium",2,3))),0))) -> 500 | R21: =IF(P21="",0,INDEX('Vendor Prices'!$G$5:$G$58,MATCH(P21,'Vendor Prices'!$A$5:$A$58,0))) -> 0.75 | S21: =IF(P21="",0,INDEX('Vendor Prices'!$H$5:$H$58,MATCH(P21,'Vendor Prices'!$A$5:$A$58,0))) -> 3.75 | T21: =IF(P21="",0,IF(INDEX('Vendor Prices'!$I$5:$I$58,MATCH(P21,'Vendor Prices'!$A$5:$A$58,0))=0,R21,INDEX('Vendor Prices'!$I$5:$I$58,MATCH(P21,'Vendor Prices'!$A$5:$A$58,0)))) -> 0.1875 | U21: =IF(LEFT(P21,10)="anthropic/",Inputs!$B$8,1) -> 1 | V21: =IF(P21="",0,I21*(G21*U21*((1-J21)*R21+J21*T21)+(H21+Q21)*U21*S21)/1000000*(1+Inputs!$B$7)) -> 0.004351875 | W21: =IF(E21="PREMIUM",Inputs!$B$12,IF(E21="WORKHORSE",Inputs!$B$13,IF(E21="ECONOMY",Inputs!$B$14,""))) -> openai/gpt-5.6-terra | X21: =IF(W21="",V21,I21*(G21*((1-J21)*INDEX('Vendor Prices'!$G$5:$G$58,MATCH(W21,'Vendor Prices'!$A$5:$A$58,0))+J21*INDEX('Vendor Prices'!$I$5:$I$58,MATCH(W21,'Vendor Prices'!$A$5:$A$58,0)))+(H21+Q21)*INDEX('Vendor Prices'!$H$5:$H$58,MATCH(W21,'Vendor Prices'!$A$5:$A$58,0)))/1000000*(1+Inputs!$B$7)) -> 0.013293 | Y21: =(1-Inputs!$B$15)*V21+Inputs!$B$15*X21 -> 0.0046201087 | Z21: =L21*Inputs!$B$29 -> 0 | AA21: =IF(M21="",0,N21*INDEX('Vendor Prices'!$G$5:$G$58,MATCH(M21,'Vendor Prices'!$A$5:$A$58,0))*(1+INDEX('Vendor Prices'!$J$5:$J$58,MATCH(M21,'Vendor Prices'!$A$5:$A$58,0))*Inputs!$B$7)) -> 0 | AB21: =Y21+Z21+AA21+O21 -> 0.0046201087 | AC21: 1.5 | AD21: =AB21*AC21 -> 0.0069301631
A22: memory_extract | B22: Assistant | C22: Memory extraction | D22: memory-extract | E22: WORKHORSE | F22: low | G22: 6000 | H22: 1200 | I22: 1 | J22: 0 | L22: 0 | P22: =IF(E22="PREMIUM",Inputs!$B$9,IF(E22="WORKHORSE",Inputs!$B$10,IF(E22="ECONOMY",Inputs!$B$11,E22))) -> google/gemini-3.8-flash | Q22: =IF(K22<>"",K22,IF(F22="",0,IFERROR(INDEX(Inputs!$B$42:$D$44,MATCH(E22,Inputs!$A$42:$A$44,0),IF(F22="low",1,IF(F22="medium",2,3))),0))) -> 500 | R22: =IF(P22="",0,INDEX('Vendor Prices'!$G$5:$G$58,MATCH(P22,'Vendor Prices'!$A$5:$A$58,0))) -> 0.75 | S22: =IF(P22="",0,INDEX('Vendor Prices'!$H$5:$H$58,MATCH(P22,'Vendor Prices'!$A$5:$A$58,0))) -> 3.75 | T22: =IF(P22="",0,IF(INDEX('Vendor Prices'!$I$5:$I$58,MATCH(P22,'Vendor Prices'!$A$5:$A$58,0))=0,R22,INDEX('Vendor Prices'!$I$5:$I$58,MATCH(P22,'Vendor Prices'!$A$5:$A$58,0)))) -> 0.1875 | U22: =IF(LEFT(P22,10)="anthropic/",Inputs!$B$8,1) -> 1 | V22: =IF(P22="",0,I22*(G22*U22*((1-J22)*R22+J22*T22)+(H22+Q22)*U22*S22)/1000000*(1+Inputs!$B$7)) -> 0.011473125 | W22: =IF(E22="PREMIUM",Inputs!$B$12,IF(E22="WORKHORSE",Inputs!$B$13,IF(E22="ECONOMY",Inputs!$B$14,""))) -> openai/gpt-5.6-terra | X22: =IF(W22="",V22,I22*(G22*((1-J22)*INDEX('Vendor Prices'!$G$5:$G$58,MATCH(W22,'Vendor Prices'!$A$5:$A$58,0))+J22*INDEX('Vendor Prices'!$I$5:$I$58,MATCH(W22,'Vendor Prices'!$A$5:$A$58,0)))+(H22+Q22)*INDEX('Vendor Prices'!$H$5:$H$58,MATCH(W22,'Vendor Prices'!$A$5:$A$58,0)))/1000000*(1+Inputs!$B$7)) -> 0.034182 | Y22: =(1-Inputs!$B$15)*V22+Inputs!$B$15*X22 -> 0.012154391 | Z22: =L22*Inputs!$B$29 -> 0 | AA22: =IF(M22="",0,N22*INDEX('Vendor Prices'!$G$5:$G$58,MATCH(M22,'Vendor Prices'!$A$5:$A$58,0))*(1+INDEX('Vendor Prices'!$J$5:$J$58,MATCH(M22,'Vendor Prices'!$A$5:$A$58,0))*Inputs!$B$7)) -> 0 | AB22: =Y22+Z22+AA22+O22 -> 0.012154391 | AC22: 1.5 | AD22: =AB22*AC22 -> 0.018231587
A23: file_extract | B23: Assistant | C23: File / image extraction | D23: file-extract | E23: ECONOMY | F23: low | G23: 8000 | H23: 1500 | I23: 1 | J23: 0 | L23: 0 | O23: =0.2*$AB$8 -> 0.003016245 | P23: =IF(E23="PREMIUM",Inputs!$B$9,IF(E23="WORKHORSE",Inputs!$B$10,IF(E23="ECONOMY",Inputs!$B$11,E23))) -> google/gemini-3.1-flash-lite | Q23: =IF(K23<>"",K23,IF(F23="",0,IFERROR(INDEX(Inputs!$B$42:$D$44,MATCH(E23,Inputs!$A$42:$A$44,0),IF(F23="low",1,IF(F23="medium",2,3))),0))) -> 200 | R23: =IF(P23="",0,INDEX('Vendor Prices'!$G$5:$G$58,MATCH(P23,'Vendor Prices'!$A$5:$A$58,0))) -> 0.25 | S23: =IF(P23="",0,INDEX('Vendor Prices'!$H$5:$H$58,MATCH(P23,'Vendor Prices'!$A$5:$A$58,0))) -> 1.5 | T23: =IF(P23="",0,IF(INDEX('Vendor Prices'!$I$5:$I$58,MATCH(P23,'Vendor Prices'!$A$5:$A$58,0))=0,R23,INDEX('Vendor Prices'!$I$5:$I$58,MATCH(P23,'Vendor Prices'!$A$5:$A$58,0)))) -> 0.0625 | U23: =IF(LEFT(P23,10)="anthropic/",Inputs!$B$8,1) -> 1 | V23: =IF(P23="",0,I23*(G23*U23*((1-J23)*R23+J23*T23)+(H23+Q23)*U23*S23)/1000000*(1+Inputs!$B$7)) -> 0.00480025 | W23: =IF(E23="PREMIUM",Inputs!$B$12,IF(E23="WORKHORSE",Inputs!$B$13,IF(E23="ECONOMY",Inputs!$B$14,""))) -> openai/gpt-5.6-luna | X23: =IF(W23="",V23,I23*(G23*((1-J23)*INDEX('Vendor Prices'!$G$5:$G$58,MATCH(W23,'Vendor Prices'!$A$5:$A$58,0))+J23*INDEX('Vendor Prices'!$I$5:$I$58,MATCH(W23,'Vendor Prices'!$A$5:$A$58,0)))+(H23+Q23)*INDEX('Vendor Prices'!$H$5:$H$58,MATCH(W23,'Vendor Prices'!$A$5:$A$58,0)))/1000000*(1+Inputs!$B$7)) -> 0.0038402 | Y23: =(1-Inputs!$B$15)*V23+Inputs!$B$15*X23 -> 0.0047714485 | Z23: =L23*Inputs!$B$29 -> 0 | AA23: =IF(M23="",0,N23*INDEX('Vendor Prices'!$G$5:$G$58,MATCH(M23,'Vendor Prices'!$A$5:$A$58,0))*(1+INDEX('Vendor Prices'!$J$5:$J$58,MATCH(M23,'Vendor Prices'!$A$5:$A$58,0))*Inputs!$B$7)) -> 0 | AB23: =Y23+Z23+AA23+O23 -> 0.0077876935 | AC23: 1.5 | AD23: =AB23*AC23 -> 0.01168154
A24: brand_dna | B24: Onboarding | C24: Brand DNA scan | D24: brand-extract (+ .search) | E24: PREMIUM | F24: medium | G24: 11000 | H24: 3500 | I24: 1.1 | J24: 0 | L24: 1 | P24: =IF(E24="PREMIUM",Inputs!$B$9,IF(E24="WORKHORSE",Inputs!$B$10,IF(E24="ECONOMY",Inputs!$B$11,E24))) -> anthropic/claude-opus-5.5 | Q24: =IF(K24<>"",K24,IF(F24="",0,IFERROR(INDEX(Inputs!$B$42:$D$44,MATCH(E24,Inputs!$A$42:$A$44,0),IF(F24="low",1,IF(F24="medium",2,3))),0))) -> 3000 | R24: =IF(P24="",0,INDEX('Vendor Prices'!$G$5:$G$58,MATCH(P24,'Vendor Prices'!$A$5:$A$58,0))) -> 4 | S24: =IF(P24="",0,INDEX('Vendor Prices'!$H$5:$H$58,MATCH(P24,'Vendor Prices'!$A$5:$A$58,0))) -> 20 | T24: =IF(P24="",0,IF(INDEX('Vendor Prices'!$I$5:$I$58,MATCH(P24,'Vendor Prices'!$A$5:$A$58,0))=0,R24,INDEX('Vendor Prices'!$I$5:$I$58,MATCH(P24,'Vendor Prices'!$A$5:$A$58,0)))) -> 0.2 | U24: =IF(LEFT(P24,10)="anthropic/",Inputs!$B$8,1) -> 1.15 | V24: =IF(P24="",0,I24*(G24*U24*((1-J24)*R24+J24*T24)+(H24+Q24)*U24*S24)/1000000*(1+Inputs!$B$7)) -> 0.23221605 | W24: =IF(E24="PREMIUM",Inputs!$B$12,IF(E24="WORKHORSE",Inputs!$B$13,IF(E24="ECONOMY",Inputs!$B$14,""))) -> google/gemini-3.8-flash | X24: =IF(W24="",V24,I24*(G24*((1-J24)*INDEX('Vendor Prices'!$G$5:$G$58,MATCH(W24,'Vendor Prices'!$A$5:$A$58,0))+J24*INDEX('Vendor Prices'!$I$5:$I$58,MATCH(W24,'Vendor Prices'!$A$5:$A$58,0)))+(H24+Q24)*INDEX('Vendor Prices'!$H$5:$H$58,MATCH(W24,'Vendor Prices'!$A$5:$A$58,0)))/1000000*(1+Inputs!$B$7)) -> 0.037861313 | Y24: =(1-Inputs!$B$15)*V24+Inputs!$B$15*X24 -> 0.22638541 | Z24: =L24*Inputs!$B$29 -> 0.008 | AA24: =IF(M24="",0,N24*INDEX('Vendor Prices'!$G$5:$G$58,MATCH(M24,'Vendor Prices'!$A$5:$A$58,0))*(1+INDEX('Vendor Prices'!$J$5:$J$58,MATCH(M24,'Vendor Prices'!$A$5:$A$58,0))*Inputs!$B$7)) -> 0 | AB24: =Y24+Z24+AA24+O24 -> 0.23438541 | AC24: 1.6 | AD24: =AB24*AC24 -> 0.37501665 | AE24: maxTokens 12,000 covers reasoning + JSON
A25: brand_writing | B25: Onboarding | C25: Brand voice analysis | D25: brand-kit/analyze-writing | E25: PREMIUM | F25: low | G25: 6000 | H25: 1500 | I25: 1 | J25: 0 | L25: 0 | P25: =IF(E25="PREMIUM",Inputs!$B$9,IF(E25="WORKHORSE",Inputs!$B$10,IF(E25="ECONOMY",Inputs!$B$11,E25))) -> anthropic/claude-opus-5.5 | Q25: =IF(K25<>"",K25,IF(F25="",0,IFERROR(INDEX(Inputs!$B$42:$D$44,MATCH(E25,Inputs!$A$42:$A$44,0),IF(F25="low",1,IF(F25="medium",2,3))),0))) -> 800 | R25: =IF(P25="",0,INDEX('Vendor Prices'!$G$5:$G$58,MATCH(P25,'Vendor Prices'!$A$5:$A$58,0))) -> 4 | S25: =IF(P25="",0,INDEX('Vendor Prices'!$H$5:$H$58,MATCH(P25,'Vendor Prices'!$A$5:$A$58,0))) -> 20 | T25: =IF(P25="",0,IF(INDEX('Vendor Prices'!$I$5:$I$58,MATCH(P25,'Vendor Prices'!$A$5:$A$58,0))=0,R25,INDEX('Vendor Prices'!$I$5:$I$58,MATCH(P25,'Vendor Prices'!$A$5:$A$58,0)))) -> 0.2 | U25: =IF(LEFT(P25,10)="anthropic/",Inputs!$B$8,1) -> 1.15 | V25: =IF(P25="",0,I25*(G25*U25*((1-J25)*R25+J25*T25)+(H25+Q25)*U25*S25)/1000000*(1+Inputs!$B$7)) -> 0.0849275 | W25: =IF(E25="PREMIUM",Inputs!$B$12,IF(E25="WORKHORSE",Inputs!$B$13,IF(E25="ECONOMY",Inputs!$B$14,""))) -> google/gemini-3.8-flash | X25: =IF(W25="",V25,I25*(G25*((1-J25)*INDEX('Vendor Prices'!$G$5:$G$58,MATCH(W25,'Vendor Prices'!$A$5:$A$58,0))+J25*INDEX('Vendor Prices'!$I$5:$I$58,MATCH(W25,'Vendor Prices'!$A$5:$A$58,0)))+(H25+Q25)*INDEX('Vendor Prices'!$H$5:$H$58,MATCH(W25,'Vendor Prices'!$A$5:$A$58,0)))/1000000*(1+Inputs!$B$7)) -> 0.013846875 | Y25: =(1-Inputs!$B$15)*V25+Inputs!$B$15*X25 -> 0.082795081 | Z25: =L25*Inputs!$B$29 -> 0 | AA25: =IF(M25="",0,N25*INDEX('Vendor Prices'!$G$5:$G$58,MATCH(M25,'Vendor Prices'!$A$5:$A$58,0))*(1+INDEX('Vendor Prices'!$J$5:$J$58,MATCH(M25,'Vendor Prices'!$A$5:$A$58,0))*Inputs!$B$7)) -> 0 | AB25: =Y25+Z25+AA25+O25 -> 0.082795081 | AC25: 1.5 | AD25: =AB25*AC25 -> 0.12419262
A26: brand_visual | B26: Onboarding | C26: Brand visual analysis | D26: brand-kit/analyze-visual, describe | E26: WORKHORSE | F26: medium | G26: 3000 | H26: 800 | I26: 1 | J26: 0 | L26: 0 | P26: =IF(E26="PREMIUM",Inputs!$B$9,IF(E26="WORKHORSE",Inputs!$B$10,IF(E26="ECONOMY",Inputs!$B$11,E26))) -> google/gemini-3.8-flash | Q26: =IF(K26<>"",K26,IF(F26="",0,IFERROR(INDEX(Inputs!$B$42:$D$44,MATCH(E26,Inputs!$A$42:$A$44,0),IF(F26="low",1,IF(F26="medium",2,3))),0))) -> 1800 | R26: =IF(P26="",0,INDEX('Vendor Prices'!$G$5:$G$58,MATCH(P26,'Vendor Prices'!$A$5:$A$58,0))) -> 0.75 | S26: =IF(P26="",0,INDEX('Vendor Prices'!$H$5:$H$58,MATCH(P26,'Vendor Prices'!$A$5:$A$58,0))) -> 3.75 | T26: =IF(P26="",0,IF(INDEX('Vendor Prices'!$I$5:$I$58,MATCH(P26,'Vendor Prices'!$A$5:$A$58,0))=0,R26,INDEX('Vendor Prices'!$I$5:$I$58,MATCH(P26,'Vendor Prices'!$A$5:$A$58,0)))) -> 0.1875 | U26: =IF(LEFT(P26,10)="anthropic/",Inputs!$B$8,1) -> 1 | V26: =IF(P26="",0,I26*(G26*U26*((1-J26)*R26+J26*T26)+(H26+Q26)*U26*S26)/1000000*(1+Inputs!$B$7)) -> 0.01266 | W26: =IF(E26="PREMIUM",Inputs!$B$12,IF(E26="WORKHORSE",Inputs!$B$13,IF(E26="ECONOMY",Inputs!$B$14,""))) -> openai/gpt-5.6-terra | X26: =IF(W26="",V26,I26*(G26*((1-J26)*INDEX('Vendor Prices'!$G$5:$G$58,MATCH(W26,'Vendor Prices'!$A$5:$A$58,0))+J26*INDEX('Vendor Prices'!$I$5:$I$58,MATCH(W26,'Vendor Prices'!$A$5:$A$58,0)))+(H26+Q26)*INDEX('Vendor Prices'!$H$5:$H$58,MATCH(W26,'Vendor Prices'!$A$5:$A$58,0)))/1000000*(1+Inputs!$B$7)) -> 0.039246 | Y26: =(1-Inputs!$B$15)*V26+Inputs!$B$15*X26 -> 0.01345758 | Z26: =L26*Inputs!$B$29 -> 0 | AA26: =IF(M26="",0,N26*INDEX('Vendor Prices'!$G$5:$G$58,MATCH(M26,'Vendor Prices'!$A$5:$A$58,0))*(1+INDEX('Vendor Prices'!$J$5:$J$58,MATCH(M26,'Vendor Prices'!$A$5:$A$58,0))*Inputs!$B$7)) -> 0 | AB26: =Y26+Z26+AA26+O26 -> 0.01345758 | AC26: 1.5 | AD26: =AB26*AC26 -> 0.02018637
A27: post_set | B27: Studio | C27: Social post set (up to 3 platforms) | D27: studio.social / content.* | E27: WORKHORSE | F27: medium | G27: 5000 | H27: 1600 | I27: 1.1 | J27: 0 | L27: 0.1 | O27: =0.3*$AB$5 -> 0.0016390744 | P27: =IF(E27="PREMIUM",Inputs!$B$9,IF(E27="WORKHORSE",Inputs!$B$10,IF(E27="ECONOMY",Inputs!$B$11,E27))) -> google/gemini-3.8-flash | Q27: =IF(K27<>"",K27,IF(F27="",0,IFERROR(INDEX(Inputs!$B$42:$D$44,MATCH(E27,Inputs!$A$42:$A$44,0),IF(F27="low",1,IF(F27="medium",2,3))),0))) -> 1800 | R27: =IF(P27="",0,INDEX('Vendor Prices'!$G$5:$G$58,MATCH(P27,'Vendor Prices'!$A$5:$A$58,0))) -> 0.75 | S27: =IF(P27="",0,INDEX('Vendor Prices'!$H$5:$H$58,MATCH(P27,'Vendor Prices'!$A$5:$A$58,0))) -> 3.75 | T27: =IF(P27="",0,IF(INDEX('Vendor Prices'!$I$5:$I$58,MATCH(P27,'Vendor Prices'!$A$5:$A$58,0))=0,R27,INDEX('Vendor Prices'!$I$5:$I$58,MATCH(P27,'Vendor Prices'!$A$5:$A$58,0)))) -> 0.1875 | U27: =IF(LEFT(P27,10)="anthropic/",Inputs!$B$8,1) -> 1 | V27: =IF(P27="",0,I27*(G27*U27*((1-J27)*R27+J27*T27)+(H27+Q27)*U27*S27)/1000000*(1+Inputs!$B$7)) -> 0.01914825 | W27: =IF(E27="PREMIUM",Inputs!$B$12,IF(E27="WORKHORSE",Inputs!$B$13,IF(E27="ECONOMY",Inputs!$B$14,""))) -> openai/gpt-5.6-terra | X27: =IF(W27="",V27,I27*(G27*((1-J27)*INDEX('Vendor Prices'!$G$5:$G$58,MATCH(W27,'Vendor Prices'!$A$5:$A$58,0))+J27*INDEX('Vendor Prices'!$I$5:$I$58,MATCH(W27,'Vendor Prices'!$A$5:$A$58,0)))+(H27+Q27)*INDEX('Vendor Prices'!$H$5:$H$58,MATCH(W27,'Vendor Prices'!$A$5:$A$58,0)))/1000000*(1+Inputs!$B$7)) -> 0.0589534 | Y27: =(1-Inputs!$B$15)*V27+Inputs!$B$15*X27 -> 0.020342405 | Z27: =L27*Inputs!$B$29 -> 0.0008 | AA27: =IF(M27="",0,N27*INDEX('Vendor Prices'!$G$5:$G$58,MATCH(M27,'Vendor Prices'!$A$5:$A$58,0))*(1+INDEX('Vendor Prices'!$J$5:$J$58,MATCH(M27,'Vendor Prices'!$A$5:$A$58,0))*Inputs!$B$7)) -> 0 | AB27: =Y27+Z27+AA27+O27 -> 0.022781479 | AC27: 1.5 | AD27: =AB27*AC27 -> 0.034172218
A28: image_post | B28: Studio | C28: Image post (copy + 1 image) | D28: studio.image.brief + studio.captions | E28: WORKHORSE | F28: medium | G28: 3750 | H28: 750 | I28: 2 | J28: 0 | L28: 0 | O28: =$AB$16+0.3*$AB$5 -> 0.038422773 | P28: =IF(E28="PREMIUM",Inputs!$B$9,IF(E28="WORKHORSE",Inputs!$B$10,IF(E28="ECONOMY",Inputs!$B$11,E28))) -> google/gemini-3.8-flash | Q28: =IF(K28<>"",K28,IF(F28="",0,IFERROR(INDEX(Inputs!$B$42:$D$44,MATCH(E28,Inputs!$A$42:$A$44,0),IF(F28="low",1,IF(F28="medium",2,3))),0))) -> 1800 | R28: =IF(P28="",0,INDEX('Vendor Prices'!$G$5:$G$58,MATCH(P28,'Vendor Prices'!$A$5:$A$58,0))) -> 0.75 | S28: =IF(P28="",0,INDEX('Vendor Prices'!$H$5:$H$58,MATCH(P28,'Vendor Prices'!$A$5:$A$58,0))) -> 3.75 | T28: =IF(P28="",0,IF(INDEX('Vendor Prices'!$I$5:$I$58,MATCH(P28,'Vendor Prices'!$A$5:$A$58,0))=0,R28,INDEX('Vendor Prices'!$I$5:$I$58,MATCH(P28,'Vendor Prices'!$A$5:$A$58,0)))) -> 0.1875 | U28: =IF(LEFT(P28,10)="anthropic/",Inputs!$B$8,1) -> 1 | V28: =IF(P28="",0,I28*(G28*U28*((1-J28)*R28+J28*T28)+(H28+Q28)*U28*S28)/1000000*(1+Inputs!$B$7)) -> 0.02611125 | W28: =IF(E28="PREMIUM",Inputs!$B$12,IF(E28="WORKHORSE",Inputs!$B$13,IF(E28="ECONOMY",Inputs!$B$14,""))) -> openai/gpt-5.6-terra | X28: =IF(W28="",V28,I28*(G28*((1-J28)*INDEX('Vendor Prices'!$G$5:$G$58,MATCH(W28,'Vendor Prices'!$A$5:$A$58,0))+J28*INDEX('Vendor Prices'!$I$5:$I$58,MATCH(W28,'Vendor Prices'!$A$5:$A$58,0)))+(H28+Q28)*INDEX('Vendor Prices'!$H$5:$H$58,MATCH(W28,'Vendor Prices'!$A$5:$A$58,0)))/1000000*(1+Inputs!$B$7)) -> 0.080391 | Y28: =(1-Inputs!$B$15)*V28+Inputs!$B$15*X28 -> 0.027739643 | Z28: =L28*Inputs!$B$29 -> 0 | AA28: =IF(M28="",0,N28*INDEX('Vendor Prices'!$G$5:$G$58,MATCH(M28,'Vendor Prices'!$A$5:$A$58,0))*(1+INDEX('Vendor Prices'!$J$5:$J$58,MATCH(M28,'Vendor Prices'!$A$5:$A$58,0))*Inputs!$B$7)) -> 0 | AB28: =Y28+Z28+AA28+O28 -> 0.066162415 | AC28: 1.8 | AD28: =AB28*AC28 -> 0.11909235
A29: carousel | B29: Studio | C29: Carousel (copy + cover image) | D29: studio.carousel | E29: WORKHORSE | F29: medium | G29: 5000 | H29: 2200 | I29: 1.1 | J29: 0 | L29: 0 | O29: =$AB$16 -> 0.036783699 | P29: =IF(E29="PREMIUM",Inputs!$B$9,IF(E29="WORKHORSE",Inputs!$B$10,IF(E29="ECONOMY",Inputs!$B$11,E29))) -> google/gemini-3.8-flash | Q29: =IF(K29<>"",K29,IF(F29="",0,IFERROR(INDEX(Inputs!$B$42:$D$44,MATCH(E29,Inputs!$A$42:$A$44,0),IF(F29="low",1,IF(F29="medium",2,3))),0))) -> 1800 | R29: =IF(P29="",0,INDEX('Vendor Prices'!$G$5:$G$58,MATCH(P29,'Vendor Prices'!$A$5:$A$58,0))) -> 0.75 | S29: =IF(P29="",0,INDEX('Vendor Prices'!$H$5:$H$58,MATCH(P29,'Vendor Prices'!$A$5:$A$58,0))) -> 3.75 | T29: =IF(P29="",0,IF(INDEX('Vendor Prices'!$I$5:$I$58,MATCH(P29,'Vendor Prices'!$A$5:$A$58,0))=0,R29,INDEX('Vendor Prices'!$I$5:$I$58,MATCH(P29,'Vendor Prices'!$A$5:$A$58,0)))) -> 0.1875 | U29: =IF(LEFT(P29,10)="anthropic/",Inputs!$B$8,1) -> 1 | V29: =IF(P29="",0,I29*(G29*U29*((1-J29)*R29+J29*T29)+(H29+Q29)*U29*S29)/1000000*(1+Inputs!$B$7)) -> 0.021759375 | W29: =IF(E29="PREMIUM",Inputs!$B$12,IF(E29="WORKHORSE",Inputs!$B$13,IF(E29="ECONOMY",Inputs!$B$14,""))) -> openai/gpt-5.6-terra | X29: =IF(W29="",V29,I29*(G29*((1-J29)*INDEX('Vendor Prices'!$G$5:$G$58,MATCH(W29,'Vendor Prices'!$A$5:$A$58,0))+J29*INDEX('Vendor Prices'!$I$5:$I$58,MATCH(W29,'Vendor Prices'!$A$5:$A$58,0)))+(H29+Q29)*INDEX('Vendor Prices'!$H$5:$H$58,MATCH(W29,'Vendor Prices'!$A$5:$A$58,0)))/1000000*(1+Inputs!$B$7)) -> 0.067309 | Y29: =(1-Inputs!$B$15)*V29+Inputs!$B$15*X29 -> 0.023125864 | Z29: =L29*Inputs!$B$29 -> 0 | AA29: =IF(M29="",0,N29*INDEX('Vendor Prices'!$G$5:$G$58,MATCH(M29,'Vendor Prices'!$A$5:$A$58,0))*(1+INDEX('Vendor Prices'!$J$5:$J$58,MATCH(M29,'Vendor Prices'!$A$5:$A$58,0))*Inputs!$B$7)) -> 0 | AB29: =Y29+Z29+AA29+O29 -> 0.059909562 | AC29: 1.8 | AD29: =AB29*AC29 -> 0.10783721
A30: ad_set | B30: Studio | C30: Ad set (copy variants + image) | D30: studio.ad | E30: WORKHORSE | F30: medium | G30: 5000 | H30: 1800 | I30: 1.1 | J30: 0 | L30: 0 | O30: =$AB$16 -> 0.036783699 | P30: =IF(E30="PREMIUM",Inputs!$B$9,IF(E30="WORKHORSE",Inputs!$B$10,IF(E30="ECONOMY",Inputs!$B$11,E30))) -> google/gemini-3.8-flash | Q30: =IF(K30<>"",K30,IF(F30="",0,IFERROR(INDEX(Inputs!$B$42:$D$44,MATCH(E30,Inputs!$A$42:$A$44,0),IF(F30="low",1,IF(F30="medium",2,3))),0))) -> 1800 | R30: =IF(P30="",0,INDEX('Vendor Prices'!$G$5:$G$58,MATCH(P30,'Vendor Prices'!$A$5:$A$58,0))) -> 0.75 | S30: =IF(P30="",0,INDEX('Vendor Prices'!$H$5:$H$58,MATCH(P30,'Vendor Prices'!$A$5:$A$58,0))) -> 3.75 | T30: =IF(P30="",0,IF(INDEX('Vendor Prices'!$I$5:$I$58,MATCH(P30,'Vendor Prices'!$A$5:$A$58,0))=0,R30,INDEX('Vendor Prices'!$I$5:$I$58,MATCH(P30,'Vendor Prices'!$A$5:$A$58,0)))) -> 0.1875 | U30: =IF(LEFT(P30,10)="anthropic/",Inputs!$B$8,1) -> 1 | V30: =IF(P30="",0,I30*(G30*U30*((1-J30)*R30+J30*T30)+(H30+Q30)*U30*S30)/1000000*(1+Inputs!$B$7)) -> 0.020018625 | W30: =IF(E30="PREMIUM",Inputs!$B$12,IF(E30="WORKHORSE",Inputs!$B$13,IF(E30="ECONOMY",Inputs!$B$14,""))) -> openai/gpt-5.6-terra | X30: =IF(W30="",V30,I30*(G30*((1-J30)*INDEX('Vendor Prices'!$G$5:$G$58,MATCH(W30,'Vendor Prices'!$A$5:$A$58,0))+J30*INDEX('Vendor Prices'!$I$5:$I$58,MATCH(W30,'Vendor Prices'!$A$5:$A$58,0)))+(H30+Q30)*INDEX('Vendor Prices'!$H$5:$H$58,MATCH(W30,'Vendor Prices'!$A$5:$A$58,0)))/1000000*(1+Inputs!$B$7)) -> 0.0617386 | Y30: =(1-Inputs!$B$15)*V30+Inputs!$B$15*X30 -> 0.021270224 | Z30: =L30*Inputs!$B$29 -> 0 | AA30: =IF(M30="",0,N30*INDEX('Vendor Prices'!$G$5:$G$58,MATCH(M30,'Vendor Prices'!$A$5:$A$58,0))*(1+INDEX('Vendor Prices'!$J$5:$J$58,MATCH(M30,'Vendor Prices'!$A$5:$A$58,0))*Inputs!$B$7)) -> 0 | AB30: =Y30+Z30+AA30+O30 -> 0.058053923 | AC30: 1.8 | AD30: =AB30*AC30 -> 0.10449706
A31: article | B31: Studio | C31: Premium article (~1,200 words, GEO-grounded) | D31: studio.article | E31: PREMIUM | F31: medium | G31: 5500 | H31: 3200 | I31: 1.1 | J31: 0 | L31: 0.4 | P31: =IF(E31="PREMIUM",Inputs!$B$9,IF(E31="WORKHORSE",Inputs!$B$10,IF(E31="ECONOMY",Inputs!$B$11,E31))) -> anthropic/claude-opus-5.5 | Q31: =IF(K31<>"",K31,IF(F31="",0,IFERROR(INDEX(Inputs!$B$42:$D$44,MATCH(E31,Inputs!$A$42:$A$44,0),IF(F31="low",1,IF(F31="medium",2,3))),0))) -> 3000 | R31: =IF(P31="",0,INDEX('Vendor Prices'!$G$5:$G$58,MATCH(P31,'Vendor Prices'!$A$5:$A$58,0))) -> 4 | S31: =IF(P31="",0,INDEX('Vendor Prices'!$H$5:$H$58,MATCH(P31,'Vendor Prices'!$A$5:$A$58,0))) -> 20 | T31: =IF(P31="",0,IF(INDEX('Vendor Prices'!$I$5:$I$58,MATCH(P31,'Vendor Prices'!$A$5:$A$58,0))=0,R31,INDEX('Vendor Prices'!$I$5:$I$58,MATCH(P31,'Vendor Prices'!$A$5:$A$58,0)))) -> 0.2 | U31: =IF(LEFT(P31,10)="anthropic/",Inputs!$B$8,1) -> 1.15 | V31: =IF(P31="",0,I31*(G31*U31*((1-J31)*R31+J31*T31)+(H31+Q31)*U31*S31)/1000000*(1+Inputs!$B$7)) -> 0.19484795 | W31: =IF(E31="PREMIUM",Inputs!$B$12,IF(E31="WORKHORSE",Inputs!$B$13,IF(E31="ECONOMY",Inputs!$B$14,""))) -> google/gemini-3.8-flash | X31: =IF(W31="",V31,I31*(G31*((1-J31)*INDEX('Vendor Prices'!$G$5:$G$58,MATCH(W31,'Vendor Prices'!$A$5:$A$58,0))+J31*INDEX('Vendor Prices'!$I$5:$I$58,MATCH(W31,'Vendor Prices'!$A$5:$A$58,0)))+(H31+Q31)*INDEX('Vendor Prices'!$H$5:$H$58,MATCH(W31,'Vendor Prices'!$A$5:$A$58,0)))/1000000*(1+Inputs!$B$7)) -> 0.031768687 | Y31: =(1-Inputs!$B$15)*V31+Inputs!$B$15*X31 -> 0.18995557 | Z31: =L31*Inputs!$B$29 -> 0.0032 | AA31: =IF(M31="",0,N31*INDEX('Vendor Prices'!$G$5:$G$58,MATCH(M31,'Vendor Prices'!$A$5:$A$58,0))*(1+INDEX('Vendor Prices'!$J$5:$J$58,MATCH(M31,'Vendor Prices'!$A$5:$A$58,0))*Inputs!$B$7)) -> 0 | AB31: =Y31+Z31+AA31+O31 -> 0.19315557 | AC31: 1.6 | AD31: =AB31*AC31 -> 0.30904892
A32: article_long | B32: Studio | C32: Long-form article (~2,500 words) | D32: studio.article | E32: PREMIUM | F32: medium | G32: 6000 | H32: 6000 | I32: 1.1 | J32: 0 | L32: 1 | P32: =IF(E32="PREMIUM",Inputs!$B$9,IF(E32="WORKHORSE",Inputs!$B$10,IF(E32="ECONOMY",Inputs!$B$11,E32))) -> anthropic/claude-opus-5.5 | Q32: =IF(K32<>"",K32,IF(F32="",0,IFERROR(INDEX(Inputs!$B$42:$D$44,MATCH(E32,Inputs!$A$42:$A$44,0),IF(F32="low",1,IF(F32="medium",2,3))),0))) -> 3000 | R32: =IF(P32="",0,INDEX('Vendor Prices'!$G$5:$G$58,MATCH(P32,'Vendor Prices'!$A$5:$A$58,0))) -> 4 | S32: =IF(P32="",0,INDEX('Vendor Prices'!$H$5:$H$58,MATCH(P32,'Vendor Prices'!$A$5:$A$58,0))) -> 20 | T32: =IF(P32="",0,IF(INDEX('Vendor Prices'!$I$5:$I$58,MATCH(P32,'Vendor Prices'!$A$5:$A$58,0))=0,R32,INDEX('Vendor Prices'!$I$5:$I$58,MATCH(P32,'Vendor Prices'!$A$5:$A$58,0)))) -> 0.2 | U32: =IF(LEFT(P32,10)="anthropic/",Inputs!$B$8,1) -> 1.15 | V32: =IF(P32="",0,I32*(G32*U32*((1-J32)*R32+J32*T32)+(H32+Q32)*U32*S32)/1000000*(1+Inputs!$B$7)) -> 0.2722533 | W32: =IF(E32="PREMIUM",Inputs!$B$12,IF(E32="WORKHORSE",Inputs!$B$13,IF(E32="ECONOMY",Inputs!$B$14,""))) -> google/gemini-3.8-flash | X32: =IF(W32="",V32,I32*(G32*((1-J32)*INDEX('Vendor Prices'!$G$5:$G$58,MATCH(W32,'Vendor Prices'!$A$5:$A$58,0))+J32*INDEX('Vendor Prices'!$I$5:$I$58,MATCH(W32,'Vendor Prices'!$A$5:$A$58,0)))+(H32+Q32)*INDEX('Vendor Prices'!$H$5:$H$58,MATCH(W32,'Vendor Prices'!$A$5:$A$58,0)))/1000000*(1+Inputs!$B$7)) -> 0.044389125 | Y32: =(1-Inputs!$B$15)*V32+Inputs!$B$15*X32 -> 0.26541737 | Z32: =L32*Inputs!$B$29 -> 0.008 | AA32: =IF(M32="",0,N32*INDEX('Vendor Prices'!$G$5:$G$58,MATCH(M32,'Vendor Prices'!$A$5:$A$58,0))*(1+INDEX('Vendor Prices'!$J$5:$J$58,MATCH(M32,'Vendor Prices'!$A$5:$A$58,0))*Inputs!$B$7)) -> 0 | AB32: =Y32+Z32+AA32+O32 -> 0.27341737 | AC32: 1.4 | AD32: =AB32*AC32 -> 0.38278432
A33: article_std | B33: Studio | C33: Standard article on WORKHORSE (suggested option) | D33: studio.article.standard (proposed) | E33: WORKHORSE | F33: medium | G33: 5500 | H33: 3200 | I33: 1.1 | J33: 0 | L33: 0.4 | P33: =IF(E33="PREMIUM",Inputs!$B$9,IF(E33="WORKHORSE",Inputs!$B$10,IF(E33="ECONOMY",Inputs!$B$11,E33))) -> google/gemini-3.8-flash | Q33: =IF(K33<>"",K33,IF(F33="",0,IFERROR(INDEX(Inputs!$B$42:$D$44,MATCH(E33,Inputs!$A$42:$A$44,0),IF(F33="low",1,IF(F33="medium",2,3))),0))) -> 1800 | R33: =IF(P33="",0,INDEX('Vendor Prices'!$G$5:$G$58,MATCH(P33,'Vendor Prices'!$A$5:$A$58,0))) -> 0.75 | S33: =IF(P33="",0,INDEX('Vendor Prices'!$H$5:$H$58,MATCH(P33,'Vendor Prices'!$A$5:$A$58,0))) -> 3.75 | T33: =IF(P33="",0,IF(INDEX('Vendor Prices'!$I$5:$I$58,MATCH(P33,'Vendor Prices'!$A$5:$A$58,0))=0,R33,INDEX('Vendor Prices'!$I$5:$I$58,MATCH(P33,'Vendor Prices'!$A$5:$A$58,0)))) -> 0.1875 | U33: =IF(LEFT(P33,10)="anthropic/",Inputs!$B$8,1) -> 1 | V33: =IF(P33="",0,I33*(G33*U33*((1-J33)*R33+J33*T33)+(H33+Q33)*U33*S33)/1000000*(1+Inputs!$B$7)) -> 0.026546437 | W33: =IF(E33="PREMIUM",Inputs!$B$12,IF(E33="WORKHORSE",Inputs!$B$13,IF(E33="ECONOMY",Inputs!$B$14,""))) -> openai/gpt-5.6-terra | X33: =IF(W33="",V33,I33*(G33*((1-J33)*INDEX('Vendor Prices'!$G$5:$G$58,MATCH(W33,'Vendor Prices'!$A$5:$A$58,0))+J33*INDEX('Vendor Prices'!$I$5:$I$58,MATCH(W33,'Vendor Prices'!$A$5:$A$58,0)))+(H33+Q33)*INDEX('Vendor Prices'!$H$5:$H$58,MATCH(W33,'Vendor Prices'!$A$5:$A$58,0)))/1000000*(1+Inputs!$B$7)) -> 0.0823955 | Y33: =(1-Inputs!$B$15)*V33+Inputs!$B$15*X33 -> 0.028221909 | Z33: =L33*Inputs!$B$29 -> 0.0032 | AA33: =IF(M33="",0,N33*INDEX('Vendor Prices'!$G$5:$G$58,MATCH(M33,'Vendor Prices'!$A$5:$A$58,0))*(1+INDEX('Vendor Prices'!$J$5:$J$58,MATCH(M33,'Vendor Prices'!$A$5:$A$58,0))*Inputs!$B$7)) -> 0 | AB33: =Y33+Z33+AA33+O33 -> 0.031421909 | AC33: 1.5 | AD33: =AB33*AC33 -> 0.047132864 | AE33: Not in the spec: a cheaper tier for everyday blog posts
A34: script | B34: Studio | C34: Video script | D34: studio.script | E34: WORKHORSE | F34: medium | G34: 4500 | H34: 1800 | I34: 1.1 | J34: 0 | L34: 0 | P34: =IF(E34="PREMIUM",Inputs!$B$9,IF(E34="WORKHORSE",Inputs!$B$10,IF(E34="ECONOMY",Inputs!$B$11,E34))) -> google/gemini-3.8-flash | Q34: =IF(K34<>"",K34,IF(F34="",0,IFERROR(INDEX(Inputs!$B$42:$D$44,MATCH(E34,Inputs!$A$42:$A$44,0),IF(F34="low",1,IF(F34="medium",2,3))),0))) -> 1800 | R34: =IF(P34="",0,INDEX('Vendor Prices'!$G$5:$G$58,MATCH(P34,'Vendor Prices'!$A$5:$A$58,0))) -> 0.75 | S34: =IF(P34="",0,INDEX('Vendor Prices'!$H$5:$H$58,MATCH(P34,'Vendor Prices'!$A$5:$A$58,0))) -> 3.75 | T34: =IF(P34="",0,IF(INDEX('Vendor Prices'!$I$5:$I$58,MATCH(P34,'Vendor Prices'!$A$5:$A$58,0))=0,R34,INDEX('Vendor Prices'!$I$5:$I$58,MATCH(P34,'Vendor Prices'!$A$5:$A$58,0)))) -> 0.1875 | U34: =IF(LEFT(P34,10)="anthropic/",Inputs!$B$8,1) -> 1 | V34: =IF(P34="",0,I34*(G34*U34*((1-J34)*R34+J34*T34)+(H34+Q34)*U34*S34)/1000000*(1+Inputs!$B$7)) -> 0.019583437 | W34: =IF(E34="PREMIUM",Inputs!$B$12,IF(E34="WORKHORSE",Inputs!$B$13,IF(E34="ECONOMY",Inputs!$B$14,""))) -> openai/gpt-5.6-terra | X34: =IF(W34="",V34,I34*(G34*((1-J34)*INDEX('Vendor Prices'!$G$5:$G$58,MATCH(W34,'Vendor Prices'!$A$5:$A$58,0))+J34*INDEX('Vendor Prices'!$I$5:$I$58,MATCH(W34,'Vendor Prices'!$A$5:$A$58,0)))+(H34+Q34)*INDEX('Vendor Prices'!$H$5:$H$58,MATCH(W34,'Vendor Prices'!$A$5:$A$58,0)))/1000000*(1+Inputs!$B$7)) -> 0.0605781 | Y34: =(1-Inputs!$B$15)*V34+Inputs!$B$15*X34 -> 0.020813277 | Z34: =L34*Inputs!$B$29 -> 0 | AA34: =IF(M34="",0,N34*INDEX('Vendor Prices'!$G$5:$G$58,MATCH(M34,'Vendor Prices'!$A$5:$A$58,0))*(1+INDEX('Vendor Prices'!$J$5:$J$58,MATCH(M34,'Vendor Prices'!$A$5:$A$58,0))*Inputs!$B$7)) -> 0 | AB34: =Y34+Z34+AA34+O34 -> 0.020813277 | AC34: 1.5 | AD34: =AB34*AC34 -> 0.031219916
A35: ideas | B35: Studio | C35: Content ideas batch | D35: studio.ideas | E35: WORKHORSE | F35: low | G35: 4500 | H35: 2000 | I35: 1 | J35: 0 | L35: 0 | P35: =IF(E35="PREMIUM",Inputs!$B$9,IF(E35="WORKHORSE",Inputs!$B$10,IF(E35="ECONOMY",Inputs!$B$11,E35))) -> google/gemini-3.8-flash | Q35: =IF(K35<>"",K35,IF(F35="",0,IFERROR(INDEX(Inputs!$B$42:$D$44,MATCH(E35,Inputs!$A$42:$A$44,0),IF(F35="low",1,IF(F35="medium",2,3))),0))) -> 500 | R35: =IF(P35="",0,INDEX('Vendor Prices'!$G$5:$G$58,MATCH(P35,'Vendor Prices'!$A$5:$A$58,0))) -> 0.75 | S35: =IF(P35="",0,INDEX('Vendor Prices'!$H$5:$H$58,MATCH(P35,'Vendor Prices'!$A$5:$A$58,0))) -> 3.75 | T35: =IF(P35="",0,IF(INDEX('Vendor Prices'!$I$5:$I$58,MATCH(P35,'Vendor Prices'!$A$5:$A$58,0))=0,R35,INDEX('Vendor Prices'!$I$5:$I$58,MATCH(P35,'Vendor Prices'!$A$5:$A$58,0)))) -> 0.1875 | U35: =IF(LEFT(P35,10)="anthropic/",Inputs!$B$8,1) -> 1 | V35: =IF(P35="",0,I35*(G35*U35*((1-J35)*R35+J35*T35)+(H35+Q35)*U35*S35)/1000000*(1+Inputs!$B$7)) -> 0.01345125 | W35: =IF(E35="PREMIUM",Inputs!$B$12,IF(E35="WORKHORSE",Inputs!$B$13,IF(E35="ECONOMY",Inputs!$B$14,""))) -> openai/gpt-5.6-terra | X35: =IF(W35="",V35,I35*(G35*((1-J35)*INDEX('Vendor Prices'!$G$5:$G$58,MATCH(W35,'Vendor Prices'!$A$5:$A$58,0))+J35*INDEX('Vendor Prices'!$I$5:$I$58,MATCH(W35,'Vendor Prices'!$A$5:$A$58,0)))+(H35+Q35)*INDEX('Vendor Prices'!$H$5:$H$58,MATCH(W35,'Vendor Prices'!$A$5:$A$58,0)))/1000000*(1+Inputs!$B$7)) -> 0.041145 | Y35: =(1-Inputs!$B$15)*V35+Inputs!$B$15*X35 -> 0.014282062 | Z35: =L35*Inputs!$B$29 -> 0 | AA35: =IF(M35="",0,N35*INDEX('Vendor Prices'!$G$5:$G$58,MATCH(M35,'Vendor Prices'!$A$5:$A$58,0))*(1+INDEX('Vendor Prices'!$J$5:$J$58,MATCH(M35,'Vendor Prices'!$A$5:$A$58,0))*Inputs!$B$7)) -> 0 | AB35: =Y35+Z35+AA35+O35 -> 0.014282062 | AC35: 1.5 | AD35: =AB35*AC35 -> 0.021423094
A36: social_multi | B36: Studio | C36: Multi-platform variants (5 platforms) | D36: social.multi | E36: WORKHORSE | F36: medium | G36: 3500 | H36: 2000 | I36: 1 | J36: 0 | L36: 0 | P36: =IF(E36="PREMIUM",Inputs!$B$9,IF(E36="WORKHORSE",Inputs!$B$10,IF(E36="ECONOMY",Inputs!$B$11,E36))) -> google/gemini-3.8-flash | Q36: =IF(K36<>"",K36,IF(F36="",0,IFERROR(INDEX(Inputs!$B$42:$D$44,MATCH(E36,Inputs!$A$42:$A$44,0),IF(F36="low",1,IF(F36="medium",2,3))),0))) -> 1800 | R36: =IF(P36="",0,INDEX('Vendor Prices'!$G$5:$G$58,MATCH(P36,'Vendor Prices'!$A$5:$A$58,0))) -> 0.75 | S36: =IF(P36="",0,INDEX('Vendor Prices'!$H$5:$H$58,MATCH(P36,'Vendor Prices'!$A$5:$A$58,0))) -> 3.75 | T36: =IF(P36="",0,IF(INDEX('Vendor Prices'!$I$5:$I$58,MATCH(P36,'Vendor Prices'!$A$5:$A$58,0))=0,R36,INDEX('Vendor Prices'!$I$5:$I$58,MATCH(P36,'Vendor Prices'!$A$5:$A$58,0)))) -> 0.1875 | U36: =IF(LEFT(P36,10)="anthropic/",Inputs!$B$8,1) -> 1 | V36: =IF(P36="",0,I36*(G36*U36*((1-J36)*R36+J36*T36)+(H36+Q36)*U36*S36)/1000000*(1+Inputs!$B$7)) -> 0.017803125 | W36: =IF(E36="PREMIUM",Inputs!$B$12,IF(E36="WORKHORSE",Inputs!$B$13,IF(E36="ECONOMY",Inputs!$B$14,""))) -> openai/gpt-5.6-terra | X36: =IF(W36="",V36,I36*(G36*((1-J36)*INDEX('Vendor Prices'!$G$5:$G$58,MATCH(W36,'Vendor Prices'!$A$5:$A$58,0))+J36*INDEX('Vendor Prices'!$I$5:$I$58,MATCH(W36,'Vendor Prices'!$A$5:$A$58,0)))+(H36+Q36)*INDEX('Vendor Prices'!$H$5:$H$58,MATCH(W36,'Vendor Prices'!$A$5:$A$58,0)))/1000000*(1+Inputs!$B$7)) -> 0.055493 | Y36: =(1-Inputs!$B$15)*V36+Inputs!$B$15*X36 -> 0.018933821 | Z36: =L36*Inputs!$B$29 -> 0 | AA36: =IF(M36="",0,N36*INDEX('Vendor Prices'!$G$5:$G$58,MATCH(M36,'Vendor Prices'!$A$5:$A$58,0))*(1+INDEX('Vendor Prices'!$J$5:$J$58,MATCH(M36,'Vendor Prices'!$A$5:$A$58,0))*Inputs!$B$7)) -> 0 | AB36: =Y36+Z36+AA36+O36 -> 0.018933821 | AC36: 1.5 | AD36: =AB36*AC36 -> 0.028400732
A37: campaign | B37: Studio | C37: Campaign plan | D37: campaign-generation | E37: PREMIUM | F37: low | G37: 6000 | H37: 2500 | I37: 1 | J37: 0 | L37: 0 | P37: =IF(E37="PREMIUM",Inputs!$B$9,IF(E37="WORKHORSE",Inputs!$B$10,IF(E37="ECONOMY",Inputs!$B$11,E37))) -> anthropic/claude-opus-5.5 | Q37: =IF(K37<>"",K37,IF(F37="",0,IFERROR(INDEX(Inputs!$B$42:$D$44,MATCH(E37,Inputs!$A$42:$A$44,0),IF(F37="low",1,IF(F37="medium",2,3))),0))) -> 800 | R37: =IF(P37="",0,INDEX('Vendor Prices'!$G$5:$G$58,MATCH(P37,'Vendor Prices'!$A$5:$A$58,0))) -> 4 | S37: =IF(P37="",0,INDEX('Vendor Prices'!$H$5:$H$58,MATCH(P37,'Vendor Prices'!$A$5:$A$58,0))) -> 20 | T37: =IF(P37="",0,IF(INDEX('Vendor Prices'!$I$5:$I$58,MATCH(P37,'Vendor Prices'!$A$5:$A$58,0))=0,R37,INDEX('Vendor Prices'!$I$5:$I$58,MATCH(P37,'Vendor Prices'!$A$5:$A$58,0)))) -> 0.2 | U37: =IF(LEFT(P37,10)="anthropic/",Inputs!$B$8,1) -> 1.15 | V37: =IF(P37="",0,I37*(G37*U37*((1-J37)*R37+J37*T37)+(H37+Q37)*U37*S37)/1000000*(1+Inputs!$B$7)) -> 0.1091925 | W37: =IF(E37="PREMIUM",Inputs!$B$12,IF(E37="WORKHORSE",Inputs!$B$13,IF(E37="ECONOMY",Inputs!$B$14,""))) -> google/gemini-3.8-flash | X37: =IF(W37="",V37,I37*(G37*((1-J37)*INDEX('Vendor Prices'!$G$5:$G$58,MATCH(W37,'Vendor Prices'!$A$5:$A$58,0))+J37*INDEX('Vendor Prices'!$I$5:$I$58,MATCH(W37,'Vendor Prices'!$A$5:$A$58,0)))+(H37+Q37)*INDEX('Vendor Prices'!$H$5:$H$58,MATCH(W37,'Vendor Prices'!$A$5:$A$58,0)))/1000000*(1+Inputs!$B$7)) -> 0.017803125 | Y37: =(1-Inputs!$B$15)*V37+Inputs!$B$15*X37 -> 0.10645082 | Z37: =L37*Inputs!$B$29 -> 0 | AA37: =IF(M37="",0,N37*INDEX('Vendor Prices'!$G$5:$G$58,MATCH(M37,'Vendor Prices'!$A$5:$A$58,0))*(1+INDEX('Vendor Prices'!$J$5:$J$58,MATCH(M37,'Vendor Prices'!$A$5:$A$58,0))*Inputs!$B$7)) -> 0 | AB37: =Y37+Z37+AA37+O37 -> 0.10645082 | AC37: 1.5 | AD37: =AB37*AC37 -> 0.15967623
A38: coach | B38: Research | C38: Marketing Coach briefing | D38: coach.briefing (+ coach.research) | E38: PREMIUM | F38: low | G38: 9000 | H38: 4000 | I38: 1.05 | J38: 0 | L38: 3 | O38: =$AB$9 -> 0.0079750088 | P38: =IF(E38="PREMIUM",Inputs!$B$9,IF(E38="WORKHORSE",Inputs!$B$10,IF(E38="ECONOMY",Inputs!$B$11,E38))) -> anthropic/claude-opus-5.5 | Q38: =IF(K38<>"",K38,IF(F38="",0,IFERROR(INDEX(Inputs!$B$42:$D$44,MATCH(E38,Inputs!$A$42:$A$44,0),IF(F38="low",1,IF(F38="medium",2,3))),0))) -> 800 | R38: =IF(P38="",0,INDEX('Vendor Prices'!$G$5:$G$58,MATCH(P38,'Vendor Prices'!$A$5:$A$58,0))) -> 4 | S38: =IF(P38="",0,INDEX('Vendor Prices'!$H$5:$H$58,MATCH(P38,'Vendor Prices'!$A$5:$A$58,0))) -> 20 | T38: =IF(P38="",0,IF(INDEX('Vendor Prices'!$I$5:$I$58,MATCH(P38,'Vendor Prices'!$A$5:$A$58,0))=0,R38,INDEX('Vendor Prices'!$I$5:$I$58,MATCH(P38,'Vendor Prices'!$A$5:$A$58,0)))) -> 0.2 | U38: =IF(LEFT(P38,10)="anthropic/",Inputs!$B$8,1) -> 1.15 | V38: =IF(P38="",0,I38*(G38*U38*((1-J38)*R38+J38*T38)+(H38+Q38)*U38*S38)/1000000*(1+Inputs!$B$7)) -> 0.16815645 | W38: =IF(E38="PREMIUM",Inputs!$B$12,IF(E38="WORKHORSE",Inputs!$B$13,IF(E38="ECONOMY",Inputs!$B$14,""))) -> google/gemini-3.8-flash | X38: =IF(W38="",V38,I38*(G38*((1-J38)*INDEX('Vendor Prices'!$G$5:$G$58,MATCH(W38,'Vendor Prices'!$A$5:$A$58,0))+J38*INDEX('Vendor Prices'!$I$5:$I$58,MATCH(W38,'Vendor Prices'!$A$5:$A$58,0)))+(H38+Q38)*INDEX('Vendor Prices'!$H$5:$H$58,MATCH(W38,'Vendor Prices'!$A$5:$A$58,0)))/1000000*(1+Inputs!$B$7)) -> 0.027416812 | Y38: =(1-Inputs!$B$15)*V38+Inputs!$B$15*X38 -> 0.16393426 | Z38: =L38*Inputs!$B$29 -> 0.024 | AA38: =IF(M38="",0,N38*INDEX('Vendor Prices'!$G$5:$G$58,MATCH(M38,'Vendor Prices'!$A$5:$A$58,0))*(1+INDEX('Vendor Prices'!$J$5:$J$58,MATCH(M38,'Vendor Prices'!$A$5:$A$58,0))*Inputs!$B$7)) -> 0 | AB38: =Y38+Z38+AA38+O38 -> 0.19590927 | AC38: 1.5 | AD38: =AB38*AC38 -> 0.2938639
A39: coach_deep | B39: Research | C39: Deep strategy (Coach, high effort) | D39: coach (escalated) | E39: PREMIUM | F39: high | G39: 9000 | H39: 4000 | I39: 1.05 | J39: 0 | L39: 3 | O39: =$AB$9 -> 0.0079750088 | P39: =IF(E39="PREMIUM",Inputs!$B$9,IF(E39="WORKHORSE",Inputs!$B$10,IF(E39="ECONOMY",Inputs!$B$11,E39))) -> anthropic/claude-opus-5.5 | Q39: =IF(K39<>"",K39,IF(F39="",0,IFERROR(INDEX(Inputs!$B$42:$D$44,MATCH(E39,Inputs!$A$42:$A$44,0),IF(F39="low",1,IF(F39="medium",2,3))),0))) -> 8000 | R39: =IF(P39="",0,INDEX('Vendor Prices'!$G$5:$G$58,MATCH(P39,'Vendor Prices'!$A$5:$A$58,0))) -> 4 | S39: =IF(P39="",0,INDEX('Vendor Prices'!$H$5:$H$58,MATCH(P39,'Vendor Prices'!$A$5:$A$58,0))) -> 20 | T39: =IF(P39="",0,IF(INDEX('Vendor Prices'!$I$5:$I$58,MATCH(P39,'Vendor Prices'!$A$5:$A$58,0))=0,R39,INDEX('Vendor Prices'!$I$5:$I$58,MATCH(P39,'Vendor Prices'!$A$5:$A$58,0)))) -> 0.2 | U39: =IF(LEFT(P39,10)="anthropic/",Inputs!$B$8,1) -> 1.15 | V39: =IF(P39="",0,I39*(G39*U39*((1-J39)*R39+J39*T39)+(H39+Q39)*U39*S39)/1000000*(1+Inputs!$B$7)) -> 0.35159985 | W39: =IF(E39="PREMIUM",Inputs!$B$12,IF(E39="WORKHORSE",Inputs!$B$13,IF(E39="ECONOMY",Inputs!$B$14,""))) -> google/gemini-3.8-flash | X39: =IF(W39="",V39,I39*(G39*((1-J39)*INDEX('Vendor Prices'!$G$5:$G$58,MATCH(W39,'Vendor Prices'!$A$5:$A$58,0))+J39*INDEX('Vendor Prices'!$I$5:$I$58,MATCH(W39,'Vendor Prices'!$A$5:$A$58,0)))+(H39+Q39)*INDEX('Vendor Prices'!$H$5:$H$58,MATCH(W39,'Vendor Prices'!$A$5:$A$58,0)))/1000000*(1+Inputs!$B$7)) -> 0.057326062 | Y39: =(1-Inputs!$B$15)*V39+Inputs!$B$15*X39 -> 0.34277164 | Z39: =L39*Inputs!$B$29 -> 0.024 | AA39: =IF(M39="",0,N39*INDEX('Vendor Prices'!$G$5:$G$58,MATCH(M39,'Vendor Prices'!$A$5:$A$58,0))*(1+INDEX('Vendor Prices'!$J$5:$J$58,MATCH(M39,'Vendor Prices'!$A$5:$A$58,0))*Inputs!$B$7)) -> 0 | AB39: =Y39+Z39+AA39+O39 -> 0.37474665 | AC39: 1.4 | AD39: =AB39*AC39 -> 0.5246453
A40: market_brain | B40: Research | C40: Market Brain refresh | D40: market-intelligence | E40: PREMIUM | F40: medium | G40: 8000 | H40: 4000 | I40: 1 | J40: 0 | L40: 5 | P40: =IF(E40="PREMIUM",Inputs!$B$9,IF(E40="WORKHORSE",Inputs!$B$10,IF(E40="ECONOMY",Inputs!$B$11,E40))) -> anthropic/claude-opus-5.5 | Q40: =IF(K40<>"",K40,IF(F40="",0,IFERROR(INDEX(Inputs!$B$42:$D$44,MATCH(E40,Inputs!$A$42:$A$44,0),IF(F40="low",1,IF(F40="medium",2,3))),0))) -> 3000 | R40: =IF(P40="",0,INDEX('Vendor Prices'!$G$5:$G$58,MATCH(P40,'Vendor Prices'!$A$5:$A$58,0))) -> 4 | S40: =IF(P40="",0,INDEX('Vendor Prices'!$H$5:$H$58,MATCH(P40,'Vendor Prices'!$A$5:$A$58,0))) -> 20 | T40: =IF(P40="",0,IF(INDEX('Vendor Prices'!$I$5:$I$58,MATCH(P40,'Vendor Prices'!$A$5:$A$58,0))=0,R40,INDEX('Vendor Prices'!$I$5:$I$58,MATCH(P40,'Vendor Prices'!$A$5:$A$58,0)))) -> 0.2 | U40: =IF(LEFT(P40,10)="anthropic/",Inputs!$B$8,1) -> 1.15 | V40: =IF(P40="",0,I40*(G40*U40*((1-J40)*R40+J40*T40)+(H40+Q40)*U40*S40)/1000000*(1+Inputs!$B$7)) -> 0.208679 | W40: =IF(E40="PREMIUM",Inputs!$B$12,IF(E40="WORKHORSE",Inputs!$B$13,IF(E40="ECONOMY",Inputs!$B$14,""))) -> google/gemini-3.8-flash | X40: =IF(W40="",V40,I40*(G40*((1-J40)*INDEX('Vendor Prices'!$G$5:$G$58,MATCH(W40,'Vendor Prices'!$A$5:$A$58,0))+J40*INDEX('Vendor Prices'!$I$5:$I$58,MATCH(W40,'Vendor Prices'!$A$5:$A$58,0)))+(H40+Q40)*INDEX('Vendor Prices'!$H$5:$H$58,MATCH(W40,'Vendor Prices'!$A$5:$A$58,0)))/1000000*(1+Inputs!$B$7)) -> 0.03402375 | Y40: =(1-Inputs!$B$15)*V40+Inputs!$B$15*X40 -> 0.20343934 | Z40: =L40*Inputs!$B$29 -> 0.04 | AA40: =IF(M40="",0,N40*INDEX('Vendor Prices'!$G$5:$G$58,MATCH(M40,'Vendor Prices'!$A$5:$A$58,0))*(1+INDEX('Vendor Prices'!$J$5:$J$58,MATCH(M40,'Vendor Prices'!$A$5:$A$58,0))*Inputs!$B$7)) -> 0 | AB40: =Y40+Z40+AA40+O40 -> 0.24343934 | AC40: 1.6 | AD40: =AB40*AC40 -> 0.38950295 | AE40: Source-content cache avoids re-billing identical evidence
A41: comp_disc | B41: Research | C41: Competitor discovery | D41: competitors.discovery | E41: WORKHORSE | F41: low | G41: 7000 | H41: 2500 | I41: 1.05 | J41: 0 | L41: 4 | P41: =IF(E41="PREMIUM",Inputs!$B$9,IF(E41="WORKHORSE",Inputs!$B$10,IF(E41="ECONOMY",Inputs!$B$11,E41))) -> google/gemini-3.8-flash | Q41: =IF(K41<>"",K41,IF(F41="",0,IFERROR(INDEX(Inputs!$B$42:$D$44,MATCH(E41,Inputs!$A$42:$A$44,0),IF(F41="low",1,IF(F41="medium",2,3))),0))) -> 500 | R41: =IF(P41="",0,INDEX('Vendor Prices'!$G$5:$G$58,MATCH(P41,'Vendor Prices'!$A$5:$A$58,0))) -> 0.75 | S41: =IF(P41="",0,INDEX('Vendor Prices'!$H$5:$H$58,MATCH(P41,'Vendor Prices'!$A$5:$A$58,0))) -> 3.75 | T41: =IF(P41="",0,IF(INDEX('Vendor Prices'!$I$5:$I$58,MATCH(P41,'Vendor Prices'!$A$5:$A$58,0))=0,R41,INDEX('Vendor Prices'!$I$5:$I$58,MATCH(P41,'Vendor Prices'!$A$5:$A$58,0)))) -> 0.1875 | U41: =IF(LEFT(P41,10)="anthropic/",Inputs!$B$8,1) -> 1 | V41: =IF(P41="",0,I41*(G41*U41*((1-J41)*R41+J41*T41)+(H41+Q41)*U41*S41)/1000000*(1+Inputs!$B$7)) -> 0.018277875 | W41: =IF(E41="PREMIUM",Inputs!$B$12,IF(E41="WORKHORSE",Inputs!$B$13,IF(E41="ECONOMY",Inputs!$B$14,""))) -> openai/gpt-5.6-terra | X41: =IF(W41="",V41,I41*(G41*((1-J41)*INDEX('Vendor Prices'!$G$5:$G$58,MATCH(W41,'Vendor Prices'!$A$5:$A$58,0))+J41*INDEX('Vendor Prices'!$I$5:$I$58,MATCH(W41,'Vendor Prices'!$A$5:$A$58,0)))+(H41+Q41)*INDEX('Vendor Prices'!$H$5:$H$58,MATCH(W41,'Vendor Prices'!$A$5:$A$58,0)))/1000000*(1+Inputs!$B$7)) -> 0.0553875 | Y41: =(1-Inputs!$B$15)*V41+Inputs!$B$15*X41 -> 0.019391164 | Z41: =L41*Inputs!$B$29 -> 0.032 | AA41: =IF(M41="",0,N41*INDEX('Vendor Prices'!$G$5:$G$58,MATCH(M41,'Vendor Prices'!$A$5:$A$58,0))*(1+INDEX('Vendor Prices'!$J$5:$J$58,MATCH(M41,'Vendor Prices'!$A$5:$A$58,0))*Inputs!$B$7)) -> 0 | AB41: =Y41+Z41+AA41+O41 -> 0.051391164 | AC41: 1.5 | AD41: =AB41*AC41 -> 0.077086746
A42: comp_profile | B42: Research | C42: Competitor profile | D42: competitors.profile | E42: WORKHORSE | F42: low | G42: 5000 | H42: 2000 | I42: 1 | J42: 0 | L42: 2 | P42: =IF(E42="PREMIUM",Inputs!$B$9,IF(E42="WORKHORSE",Inputs!$B$10,IF(E42="ECONOMY",Inputs!$B$11,E42))) -> google/gemini-3.8-flash | Q42: =IF(K42<>"",K42,IF(F42="",0,IFERROR(INDEX(Inputs!$B$42:$D$44,MATCH(E42,Inputs!$A$42:$A$44,0),IF(F42="low",1,IF(F42="medium",2,3))),0))) -> 500 | R42: =IF(P42="",0,INDEX('Vendor Prices'!$G$5:$G$58,MATCH(P42,'Vendor Prices'!$A$5:$A$58,0))) -> 0.75 | S42: =IF(P42="",0,INDEX('Vendor Prices'!$H$5:$H$58,MATCH(P42,'Vendor Prices'!$A$5:$A$58,0))) -> 3.75 | T42: =IF(P42="",0,IF(INDEX('Vendor Prices'!$I$5:$I$58,MATCH(P42,'Vendor Prices'!$A$5:$A$58,0))=0,R42,INDEX('Vendor Prices'!$I$5:$I$58,MATCH(P42,'Vendor Prices'!$A$5:$A$58,0)))) -> 0.1875 | U42: =IF(LEFT(P42,10)="anthropic/",Inputs!$B$8,1) -> 1 | V42: =IF(P42="",0,I42*(G42*U42*((1-J42)*R42+J42*T42)+(H42+Q42)*U42*S42)/1000000*(1+Inputs!$B$7)) -> 0.013846875 | W42: =IF(E42="PREMIUM",Inputs!$B$12,IF(E42="WORKHORSE",Inputs!$B$13,IF(E42="ECONOMY",Inputs!$B$14,""))) -> openai/gpt-5.6-terra | X42: =IF(W42="",V42,I42*(G42*((1-J42)*INDEX('Vendor Prices'!$G$5:$G$58,MATCH(W42,'Vendor Prices'!$A$5:$A$58,0))+J42*INDEX('Vendor Prices'!$I$5:$I$58,MATCH(W42,'Vendor Prices'!$A$5:$A$58,0)))+(H42+Q42)*INDEX('Vendor Prices'!$H$5:$H$58,MATCH(W42,'Vendor Prices'!$A$5:$A$58,0)))/1000000*(1+Inputs!$B$7)) -> 0.0422 | Y42: =(1-Inputs!$B$15)*V42+Inputs!$B$15*X42 -> 0.014697469 | Z42: =L42*Inputs!$B$29 -> 0.016 | AA42: =IF(M42="",0,N42*INDEX('Vendor Prices'!$G$5:$G$58,MATCH(M42,'Vendor Prices'!$A$5:$A$58,0))*(1+INDEX('Vendor Prices'!$J$5:$J$58,MATCH(M42,'Vendor Prices'!$A$5:$A$58,0))*Inputs!$B$7)) -> 0 | AB42: =Y42+Z42+AA42+O42 -> 0.030697469 | AC42: 1.5 | AD42: =AB42*AC42 -> 0.046046203
A43: comp_sweep | B43: Research | C43: Competitor update sweep (1 competitor) | D43: competitors.updates | E43: ECONOMY | F43: low | G43: 5000 | H43: 1500 | I43: 0.6 | J43: 0 | L43: 2 | P43: =IF(E43="PREMIUM",Inputs!$B$9,IF(E43="WORKHORSE",Inputs!$B$10,IF(E43="ECONOMY",Inputs!$B$11,E43))) -> google/gemini-3.1-flash-lite | Q43: =IF(K43<>"",K43,IF(F43="",0,IFERROR(INDEX(Inputs!$B$42:$D$44,MATCH(E43,Inputs!$A$42:$A$44,0),IF(F43="low",1,IF(F43="medium",2,3))),0))) -> 200 | R43: =IF(P43="",0,INDEX('Vendor Prices'!$G$5:$G$58,MATCH(P43,'Vendor Prices'!$A$5:$A$58,0))) -> 0.25 | S43: =IF(P43="",0,INDEX('Vendor Prices'!$H$5:$H$58,MATCH(P43,'Vendor Prices'!$A$5:$A$58,0))) -> 1.5 | T43: =IF(P43="",0,IF(INDEX('Vendor Prices'!$I$5:$I$58,MATCH(P43,'Vendor Prices'!$A$5:$A$58,0))=0,R43,INDEX('Vendor Prices'!$I$5:$I$58,MATCH(P43,'Vendor Prices'!$A$5:$A$58,0)))) -> 0.0625 | U43: =IF(LEFT(P43,10)="anthropic/",Inputs!$B$8,1) -> 1 | V43: =IF(P43="",0,I43*(G43*U43*((1-J43)*R43+J43*T43)+(H43+Q43)*U43*S43)/1000000*(1+Inputs!$B$7)) -> 0.0024054 | W43: =IF(E43="PREMIUM",Inputs!$B$12,IF(E43="WORKHORSE",Inputs!$B$13,IF(E43="ECONOMY",Inputs!$B$14,""))) -> openai/gpt-5.6-luna | X43: =IF(W43="",V43,I43*(G43*((1-J43)*INDEX('Vendor Prices'!$G$5:$G$58,MATCH(W43,'Vendor Prices'!$A$5:$A$58,0))+J43*INDEX('Vendor Prices'!$I$5:$I$58,MATCH(W43,'Vendor Prices'!$A$5:$A$58,0)))+(H43+Q43)*INDEX('Vendor Prices'!$H$5:$H$58,MATCH(W43,'Vendor Prices'!$A$5:$A$58,0)))/1000000*(1+Inputs!$B$7)) -> 0.00192432 | Y43: =(1-Inputs!$B$15)*V43+Inputs!$B$15*X43 -> 0.0023909676 | Z43: =L43*Inputs!$B$29 -> 0.016 | AA43: =IF(M43="",0,N43*INDEX('Vendor Prices'!$G$5:$G$58,MATCH(M43,'Vendor Prices'!$A$5:$A$58,0))*(1+INDEX('Vendor Prices'!$J$5:$J$58,MATCH(M43,'Vendor Prices'!$A$5:$A$58,0))*Inputs!$B$7)) -> 0 | AB43: =Y43+Z43+AA43+O43 -> 0.018390968 | AC43: 2 | AD43: =AB43*AC43 -> 0.036781935 | AE43: Model runs only when something new appears
A44: comp_intel | B44: Research | C44: Competitor intelligence report | D44: competitor-intel | E44: WORKHORSE | F44: medium | G44: 10000 | H44: 4000 | I44: 1 | J44: 0 | L44: 3 | P44: =IF(E44="PREMIUM",Inputs!$B$9,IF(E44="WORKHORSE",Inputs!$B$10,IF(E44="ECONOMY",Inputs!$B$11,E44))) -> google/gemini-3.8-flash | Q44: =IF(K44<>"",K44,IF(F44="",0,IFERROR(INDEX(Inputs!$B$42:$D$44,MATCH(E44,Inputs!$A$42:$A$44,0),IF(F44="low",1,IF(F44="medium",2,3))),0))) -> 1800 | R44: =IF(P44="",0,INDEX('Vendor Prices'!$G$5:$G$58,MATCH(P44,'Vendor Prices'!$A$5:$A$58,0))) -> 0.75 | S44: =IF(P44="",0,INDEX('Vendor Prices'!$H$5:$H$58,MATCH(P44,'Vendor Prices'!$A$5:$A$58,0))) -> 3.75 | T44: =IF(P44="",0,IF(INDEX('Vendor Prices'!$I$5:$I$58,MATCH(P44,'Vendor Prices'!$A$5:$A$58,0))=0,R44,INDEX('Vendor Prices'!$I$5:$I$58,MATCH(P44,'Vendor Prices'!$A$5:$A$58,0)))) -> 0.1875 | U44: =IF(LEFT(P44,10)="anthropic/",Inputs!$B$8,1) -> 1 | V44: =IF(P44="",0,I44*(G44*U44*((1-J44)*R44+J44*T44)+(H44+Q44)*U44*S44)/1000000*(1+Inputs!$B$7)) -> 0.03085875 | W44: =IF(E44="PREMIUM",Inputs!$B$12,IF(E44="WORKHORSE",Inputs!$B$13,IF(E44="ECONOMY",Inputs!$B$14,""))) -> openai/gpt-5.6-terra | X44: =IF(W44="",V44,I44*(G44*((1-J44)*INDEX('Vendor Prices'!$G$5:$G$58,MATCH(W44,'Vendor Prices'!$A$5:$A$58,0))+J44*INDEX('Vendor Prices'!$I$5:$I$58,MATCH(W44,'Vendor Prices'!$A$5:$A$58,0)))+(H44+Q44)*INDEX('Vendor Prices'!$H$5:$H$58,MATCH(W44,'Vendor Prices'!$A$5:$A$58,0)))/1000000*(1+Inputs!$B$7)) -> 0.094528 | Y44: =(1-Inputs!$B$15)*V44+Inputs!$B$15*X44 -> 0.032768828 | Z44: =L44*Inputs!$B$29 -> 0.024 | AA44: =IF(M44="",0,N44*INDEX('Vendor Prices'!$G$5:$G$58,MATCH(M44,'Vendor Prices'!$A$5:$A$58,0))*(1+INDEX('Vendor Prices'!$J$5:$J$58,MATCH(M44,'Vendor Prices'!$A$5:$A$58,0))*Inputs!$B$7)) -> 0 | AB44: =Y44+Z44+AA44+O44 -> 0.056768828 | AC44: 1.5 | AD44: =AB44*AC44 -> 0.085153241
A45: insights | B45: Research | C45: Analytics insight refresh | D45: analytics/insights | E45: WORKHORSE | F45: medium | G45: 5000 | H45: 1200 | I45: 1 | J45: 0 | L45: 0 | P45: =IF(E45="PREMIUM",Inputs!$B$9,IF(E45="WORKHORSE",Inputs!$B$10,IF(E45="ECONOMY",Inputs!$B$11,E45))) -> google/gemini-3.8-flash | Q45: =IF(K45<>"",K45,IF(F45="",0,IFERROR(INDEX(Inputs!$B$42:$D$44,MATCH(E45,Inputs!$A$42:$A$44,0),IF(F45="low",1,IF(F45="medium",2,3))),0))) -> 1800 | R45: =IF(P45="",0,INDEX('Vendor Prices'!$G$5:$G$58,MATCH(P45,'Vendor Prices'!$A$5:$A$58,0))) -> 0.75 | S45: =IF(P45="",0,INDEX('Vendor Prices'!$H$5:$H$58,MATCH(P45,'Vendor Prices'!$A$5:$A$58,0))) -> 3.75 | T45: =IF(P45="",0,IF(INDEX('Vendor Prices'!$I$5:$I$58,MATCH(P45,'Vendor Prices'!$A$5:$A$58,0))=0,R45,INDEX('Vendor Prices'!$I$5:$I$58,MATCH(P45,'Vendor Prices'!$A$5:$A$58,0)))) -> 0.1875 | U45: =IF(LEFT(P45,10)="anthropic/",Inputs!$B$8,1) -> 1 | V45: =IF(P45="",0,I45*(G45*U45*((1-J45)*R45+J45*T45)+(H45+Q45)*U45*S45)/1000000*(1+Inputs!$B$7)) -> 0.015825 | W45: =IF(E45="PREMIUM",Inputs!$B$12,IF(E45="WORKHORSE",Inputs!$B$13,IF(E45="ECONOMY",Inputs!$B$14,""))) -> openai/gpt-5.6-terra | X45: =IF(W45="",V45,I45*(G45*((1-J45)*INDEX('Vendor Prices'!$G$5:$G$58,MATCH(W45,'Vendor Prices'!$A$5:$A$58,0))+J45*INDEX('Vendor Prices'!$I$5:$I$58,MATCH(W45,'Vendor Prices'!$A$5:$A$58,0)))+(H45+Q45)*INDEX('Vendor Prices'!$H$5:$H$58,MATCH(W45,'Vendor Prices'!$A$5:$A$58,0)))/1000000*(1+Inputs!$B$7)) -> 0.04853 | Y45: =(1-Inputs!$B$15)*V45+Inputs!$B$15*X45 -> 0.01680615 | Z45: =L45*Inputs!$B$29 -> 0 | AA45: =IF(M45="",0,N45*INDEX('Vendor Prices'!$G$5:$G$58,MATCH(M45,'Vendor Prices'!$A$5:$A$58,0))*(1+INDEX('Vendor Prices'!$J$5:$J$58,MATCH(M45,'Vendor Prices'!$A$5:$A$58,0))*Inputs!$B$7)) -> 0 | AB45: =Y45+Z45+AA45+O45 -> 0.01680615 | AC45: 1.5 | AD45: =AB45*AC45 -> 0.025209225
A46: site_scan | B46: AI Visibility | C46: Site scan, per 100 pages | D46: geo scan-runner + citation probes | G46: 0 | H46: 0 | I46: 1 | J46: 0 | L46: 5 | M46: compute-per-page | N46: 100 | P46: =IF(E46="PREMIUM",Inputs!$B$9,IF(E46="WORKHORSE",Inputs!$B$10,IF(E46="ECONOMY",Inputs!$B$11,E46))) -> 0 | Q46: =IF(K46<>"",K46,IF(F46="",0,IFERROR(INDEX(Inputs!$B$42:$D$44,MATCH(E46,Inputs!$A$42:$A$44,0),IF(F46="low",1,IF(F46="medium",2,3))),0))) -> 0 | R46: =IF(P46="",0,INDEX('Vendor Prices'!$G$5:$G$58,MATCH(P46,'Vendor Prices'!$A$5:$A$58,0))) -> 0 | S46: =IF(P46="",0,INDEX('Vendor Prices'!$H$5:$H$58,MATCH(P46,'Vendor Prices'!$A$5:$A$58,0))) -> 0 | T46: =IF(P46="",0,IF(INDEX('Vendor Prices'!$I$5:$I$58,MATCH(P46,'Vendor Prices'!$A$5:$A$58,0))=0,R46,INDEX('Vendor Prices'!$I$5:$I$58,MATCH(P46,'Vendor Prices'!$A$5:$A$58,0)))) -> 0 | U46: =IF(LEFT(P46,10)="anthropic/",Inputs!$B$8,1) -> 1 | V46: =IF(P46="",0,I46*(G46*U46*((1-J46)*R46+J46*T46)+(H46+Q46)*U46*S46)/1000000*(1+Inputs!$B$7)) -> 0 | W46: =IF(E46="PREMIUM",Inputs!$B$12,IF(E46="WORKHORSE",Inputs!$B$13,IF(E46="ECONOMY",Inputs!$B$14,""))) | X46: =IF(W46="",V46,I46*(G46*((1-J46)*INDEX('Vendor Prices'!$G$5:$G$58,MATCH(W46,'Vendor Prices'!$A$5:$A$58,0))+J46*INDEX('Vendor Prices'!$I$5:$I$58,MATCH(W46,'Vendor Prices'!$A$5:$A$58,0)))+(H46+Q46)*INDEX('Vendor Prices'!$H$5:$H$58,MATCH(W46,'Vendor Prices'!$A$5:$A$58,0)))/1000000*(1+Inputs!$B$7)) -> 0 | Y46: =(1-Inputs!$B$15)*V46+Inputs!$B$15*X46 -> 0 | Z46: =L46*Inputs!$B$29 -> 0.04 | AA46: =IF(M46="",0,N46*INDEX('Vendor Prices'!$G$5:$G$58,MATCH(M46,'Vendor Prices'!$A$5:$A$58,0))*(1+INDEX('Vendor Prices'!$J$5:$J$58,MATCH(M46,'Vendor Prices'!$A$5:$A$58,0))*Inputs!$B$7)) -> 0.03 | AB46: =Y46+Z46+AA46+O46 -> 0.07 | AC46: 3 | AD46: =AB46*AC46 -> 0.21
A47: probe_pplx | B47: AI Visibility | C47: Prompt check: Perplexity (Sonar) | D47: geo.probe | E47: perplexity/sonar | G47: 150 | H47: 600 | I47: 1 | J47: 0 | K47: 0 | L47: 0 | M47: sonar-request-low | N47: 1 | P47: =IF(E47="PREMIUM",Inputs!$B$9,IF(E47="WORKHORSE",Inputs!$B$10,IF(E47="ECONOMY",Inputs!$B$11,E47))) -> perplexity/sonar | Q47: =IF(K47<>"",K47,IF(F47="",0,IFERROR(INDEX(Inputs!$B$42:$D$44,MATCH(E47,Inputs!$A$42:$A$44,0),IF(F47="low",1,IF(F47="medium",2,3))),0))) -> 0 | R47: =IF(P47="",0,INDEX('Vendor Prices'!$G$5:$G$58,MATCH(P47,'Vendor Prices'!$A$5:$A$58,0))) -> 1 | S47: =IF(P47="",0,INDEX('Vendor Prices'!$H$5:$H$58,MATCH(P47,'Vendor Prices'!$A$5:$A$58,0))) -> 1 | T47: =IF(P47="",0,IF(INDEX('Vendor Prices'!$I$5:$I$58,MATCH(P47,'Vendor Prices'!$A$5:$A$58,0))=0,R47,INDEX('Vendor Prices'!$I$5:$I$58,MATCH(P47,'Vendor Prices'!$A$5:$A$58,0)))) -> 1 | U47: =IF(LEFT(P47,10)="anthropic/",Inputs!$B$8,1) -> 1 | V47: =IF(P47="",0,I47*(G47*U47*((1-J47)*R47+J47*T47)+(H47+Q47)*U47*S47)/1000000*(1+Inputs!$B$7)) -> 0.00079125 | W47: =IF(E47="PREMIUM",Inputs!$B$12,IF(E47="WORKHORSE",Inputs!$B$13,IF(E47="ECONOMY",Inputs!$B$14,""))) | X47: =IF(W47="",V47,I47*(G47*((1-J47)*INDEX('Vendor Prices'!$G$5:$G$58,MATCH(W47,'Vendor Prices'!$A$5:$A$58,0))+J47*INDEX('Vendor Prices'!$I$5:$I$58,MATCH(W47,'Vendor Prices'!$A$5:$A$58,0)))+(H47+Q47)*INDEX('Vendor Prices'!$H$5:$H$58,MATCH(W47,'Vendor Prices'!$A$5:$A$58,0)))/1000000*(1+Inputs!$B$7)) -> 0.00079125 | Y47: =(1-Inputs!$B$15)*V47+Inputs!$B$15*X47 -> 0.00079125 | Z47: =L47*Inputs!$B$29 -> 0 | AA47: =IF(M47="",0,N47*INDEX('Vendor Prices'!$G$5:$G$58,MATCH(M47,'Vendor Prices'!$A$5:$A$58,0))*(1+INDEX('Vendor Prices'!$J$5:$J$58,MATCH(M47,'Vendor Prices'!$A$5:$A$58,0))*Inputs!$B$7)) -> 0.005275 | AB47: =Y47+Z47+AA47+O47 -> 0.00606625 | AC47: 1.5 | AD47: =AB47*AC47 -> 0.009099375
A48: probe_luna | B48: AI Visibility | C48: Prompt check: 'ChatGPT' (GPT-5.6 Luna, no search) | D48: geo.probe | E48: openai/gpt-5.6-luna | G48: 150 | H48: 600 | I48: 1 | J48: 0 | K48: 500 | L48: 0 | P48: =IF(E48="PREMIUM",Inputs!$B$9,IF(E48="WORKHORSE",Inputs!$B$10,IF(E48="ECONOMY",Inputs!$B$11,E48))) -> openai/gpt-5.6-luna | Q48: =IF(K48<>"",K48,IF(F48="",0,IFERROR(INDEX(Inputs!$B$42:$D$44,MATCH(E48,Inputs!$A$42:$A$44,0),IF(F48="low",1,IF(F48="medium",2,3))),0))) -> 500 | R48: =IF(P48="",0,INDEX('Vendor Prices'!$G$5:$G$58,MATCH(P48,'Vendor Prices'!$A$5:$A$58,0))) -> 0.2 | S48: =IF(P48="",0,INDEX('Vendor Prices'!$H$5:$H$58,MATCH(P48,'Vendor Prices'!$A$5:$A$58,0))) -> 1.2 | T48: =IF(P48="",0,IF(INDEX('Vendor Prices'!$I$5:$I$58,MATCH(P48,'Vendor Prices'!$A$5:$A$58,0))=0,R48,INDEX('Vendor Prices'!$I$5:$I$58,MATCH(P48,'Vendor Prices'!$A$5:$A$58,0)))) -> 0.05 | U48: =IF(LEFT(P48,10)="anthropic/",Inputs!$B$8,1) -> 1 | V48: =IF(P48="",0,I48*(G48*U48*((1-J48)*R48+J48*T48)+(H48+Q48)*U48*S48)/1000000*(1+Inputs!$B$7)) -> 0.00142425 | W48: =IF(E48="PREMIUM",Inputs!$B$12,IF(E48="WORKHORSE",Inputs!$B$13,IF(E48="ECONOMY",Inputs!$B$14,""))) | X48: =IF(W48="",V48,I48*(G48*((1-J48)*INDEX('Vendor Prices'!$G$5:$G$58,MATCH(W48,'Vendor Prices'!$A$5:$A$58,0))+J48*INDEX('Vendor Prices'!$I$5:$I$58,MATCH(W48,'Vendor Prices'!$A$5:$A$58,0)))+(H48+Q48)*INDEX('Vendor Prices'!$H$5:$H$58,MATCH(W48,'Vendor Prices'!$A$5:$A$58,0)))/1000000*(1+Inputs!$B$7)) -> 0.00142425 | Y48: =(1-Inputs!$B$15)*V48+Inputs!$B$15*X48 -> 0.00142425 | Z48: =L48*Inputs!$B$29 -> 0 | AA48: =IF(M48="",0,N48*INDEX('Vendor Prices'!$G$5:$G$58,MATCH(M48,'Vendor Prices'!$A$5:$A$58,0))*(1+INDEX('Vendor Prices'!$J$5:$J$58,MATCH(M48,'Vendor Prices'!$A$5:$A$58,0))*Inputs!$B$7)) -> 0 | AB48: =Y48+Z48+AA48+O48 -> 0.00142425 | AC48: 1.5 | AD48: =AB48*AC48 -> 0.002136375
A49: probe_gemini | B49: AI Visibility | C49: Prompt check: Gemini (3.8 Flash, no search) | D49: geo.probe | E49: google/gemini-3.8-flash | G49: 150 | H49: 600 | I49: 1 | J49: 0 | K49: 1500 | L49: 0 | P49: =IF(E49="PREMIUM",Inputs!$B$9,IF(E49="WORKHORSE",Inputs!$B$10,IF(E49="ECONOMY",Inputs!$B$11,E49))) -> google/gemini-3.8-flash | Q49: =IF(K49<>"",K49,IF(F49="",0,IFERROR(INDEX(Inputs!$B$42:$D$44,MATCH(E49,Inputs!$A$42:$A$44,0),IF(F49="low",1,IF(F49="medium",2,3))),0))) -> 1500 | R49: =IF(P49="",0,INDEX('Vendor Prices'!$G$5:$G$58,MATCH(P49,'Vendor Prices'!$A$5:$A$58,0))) -> 0.75 | S49: =IF(P49="",0,INDEX('Vendor Prices'!$H$5:$H$58,MATCH(P49,'Vendor Prices'!$A$5:$A$58,0))) -> 3.75 | T49: =IF(P49="",0,IF(INDEX('Vendor Prices'!$I$5:$I$58,MATCH(P49,'Vendor Prices'!$A$5:$A$58,0))=0,R49,INDEX('Vendor Prices'!$I$5:$I$58,MATCH(P49,'Vendor Prices'!$A$5:$A$58,0)))) -> 0.1875 | U49: =IF(LEFT(P49,10)="anthropic/",Inputs!$B$8,1) -> 1 | V49: =IF(P49="",0,I49*(G49*U49*((1-J49)*R49+J49*T49)+(H49+Q49)*U49*S49)/1000000*(1+Inputs!$B$7)) -> 0.0084268125 | W49: =IF(E49="PREMIUM",Inputs!$B$12,IF(E49="WORKHORSE",Inputs!$B$13,IF(E49="ECONOMY",Inputs!$B$14,""))) | X49: =IF(W49="",V49,I49*(G49*((1-J49)*INDEX('Vendor Prices'!$G$5:$G$58,MATCH(W49,'Vendor Prices'!$A$5:$A$58,0))+J49*INDEX('Vendor Prices'!$I$5:$I$58,MATCH(W49,'Vendor Prices'!$A$5:$A$58,0)))+(H49+Q49)*INDEX('Vendor Prices'!$H$5:$H$58,MATCH(W49,'Vendor Prices'!$A$5:$A$58,0)))/1000000*(1+Inputs!$B$7)) -> 0.0084268125 | Y49: =(1-Inputs!$B$15)*V49+Inputs!$B$15*X49 -> 0.0084268125 | Z49: =L49*Inputs!$B$29 -> 0 | AA49: =IF(M49="",0,N49*INDEX('Vendor Prices'!$G$5:$G$58,MATCH(M49,'Vendor Prices'!$A$5:$A$58,0))*(1+INDEX('Vendor Prices'!$J$5:$J$58,MATCH(M49,'Vendor Prices'!$A$5:$A$58,0))*Inputs!$B$7)) -> 0 | AB49: =Y49+Z49+AA49+O49 -> 0.0084268125 | AC49: 1.5 | AD49: =AB49*AC49 -> 0.012640219
A50: probe_set | B50: AI Visibility | C50: One tracked prompt across the 3 spec engines | D50: geo.probe x3 | G50: 0 | H50: 0 | I50: 1 | J50: 0 | L50: 0 | O50: =$AB$47+$AB$48+$AB$49 -> 0.015917312 | P50: =IF(E50="PREMIUM",Inputs!$B$9,IF(E50="WORKHORSE",Inputs!$B$10,IF(E50="ECONOMY",Inputs!$B$11,E50))) -> 0 | Q50: =IF(K50<>"",K50,IF(F50="",0,IFERROR(INDEX(Inputs!$B$42:$D$44,MATCH(E50,Inputs!$A$42:$A$44,0),IF(F50="low",1,IF(F50="medium",2,3))),0))) -> 0 | R50: =IF(P50="",0,INDEX('Vendor Prices'!$G$5:$G$58,MATCH(P50,'Vendor Prices'!$A$5:$A$58,0))) -> 0 | S50: =IF(P50="",0,INDEX('Vendor Prices'!$H$5:$H$58,MATCH(P50,'Vendor Prices'!$A$5:$A$58,0))) -> 0 | T50: =IF(P50="",0,IF(INDEX('Vendor Prices'!$I$5:$I$58,MATCH(P50,'Vendor Prices'!$A$5:$A$58,0))=0,R50,INDEX('Vendor Prices'!$I$5:$I$58,MATCH(P50,'Vendor Prices'!$A$5:$A$58,0)))) -> 0 | U50: =IF(LEFT(P50,10)="anthropic/",Inputs!$B$8,1) -> 1 | V50: =IF(P50="",0,I50*(G50*U50*((1-J50)*R50+J50*T50)+(H50+Q50)*U50*S50)/1000000*(1+Inputs!$B$7)) -> 0 | W50: =IF(E50="PREMIUM",Inputs!$B$12,IF(E50="WORKHORSE",Inputs!$B$13,IF(E50="ECONOMY",Inputs!$B$14,""))) | X50: =IF(W50="",V50,I50*(G50*((1-J50)*INDEX('Vendor Prices'!$G$5:$G$58,MATCH(W50,'Vendor Prices'!$A$5:$A$58,0))+J50*INDEX('Vendor Prices'!$I$5:$I$58,MATCH(W50,'Vendor Prices'!$A$5:$A$58,0)))+(H50+Q50)*INDEX('Vendor Prices'!$H$5:$H$58,MATCH(W50,'Vendor Prices'!$A$5:$A$58,0)))/1000000*(1+Inputs!$B$7)) -> 0 | Y50: =(1-Inputs!$B$15)*V50+Inputs!$B$15*X50 -> 0 | Z50: =L50*Inputs!$B$29 -> 0 | AA50: =IF(M50="",0,N50*INDEX('Vendor Prices'!$G$5:$G$58,MATCH(M50,'Vendor Prices'!$A$5:$A$58,0))*(1+INDEX('Vendor Prices'!$J$5:$J$58,MATCH(M50,'Vendor Prices'!$A$5:$A$58,0))*Inputs!$B$7)) -> 0 | AB50: =Y50+Z50+AA50+O50 -> 0.015917312 | AC50: 1.3 | AD50: =AB50*AC50 -> 0.020692506
A51: probe_chatgpt_real | B51: AI Visibility | C51: Option: real ChatGPT answer (DataForSEO + parse) | D51: proposed | E51: ECONOMY | F51: low | G51: 2000 | H51: 300 | I51: 1 | J51: 0 | L51: 0 | M51: dfs-llm-scraper-std | N51: 1 | P51: =IF(E51="PREMIUM",Inputs!$B$9,IF(E51="WORKHORSE",Inputs!$B$10,IF(E51="ECONOMY",Inputs!$B$11,E51))) -> google/gemini-3.1-flash-lite | Q51: =IF(K51<>"",K51,IF(F51="",0,IFERROR(INDEX(Inputs!$B$42:$D$44,MATCH(E51,Inputs!$A$42:$A$44,0),IF(F51="low",1,IF(F51="medium",2,3))),0))) -> 200 | R51: =IF(P51="",0,INDEX('Vendor Prices'!$G$5:$G$58,MATCH(P51,'Vendor Prices'!$A$5:$A$58,0))) -> 0.25 | S51: =IF(P51="",0,INDEX('Vendor Prices'!$H$5:$H$58,MATCH(P51,'Vendor Prices'!$A$5:$A$58,0))) -> 1.5 | T51: =IF(P51="",0,IF(INDEX('Vendor Prices'!$I$5:$I$58,MATCH(P51,'Vendor Prices'!$A$5:$A$58,0))=0,R51,INDEX('Vendor Prices'!$I$5:$I$58,MATCH(P51,'Vendor Prices'!$A$5:$A$58,0)))) -> 0.0625 | U51: =IF(LEFT(P51,10)="anthropic/",Inputs!$B$8,1) -> 1 | V51: =IF(P51="",0,I51*(G51*U51*((1-J51)*R51+J51*T51)+(H51+Q51)*U51*S51)/1000000*(1+Inputs!$B$7)) -> 0.00131875 | W51: =IF(E51="PREMIUM",Inputs!$B$12,IF(E51="WORKHORSE",Inputs!$B$13,IF(E51="ECONOMY",Inputs!$B$14,""))) -> openai/gpt-5.6-luna | X51: =IF(W51="",V51,I51*(G51*((1-J51)*INDEX('Vendor Prices'!$G$5:$G$58,MATCH(W51,'Vendor Prices'!$A$5:$A$58,0))+J51*INDEX('Vendor Prices'!$I$5:$I$58,MATCH(W51,'Vendor Prices'!$A$5:$A$58,0)))+(H51+Q51)*INDEX('Vendor Prices'!$H$5:$H$58,MATCH(W51,'Vendor Prices'!$A$5:$A$58,0)))/1000000*(1+Inputs!$B$7)) -> 0.001055 | Y51: =(1-Inputs!$B$15)*V51+Inputs!$B$15*X51 -> 0.0013108375 | Z51: =L51*Inputs!$B$29 -> 0 | AA51: =IF(M51="",0,N51*INDEX('Vendor Prices'!$G$5:$G$58,MATCH(M51,'Vendor Prices'!$A$5:$A$58,0))*(1+INDEX('Vendor Prices'!$J$5:$J$58,MATCH(M51,'Vendor Prices'!$A$5:$A$58,0))*Inputs!$B$7)) -> 0.0012 | AB51: =Y51+Z51+AA51+O51 -> 0.0025108375 | AC51: 3 | AD51: =AB51*AC51 -> 0.0075325125
A52: probe_aio_real | B52: AI Visibility | C52: Option: Google AI Overview (DataForSEO SERP + parse) | D52: proposed | E52: ECONOMY | F52: low | G52: 2000 | H52: 300 | I52: 1 | J52: 0 | L52: 0 | M52: dfs-serp-std | N52: 1 | P52: =IF(E52="PREMIUM",Inputs!$B$9,IF(E52="WORKHORSE",Inputs!$B$10,IF(E52="ECONOMY",Inputs!$B$11,E52))) -> google/gemini-3.1-flash-lite | Q52: =IF(K52<>"",K52,IF(F52="",0,IFERROR(INDEX(Inputs!$B$42:$D$44,MATCH(E52,Inputs!$A$42:$A$44,0),IF(F52="low",1,IF(F52="medium",2,3))),0))) -> 200 | R52: =IF(P52="",0,INDEX('Vendor Prices'!$G$5:$G$58,MATCH(P52,'Vendor Prices'!$A$5:$A$58,0))) -> 0.25 | S52: =IF(P52="",0,INDEX('Vendor Prices'!$H$5:$H$58,MATCH(P52,'Vendor Prices'!$A$5:$A$58,0))) -> 1.5 | T52: =IF(P52="",0,IF(INDEX('Vendor Prices'!$I$5:$I$58,MATCH(P52,'Vendor Prices'!$A$5:$A$58,0))=0,R52,INDEX('Vendor Prices'!$I$5:$I$58,MATCH(P52,'Vendor Prices'!$A$5:$A$58,0)))) -> 0.0625 | U52: =IF(LEFT(P52,10)="anthropic/",Inputs!$B$8,1) -> 1 | V52: =IF(P52="",0,I52*(G52*U52*((1-J52)*R52+J52*T52)+(H52+Q52)*U52*S52)/1000000*(1+Inputs!$B$7)) -> 0.00131875 | W52: =IF(E52="PREMIUM",Inputs!$B$12,IF(E52="WORKHORSE",Inputs!$B$13,IF(E52="ECONOMY",Inputs!$B$14,""))) -> openai/gpt-5.6-luna | X52: =IF(W52="",V52,I52*(G52*((1-J52)*INDEX('Vendor Prices'!$G$5:$G$58,MATCH(W52,'Vendor Prices'!$A$5:$A$58,0))+J52*INDEX('Vendor Prices'!$I$5:$I$58,MATCH(W52,'Vendor Prices'!$A$5:$A$58,0)))+(H52+Q52)*INDEX('Vendor Prices'!$H$5:$H$58,MATCH(W52,'Vendor Prices'!$A$5:$A$58,0)))/1000000*(1+Inputs!$B$7)) -> 0.001055 | Y52: =(1-Inputs!$B$15)*V52+Inputs!$B$15*X52 -> 0.0013108375 | Z52: =L52*Inputs!$B$29 -> 0 | AA52: =IF(M52="",0,N52*INDEX('Vendor Prices'!$G$5:$G$58,MATCH(M52,'Vendor Prices'!$A$5:$A$58,0))*(1+INDEX('Vendor Prices'!$J$5:$J$58,MATCH(M52,'Vendor Prices'!$A$5:$A$58,0))*Inputs!$B$7)) -> 0.0006 | AB52: =Y52+Z52+AA52+O52 -> 0.0019108375 | AC52: 3 | AD52: =AB52*AC52 -> 0.0057325125
A53: geo_fix | B53: AI Visibility | C53: GEO fix proposal | D53: geo.fix.propose / geo.fix.batch | E53: PREMIUM | F53: medium | G53: 10000 | H53: 6000 | I53: 1.1 | J53: 0 | L53: 0 | P53: =IF(E53="PREMIUM",Inputs!$B$9,IF(E53="WORKHORSE",Inputs!$B$10,IF(E53="ECONOMY",Inputs!$B$11,E53))) -> anthropic/claude-opus-5.5 | Q53: =IF(K53<>"",K53,IF(F53="",0,IFERROR(INDEX(Inputs!$B$42:$D$44,MATCH(E53,Inputs!$A$42:$A$44,0),IF(F53="low",1,IF(F53="medium",2,3))),0))) -> 3000 | R53: =IF(P53="",0,INDEX('Vendor Prices'!$G$5:$G$58,MATCH(P53,'Vendor Prices'!$A$5:$A$58,0))) -> 4 | S53: =IF(P53="",0,INDEX('Vendor Prices'!$H$5:$H$58,MATCH(P53,'Vendor Prices'!$A$5:$A$58,0))) -> 20 | T53: =IF(P53="",0,IF(INDEX('Vendor Prices'!$I$5:$I$58,MATCH(P53,'Vendor Prices'!$A$5:$A$58,0))=0,R53,INDEX('Vendor Prices'!$I$5:$I$58,MATCH(P53,'Vendor Prices'!$A$5:$A$58,0)))) -> 0.2 | U53: =IF(LEFT(P53,10)="anthropic/",Inputs!$B$8,1) -> 1.15 | V53: =IF(P53="",0,I53*(G53*U53*((1-J53)*R53+J53*T53)+(H53+Q53)*U53*S53)/1000000*(1+Inputs!$B$7)) -> 0.2936065 | W53: =IF(E53="PREMIUM",Inputs!$B$12,IF(E53="WORKHORSE",Inputs!$B$13,IF(E53="ECONOMY",Inputs!$B$14,""))) -> google/gemini-3.8-flash | X53: =IF(W53="",V53,I53*(G53*((1-J53)*INDEX('Vendor Prices'!$G$5:$G$58,MATCH(W53,'Vendor Prices'!$A$5:$A$58,0))+J53*INDEX('Vendor Prices'!$I$5:$I$58,MATCH(W53,'Vendor Prices'!$A$5:$A$58,0)))+(H53+Q53)*INDEX('Vendor Prices'!$H$5:$H$58,MATCH(W53,'Vendor Prices'!$A$5:$A$58,0)))/1000000*(1+Inputs!$B$7)) -> 0.047870625 | Y53: =(1-Inputs!$B$15)*V53+Inputs!$B$15*X53 -> 0.28623442 | Z53: =L53*Inputs!$B$29 -> 0 | AA53: =IF(M53="",0,N53*INDEX('Vendor Prices'!$G$5:$G$58,MATCH(M53,'Vendor Prices'!$A$5:$A$58,0))*(1+INDEX('Vendor Prices'!$J$5:$J$58,MATCH(M53,'Vendor Prices'!$A$5:$A$58,0))*Inputs!$B$7)) -> 0 | AB53: =Y53+Z53+AA53+O53 -> 0.28623442 | AC53: 1.4 | AD53: =AB53*AC53 -> 0.40072819
A54: geo_cms | B54: AI Visibility | C54: GEO CMS fix (WordPress / Webflow) | D54: geo.cms.fix | E54: WORKHORSE | F54: medium | G54: 8000 | H54: 1870 | I54: 3 | J54: 0 | L54: 0 | O54: =0.2*$AB$10 -> 0.040687869 | P54: =IF(E54="PREMIUM",Inputs!$B$9,IF(E54="WORKHORSE",Inputs!$B$10,IF(E54="ECONOMY",Inputs!$B$11,E54))) -> google/gemini-3.8-flash | Q54: =IF(K54<>"",K54,IF(F54="",0,IFERROR(INDEX(Inputs!$B$42:$D$44,MATCH(E54,Inputs!$A$42:$A$44,0),IF(F54="low",1,IF(F54="medium",2,3))),0))) -> 1800 | R54: =IF(P54="",0,INDEX('Vendor Prices'!$G$5:$G$58,MATCH(P54,'Vendor Prices'!$A$5:$A$58,0))) -> 0.75 | S54: =IF(P54="",0,INDEX('Vendor Prices'!$H$5:$H$58,MATCH(P54,'Vendor Prices'!$A$5:$A$58,0))) -> 3.75 | T54: =IF(P54="",0,IF(INDEX('Vendor Prices'!$I$5:$I$58,MATCH(P54,'Vendor Prices'!$A$5:$A$58,0))=0,R54,INDEX('Vendor Prices'!$I$5:$I$58,MATCH(P54,'Vendor Prices'!$A$5:$A$58,0)))) -> 0.1875 | U54: =IF(LEFT(P54,10)="anthropic/",Inputs!$B$8,1) -> 1 | V54: =IF(P54="",0,I54*(G54*U54*((1-J54)*R54+J54*T54)+(H54+Q54)*U54*S54)/1000000*(1+Inputs!$B$7)) -> 0.062548312 | W54: =IF(E54="PREMIUM",Inputs!$B$12,IF(E54="WORKHORSE",Inputs!$B$13,IF(E54="ECONOMY",Inputs!$B$14,""))) -> openai/gpt-5.6-terra | X54: =IF(W54="",V54,I54*(G54*((1-J54)*INDEX('Vendor Prices'!$G$5:$G$58,MATCH(W54,'Vendor Prices'!$A$5:$A$58,0))+J54*INDEX('Vendor Prices'!$I$5:$I$58,MATCH(W54,'Vendor Prices'!$A$5:$A$58,0)))+(H54+Q54)*INDEX('Vendor Prices'!$H$5:$H$58,MATCH(W54,'Vendor Prices'!$A$5:$A$58,0)))/1000000*(1+Inputs!$B$7)) -> 0.1900266 | Y54: =(1-Inputs!$B$15)*V54+Inputs!$B$15*X54 -> 0.066372661 | Z54: =L54*Inputs!$B$29 -> 0 | AA54: =IF(M54="",0,N54*INDEX('Vendor Prices'!$G$5:$G$58,MATCH(M54,'Vendor Prices'!$A$5:$A$58,0))*(1+INDEX('Vendor Prices'!$J$5:$J$58,MATCH(M54,'Vendor Prices'!$A$5:$A$58,0))*Inputs!$B$7)) -> 0 | AB54: =Y54+Z54+AA54+O54 -> 0.10706053 | AC54: 1.5 | AD54: =AB54*AC54 -> 0.16059079
A55: geo_agent | B55: AI Visibility | C55: GEO Engineer agent run (GitHub PR) | D55: GEO coding agent (PREMIUM high) | G55: 0 | H55: 0 | I55: 1 | J55: 0 | L55: 0 | O55: 1.6 | P55: =IF(E55="PREMIUM",Inputs!$B$9,IF(E55="WORKHORSE",Inputs!$B$10,IF(E55="ECONOMY",Inputs!$B$11,E55))) -> 0 | Q55: =IF(K55<>"",K55,IF(F55="",0,IFERROR(INDEX(Inputs!$B$42:$D$44,MATCH(E55,Inputs!$A$42:$A$44,0),IF(F55="low",1,IF(F55="medium",2,3))),0))) -> 0 | R55: =IF(P55="",0,INDEX('Vendor Prices'!$G$5:$G$58,MATCH(P55,'Vendor Prices'!$A$5:$A$58,0))) -> 0 | S55: =IF(P55="",0,INDEX('Vendor Prices'!$H$5:$H$58,MATCH(P55,'Vendor Prices'!$A$5:$A$58,0))) -> 0 | T55: =IF(P55="",0,IF(INDEX('Vendor Prices'!$I$5:$I$58,MATCH(P55,'Vendor Prices'!$A$5:$A$58,0))=0,R55,INDEX('Vendor Prices'!$I$5:$I$58,MATCH(P55,'Vendor Prices'!$A$5:$A$58,0)))) -> 0 | U55: =IF(LEFT(P55,10)="anthropic/",Inputs!$B$8,1) -> 1 | V55: =IF(P55="",0,I55*(G55*U55*((1-J55)*R55+J55*T55)+(H55+Q55)*U55*S55)/1000000*(1+Inputs!$B$7)) -> 0 | W55: =IF(E55="PREMIUM",Inputs!$B$12,IF(E55="WORKHORSE",Inputs!$B$13,IF(E55="ECONOMY",Inputs!$B$14,""))) | X55: =IF(W55="",V55,I55*(G55*((1-J55)*INDEX('Vendor Prices'!$G$5:$G$58,MATCH(W55,'Vendor Prices'!$A$5:$A$58,0))+J55*INDEX('Vendor Prices'!$I$5:$I$58,MATCH(W55,'Vendor Prices'!$A$5:$A$58,0)))+(H55+Q55)*INDEX('Vendor Prices'!$H$5:$H$58,MATCH(W55,'Vendor Prices'!$A$5:$A$58,0)))/1000000*(1+Inputs!$B$7)) -> 0 | Y55: =(1-Inputs!$B$15)*V55+Inputs!$B$15*X55 -> 0 | Z55: =L55*Inputs!$B$29 -> 0 | AA55: =IF(M55="",0,N55*INDEX('Vendor Prices'!$G$5:$G$58,MATCH(M55,'Vendor Prices'!$A$5:$A$58,0))*(1+INDEX('Vendor Prices'!$J$5:$J$58,MATCH(M55,'Vendor Prices'!$A$5:$A$58,0))*Inputs!$B$7)) -> 0 | AB55: =Y55+Z55+AA55+O55 -> 1.6 | AC55: 1.875 | AD55: =AB55*AC55 -> 3 | AE55: Expected ~$1.60 on Opus 5.5 high; raise GEO_AGENT_MAX_COST_USD to $3.00
A56: experiment | B56: AI Visibility | C56: Proof Engine experiment | D56: experiments.hypotheses + values + analysis | E56: PREMIUM | F56: low | G56: 5000 | H56: 2000 | I56: 1 | J56: 0 | L56: 0 | O56: =$AB$11+$AB$12 -> 0.05372904 | P56: =IF(E56="PREMIUM",Inputs!$B$9,IF(E56="WORKHORSE",Inputs!$B$10,IF(E56="ECONOMY",Inputs!$B$11,E56))) -> anthropic/claude-opus-5.5 | Q56: =IF(K56<>"",K56,IF(F56="",0,IFERROR(INDEX(Inputs!$B$42:$D$44,MATCH(E56,Inputs!$A$42:$A$44,0),IF(F56="low",1,IF(F56="medium",2,3))),0))) -> 800 | R56: =IF(P56="",0,INDEX('Vendor Prices'!$G$5:$G$58,MATCH(P56,'Vendor Prices'!$A$5:$A$58,0))) -> 4 | S56: =IF(P56="",0,INDEX('Vendor Prices'!$H$5:$H$58,MATCH(P56,'Vendor Prices'!$A$5:$A$58,0))) -> 20 | T56: =IF(P56="",0,IF(INDEX('Vendor Prices'!$I$5:$I$58,MATCH(P56,'Vendor Prices'!$A$5:$A$58,0))=0,R56,INDEX('Vendor Prices'!$I$5:$I$58,MATCH(P56,'Vendor Prices'!$A$5:$A$58,0)))) -> 0.2 | U56: =IF(LEFT(P56,10)="anthropic/",Inputs!$B$8,1) -> 1.15 | V56: =IF(P56="",0,I56*(G56*U56*((1-J56)*R56+J56*T56)+(H56+Q56)*U56*S56)/1000000*(1+Inputs!$B$7)) -> 0.092207 | W56: =IF(E56="PREMIUM",Inputs!$B$12,IF(E56="WORKHORSE",Inputs!$B$13,IF(E56="ECONOMY",Inputs!$B$14,""))) -> google/gemini-3.8-flash | X56: =IF(W56="",V56,I56*(G56*((1-J56)*INDEX('Vendor Prices'!$G$5:$G$58,MATCH(W56,'Vendor Prices'!$A$5:$A$58,0))+J56*INDEX('Vendor Prices'!$I$5:$I$58,MATCH(W56,'Vendor Prices'!$A$5:$A$58,0)))+(H56+Q56)*INDEX('Vendor Prices'!$H$5:$H$58,MATCH(W56,'Vendor Prices'!$A$5:$A$58,0)))/1000000*(1+Inputs!$B$7)) -> 0.01503375 | Y56: =(1-Inputs!$B$15)*V56+Inputs!$B$15*X56 -> 0.089891803 | Z56: =L56*Inputs!$B$29 -> 0 | AA56: =IF(M56="",0,N56*INDEX('Vendor Prices'!$G$5:$G$58,MATCH(M56,'Vendor Prices'!$A$5:$A$58,0))*(1+INDEX('Vendor Prices'!$J$5:$J$58,MATCH(M56,'Vendor Prices'!$A$5:$A$58,0))*Inputs!$B$7)) -> 0 | AB56: =Y56+Z56+AA56+O56 -> 0.14362084 | AC56: 1.5 | AD56: =AB56*AC56 -> 0.21543126
A57: ugc_concepts | B57: UGC Ads | C57: UGC concept pack (extract + concepts + notes) | D57: ugc.concepts (+ extract, notes) | E57: WORKHORSE | F57: medium | G57: 6000 | H57: 4000 | I57: 1 | J57: 0 | L57: 0 | O57: =$AB$14+$AB$15 -> 0.021829005 | P57: =IF(E57="PREMIUM",Inputs!$B$9,IF(E57="WORKHORSE",Inputs!$B$10,IF(E57="ECONOMY",Inputs!$B$11,E57))) -> google/gemini-3.8-flash | Q57: =IF(K57<>"",K57,IF(F57="",0,IFERROR(INDEX(Inputs!$B$42:$D$44,MATCH(E57,Inputs!$A$42:$A$44,0),IF(F57="low",1,IF(F57="medium",2,3))),0))) -> 1800 | R57: =IF(P57="",0,INDEX('Vendor Prices'!$G$5:$G$58,MATCH(P57,'Vendor Prices'!$A$5:$A$58,0))) -> 0.75 | S57: =IF(P57="",0,INDEX('Vendor Prices'!$H$5:$H$58,MATCH(P57,'Vendor Prices'!$A$5:$A$58,0))) -> 3.75 | T57: =IF(P57="",0,IF(INDEX('Vendor Prices'!$I$5:$I$58,MATCH(P57,'Vendor Prices'!$A$5:$A$58,0))=0,R57,INDEX('Vendor Prices'!$I$5:$I$58,MATCH(P57,'Vendor Prices'!$A$5:$A$58,0)))) -> 0.1875 | U57: =IF(LEFT(P57,10)="anthropic/",Inputs!$B$8,1) -> 1 | V57: =IF(P57="",0,I57*(G57*U57*((1-J57)*R57+J57*T57)+(H57+Q57)*U57*S57)/1000000*(1+Inputs!$B$7)) -> 0.02769375 | W57: =IF(E57="PREMIUM",Inputs!$B$12,IF(E57="WORKHORSE",Inputs!$B$13,IF(E57="ECONOMY",Inputs!$B$14,""))) -> openai/gpt-5.6-terra | X57: =IF(W57="",V57,I57*(G57*((1-J57)*INDEX('Vendor Prices'!$G$5:$G$58,MATCH(W57,'Vendor Prices'!$A$5:$A$58,0))+J57*INDEX('Vendor Prices'!$I$5:$I$58,MATCH(W57,'Vendor Prices'!$A$5:$A$58,0)))+(H57+Q57)*INDEX('Vendor Prices'!$H$5:$H$58,MATCH(W57,'Vendor Prices'!$A$5:$A$58,0)))/1000000*(1+Inputs!$B$7)) -> 0.086088 | Y57: =(1-Inputs!$B$15)*V57+Inputs!$B$15*X57 -> 0.029445578 | Z57: =L57*Inputs!$B$29 -> 0 | AA57: =IF(M57="",0,N57*INDEX('Vendor Prices'!$G$5:$G$58,MATCH(M57,'Vendor Prices'!$A$5:$A$58,0))*(1+INDEX('Vendor Prices'!$J$5:$J$58,MATCH(M57,'Vendor Prices'!$A$5:$A$58,0))*Inputs!$B$7)) -> 0 | AB57: =Y57+Z57+AA57+O57 -> 0.051274582 | AC57: 1.5 | AD57: =AB57*AC57 -> 0.076911874
A58: link_research | B58: Backlinks | C58: Link research (10 candidate sites) | D58: links-topical-fit x10 + relevance pick | E58: ECONOMY | F58: low | G58: 3000 | H58: 600 | I58: 10 | J58: 0 | L58: 0 | O58: =$AB$13 -> 0.0096366337 | P58: =IF(E58="PREMIUM",Inputs!$B$9,IF(E58="WORKHORSE",Inputs!$B$10,IF(E58="ECONOMY",Inputs!$B$11,E58))) -> google/gemini-3.1-flash-lite | Q58: =IF(K58<>"",K58,IF(F58="",0,IFERROR(INDEX(Inputs!$B$42:$D$44,MATCH(E58,Inputs!$A$42:$A$44,0),IF(F58="low",1,IF(F58="medium",2,3))),0))) -> 200 | R58: =IF(P58="",0,INDEX('Vendor Prices'!$G$5:$G$58,MATCH(P58,'Vendor Prices'!$A$5:$A$58,0))) -> 0.25 | S58: =IF(P58="",0,INDEX('Vendor Prices'!$H$5:$H$58,MATCH(P58,'Vendor Prices'!$A$5:$A$58,0))) -> 1.5 | T58: =IF(P58="",0,IF(INDEX('Vendor Prices'!$I$5:$I$58,MATCH(P58,'Vendor Prices'!$A$5:$A$58,0))=0,R58,INDEX('Vendor Prices'!$I$5:$I$58,MATCH(P58,'Vendor Prices'!$A$5:$A$58,0)))) -> 0.0625 | U58: =IF(LEFT(P58,10)="anthropic/",Inputs!$B$8,1) -> 1 | V58: =IF(P58="",0,I58*(G58*U58*((1-J58)*R58+J58*T58)+(H58+Q58)*U58*S58)/1000000*(1+Inputs!$B$7)) -> 0.0205725 | W58: =IF(E58="PREMIUM",Inputs!$B$12,IF(E58="WORKHORSE",Inputs!$B$13,IF(E58="ECONOMY",Inputs!$B$14,""))) -> openai/gpt-5.6-luna | X58: =IF(W58="",V58,I58*(G58*((1-J58)*INDEX('Vendor Prices'!$G$5:$G$58,MATCH(W58,'Vendor Prices'!$A$5:$A$58,0))+J58*INDEX('Vendor Prices'!$I$5:$I$58,MATCH(W58,'Vendor Prices'!$A$5:$A$58,0)))+(H58+Q58)*INDEX('Vendor Prices'!$H$5:$H$58,MATCH(W58,'Vendor Prices'!$A$5:$A$58,0)))/1000000*(1+Inputs!$B$7)) -> 0.016458 | Y58: =(1-Inputs!$B$15)*V58+Inputs!$B$15*X58 -> 0.020449065 | Z58: =L58*Inputs!$B$29 -> 0 | AA58: =IF(M58="",0,N58*INDEX('Vendor Prices'!$G$5:$G$58,MATCH(M58,'Vendor Prices'!$A$5:$A$58,0))*(1+INDEX('Vendor Prices'!$J$5:$J$58,MATCH(M58,'Vendor Prices'!$A$5:$A$58,0))*Inputs!$B$7)) -> 0 | AB58: =Y58+Z58+AA58+O58 -> 0.030085699 | AC58: 1.5 | AD58: =AB58*AC58 -> 0.045128548
A59: social_post | B59: Distribution | C59: Social publishing: 1 post on 1 network | D59: Post for Me | G59: 0 | H59: 0 | I59: 1 | J59: 0 | L59: 0 | O59: =Inputs!$B$26 -> 0.01 | P59: =IF(E59="PREMIUM",Inputs!$B$9,IF(E59="WORKHORSE",Inputs!$B$10,IF(E59="ECONOMY",Inputs!$B$11,E59))) -> 0 | Q59: =IF(K59<>"",K59,IF(F59="",0,IFERROR(INDEX(Inputs!$B$42:$D$44,MATCH(E59,Inputs!$A$42:$A$44,0),IF(F59="low",1,IF(F59="medium",2,3))),0))) -> 0 | R59: =IF(P59="",0,INDEX('Vendor Prices'!$G$5:$G$58,MATCH(P59,'Vendor Prices'!$A$5:$A$58,0))) -> 0 | S59: =IF(P59="",0,INDEX('Vendor Prices'!$H$5:$H$58,MATCH(P59,'Vendor Prices'!$A$5:$A$58,0))) -> 0 | T59: =IF(P59="",0,IF(INDEX('Vendor Prices'!$I$5:$I$58,MATCH(P59,'Vendor Prices'!$A$5:$A$58,0))=0,R59,INDEX('Vendor Prices'!$I$5:$I$58,MATCH(P59,'Vendor Prices'!$A$5:$A$58,0)))) -> 0 | U59: =IF(LEFT(P59,10)="anthropic/",Inputs!$B$8,1) -> 1 | V59: =IF(P59="",0,I59*(G59*U59*((1-J59)*R59+J59*T59)+(H59+Q59)*U59*S59)/1000000*(1+Inputs!$B$7)) -> 0 | W59: =IF(E59="PREMIUM",Inputs!$B$12,IF(E59="WORKHORSE",Inputs!$B$13,IF(E59="ECONOMY",Inputs!$B$14,""))) | X59: =IF(W59="",V59,I59*(G59*((1-J59)*INDEX('Vendor Prices'!$G$5:$G$58,MATCH(W59,'Vendor Prices'!$A$5:$A$58,0))+J59*INDEX('Vendor Prices'!$I$5:$I$58,MATCH(W59,'Vendor Prices'!$A$5:$A$58,0)))+(H59+Q59)*INDEX('Vendor Prices'!$H$5:$H$58,MATCH(W59,'Vendor Prices'!$A$5:$A$58,0)))/1000000*(1+Inputs!$B$7)) -> 0 | Y59: =(1-Inputs!$B$15)*V59+Inputs!$B$15*X59 -> 0 | Z59: =L59*Inputs!$B$29 -> 0 | AA59: =IF(M59="",0,N59*INDEX('Vendor Prices'!$G$5:$G$58,MATCH(M59,'Vendor Prices'!$A$5:$A$58,0))*(1+INDEX('Vendor Prices'!$J$5:$J$58,MATCH(M59,'Vendor Prices'!$A$5:$A$58,0))*Inputs!$B$7)) -> 0 | AB59: =Y59+Z59+AA59+O59 -> 0.01 | AC59: 1 | AD59: =AB59*AC59 -> 0.01
A60: background | B60: Platform | C60: Background jobs + storage per brand / month | D60: cron, agents, storage | G60: 0 | H60: 0 | I60: 1 | J60: 0 | L60: 0 | O60: 0.4 | P60: =IF(E60="PREMIUM",Inputs!$B$9,IF(E60="WORKHORSE",Inputs!$B$10,IF(E60="ECONOMY",Inputs!$B$11,E60))) -> 0 | Q60: =IF(K60<>"",K60,IF(F60="",0,IFERROR(INDEX(Inputs!$B$42:$D$44,MATCH(E60,Inputs!$A$42:$A$44,0),IF(F60="low",1,IF(F60="medium",2,3))),0))) -> 0 | R60: =IF(P60="",0,INDEX('Vendor Prices'!$G$5:$G$58,MATCH(P60,'Vendor Prices'!$A$5:$A$58,0))) -> 0 | S60: =IF(P60="",0,INDEX('Vendor Prices'!$H$5:$H$58,MATCH(P60,'Vendor Prices'!$A$5:$A$58,0))) -> 0 | T60: =IF(P60="",0,IF(INDEX('Vendor Prices'!$I$5:$I$58,MATCH(P60,'Vendor Prices'!$A$5:$A$58,0))=0,R60,INDEX('Vendor Prices'!$I$5:$I$58,MATCH(P60,'Vendor Prices'!$A$5:$A$58,0)))) -> 0 | U60: =IF(LEFT(P60,10)="anthropic/",Inputs!$B$8,1) -> 1 | V60: =IF(P60="",0,I60*(G60*U60*((1-J60)*R60+J60*T60)+(H60+Q60)*U60*S60)/1000000*(1+Inputs!$B$7)) -> 0 | W60: =IF(E60="PREMIUM",Inputs!$B$12,IF(E60="WORKHORSE",Inputs!$B$13,IF(E60="ECONOMY",Inputs!$B$14,""))) | X60: =IF(W60="",V60,I60*(G60*((1-J60)*INDEX('Vendor Prices'!$G$5:$G$58,MATCH(W60,'Vendor Prices'!$A$5:$A$58,0))+J60*INDEX('Vendor Prices'!$I$5:$I$58,MATCH(W60,'Vendor Prices'!$A$5:$A$58,0)))+(H60+Q60)*INDEX('Vendor Prices'!$H$5:$H$58,MATCH(W60,'Vendor Prices'!$A$5:$A$58,0)))/1000000*(1+Inputs!$B$7)) -> 0 | Y60: =(1-Inputs!$B$15)*V60+Inputs!$B$15*X60 -> 0 | Z60: =L60*Inputs!$B$29 -> 0 | AA60: =IF(M60="",0,N60*INDEX('Vendor Prices'!$G$5:$G$58,MATCH(M60,'Vendor Prices'!$A$5:$A$58,0))*(1+INDEX('Vendor Prices'!$J$5:$J$58,MATCH(M60,'Vendor Prices'!$A$5:$A$58,0))*Inputs!$B$7)) -> 0 | AB60: =Y60+Z60+AA60+O60 -> 0.4 | AC60: 2 | AD60: =AB60*AC60 -> 0.8

Sheet Model Routing
A1: Model routing by task (from your OpenRouter migration spec)
A2: Model column resolves from the tier cells on Inputs, so a tier swap updates everything.
A4: Route label(s) | B4: Tier | C4: Model (resolved) | D4: Effort | E4: Fallback | F4: Rule / escalation | G4: Modeled cost per action ($)
A5: brand-extract | B5: PREMIUM | C5: =IF(B5="PREMIUM",Inputs!$B$9,IF(B5="WORKHORSE",Inputs!$B$10,IF(B5="ECONOMY",Inputs!$B$11,B5))) -> anthropic/claude-opus-5.5 | D5: medium | E5: =IF(B5="PREMIUM",Inputs!$B$12&" (high)",IF(B5="WORKHORSE",Inputs!$B$13,IF(B5="ECONOMY",Inputs!$B$14,""))) -> google/gemini-3.8-flash (high) | F5: Runs once per brand; maxTokens 12,000 | G5: ='Unit Costs'!$AB$24 -> 0.23438541
A6: brand-extract.search | B6: ECONOMY | C6: =IF(B6="PREMIUM",Inputs!$B$9,IF(B6="WORKHORSE",Inputs!$B$10,IF(B6="ECONOMY",Inputs!$B$11,B6))) -> google/gemini-3.1-flash-lite | D6: low | E6: =IF(B6="PREMIUM",Inputs!$B$12&" (high)",IF(B6="WORKHORSE",Inputs!$B$13,IF(B6="ECONOMY",Inputs!$B$14,""))) -> openai/gpt-5.6-luna
A7: brand-kit/analyze-visual, describe | B7: WORKHORSE | C7: =IF(B7="PREMIUM",Inputs!$B$9,IF(B7="WORKHORSE",Inputs!$B$10,IF(B7="ECONOMY",Inputs!$B$11,B7))) -> google/gemini-3.8-flash | D7: medium | E7: =IF(B7="PREMIUM",Inputs!$B$12&" (high)",IF(B7="WORKHORSE",Inputs!$B$13,IF(B7="ECONOMY",Inputs!$B$14,""))) -> openai/gpt-5.6-terra | F7: Vision | G7: ='Unit Costs'!$AB$26 -> 0.01345758
A8: brand-kit/analyze-writing | B8: PREMIUM | C8: =IF(B8="PREMIUM",Inputs!$B$9,IF(B8="WORKHORSE",Inputs!$B$10,IF(B8="ECONOMY",Inputs!$B$11,B8))) -> anthropic/claude-opus-5.5 | D8: low | E8: =IF(B8="PREMIUM",Inputs!$B$12&" (high)",IF(B8="WORKHORSE",Inputs!$B$13,IF(B8="ECONOMY",Inputs!$B$14,""))) -> google/gemini-3.8-flash (high) | F8: Voice profile feeds every caption | G8: ='Unit Costs'!$AB$25 -> 0.082795081
A9: memory-extract | B9: WORKHORSE | C9: =IF(B9="PREMIUM",Inputs!$B$9,IF(B9="WORKHORSE",Inputs!$B$10,IF(B9="ECONOMY",Inputs!$B$11,B9))) -> google/gemini-3.8-flash | D9: low | E9: =IF(B9="PREMIUM",Inputs!$B$12&" (high)",IF(B9="WORKHORSE",Inputs!$B$13,IF(B9="ECONOMY",Inputs!$B$14,""))) -> openai/gpt-5.6-terra | G9: ='Unit Costs'!$AB$22 -> 0.012154391
A10: file-extract | B10: ECONOMY | C10: =IF(B10="PREMIUM",Inputs!$B$9,IF(B10="WORKHORSE",Inputs!$B$10,IF(B10="ECONOMY",Inputs!$B$11,B10))) -> google/gemini-3.1-flash-lite | D10: low | E10: =IF(B10="PREMIUM",Inputs!$B$12&" (high)",IF(B10="WORKHORSE",Inputs!$B$13,IF(B10="ECONOMY",Inputs!$B$14,""))) -> openai/gpt-5.6-luna | F10: Escalate to WORKHORSE when first read is thin | G10: ='Unit Costs'!$AB$23 -> 0.0077876935
A11: chat (mellox-flash, default) | B11: WORKHORSE | C11: =IF(B11="PREMIUM",Inputs!$B$9,IF(B11="WORKHORSE",Inputs!$B$10,IF(B11="ECONOMY",Inputs!$B$11,B11))) -> google/gemini-3.8-flash | D11: low | E11: =IF(B11="PREMIUM",Inputs!$B$12&" (high)",IF(B11="WORKHORSE",Inputs!$B$13,IF(B11="ECONOMY",Inputs!$B$14,""))) -> openai/gpt-5.6-terra | G11: ='Unit Costs'!$AB$19 -> 0.0089300575
A12: chat (mellox-pro) | B12: PREMIUM | C12: =IF(B12="PREMIUM",Inputs!$B$9,IF(B12="WORKHORSE",Inputs!$B$10,IF(B12="ECONOMY",Inputs!$B$11,B12))) -> anthropic/claude-opus-5.5 | D12: low | E12: =IF(B12="PREMIUM",Inputs!$B$12&" (high)",IF(B12="WORKHORSE",Inputs!$B$13,IF(B12="ECONOMY",Inputs!$B$14,""))) -> google/gemini-3.8-flash (high) | F12: Escalate to medium on strategy turns | G12: ='Unit Costs'!$AB$20 -> 0.04822555
A13: chat.research | B13: WORKHORSE | C13: =IF(B13="PREMIUM",Inputs!$B$9,IF(B13="WORKHORSE",Inputs!$B$10,IF(B13="ECONOMY",Inputs!$B$11,B13))) -> google/gemini-3.8-flash | D13: medium | E13: =IF(B13="PREMIUM",Inputs!$B$12&" (high)",IF(B13="WORKHORSE",Inputs!$B$13,IF(B13="ECONOMY",Inputs!$B$14,""))) -> openai/gpt-5.6-terra
A14: clarify | B14: WORKHORSE | C14: =IF(B14="PREMIUM",Inputs!$B$9,IF(B14="WORKHORSE",Inputs!$B$10,IF(B14="ECONOMY",Inputs!$B$11,B14))) -> google/gemini-3.8-flash | D14: low | E14: =IF(B14="PREMIUM",Inputs!$B$12&" (high)",IF(B14="WORKHORSE",Inputs!$B$13,IF(B14="ECONOMY",Inputs!$B$14,""))) -> openai/gpt-5.6-terra | F14: tool_choice auto only | G14: ='Unit Costs'!$AB$21 -> 0.0046201087
A15: chat.history-summary | B15: ECONOMY | C15: =IF(B15="PREMIUM",Inputs!$B$9,IF(B15="WORKHORSE",Inputs!$B$10,IF(B15="ECONOMY",Inputs!$B$11,B15))) -> google/gemini-3.1-flash-lite | D15: low | E15: =IF(B15="PREMIUM",Inputs!$B$12&" (high)",IF(B15="WORKHORSE",Inputs!$B$13,IF(B15="ECONOMY",Inputs!$B$14,""))) -> openai/gpt-5.6-luna | G15: ='Unit Costs'!$AB$6 -> 0.002831409
A16: content.*, social.multi | B16: WORKHORSE | C16: =IF(B16="PREMIUM",Inputs!$B$9,IF(B16="WORKHORSE",Inputs!$B$10,IF(B16="ECONOMY",Inputs!$B$11,B16))) -> google/gemini-3.8-flash | D16: medium | E16: =IF(B16="PREMIUM",Inputs!$B$12&" (high)",IF(B16="WORKHORSE",Inputs!$B$13,IF(B16="ECONOMY",Inputs!$B$14,""))) -> openai/gpt-5.6-terra | G16: ='Unit Costs'!$AB$36 -> 0.018933821
A17: ai-generate.* | B17: WORKHORSE | C17: =IF(B17="PREMIUM",Inputs!$B$9,IF(B17="WORKHORSE",Inputs!$B$10,IF(B17="ECONOMY",Inputs!$B$11,B17))) -> google/gemini-3.8-flash | D17: medium | E17: =IF(B17="PREMIUM",Inputs!$B$12&" (high)",IF(B17="WORKHORSE",Inputs!$B$13,IF(B17="ECONOMY",Inputs!$B$14,""))) -> openai/gpt-5.6-terra | F17: Escalate to PREMIUM for >1,500 words
A18: studio.article | B18: PREMIUM | C18: =IF(B18="PREMIUM",Inputs!$B$9,IF(B18="WORKHORSE",Inputs!$B$10,IF(B18="ECONOMY",Inputs!$B$11,B18))) -> anthropic/claude-opus-5.5 | D18: medium | E18: =IF(B18="PREMIUM",Inputs!$B$12&" (high)",IF(B18="WORKHORSE",Inputs!$B$13,IF(B18="ECONOMY",Inputs!$B$14,""))) -> google/gemini-3.8-flash (high) | F18: Articles go live; grounding/GEO gate | G18: ='Unit Costs'!$AB$31 -> 0.19315557
A19: studio.naturalize | B19: WORKHORSE | C19: =IF(B19="PREMIUM",Inputs!$B$9,IF(B19="WORKHORSE",Inputs!$B$10,IF(B19="ECONOMY",Inputs!$B$11,B19))) -> google/gemini-3.8-flash | D19: low | E19: =IF(B19="PREMIUM",Inputs!$B$12&" (high)",IF(B19="WORKHORSE",Inputs!$B$13,IF(B19="ECONOMY",Inputs!$B$14,""))) -> openai/gpt-5.6-terra | G19: ='Unit Costs'!$AB$5 -> 0.0054635813
A20: studio.ideas | B20: WORKHORSE | C20: =IF(B20="PREMIUM",Inputs!$B$9,IF(B20="WORKHORSE",Inputs!$B$10,IF(B20="ECONOMY",Inputs!$B$11,B20))) -> google/gemini-3.8-flash | D20: low | E20: =IF(B20="PREMIUM",Inputs!$B$12&" (high)",IF(B20="WORKHORSE",Inputs!$B$13,IF(B20="ECONOMY",Inputs!$B$14,""))) -> openai/gpt-5.6-terra | F20: temperature ~0.9 | G20: ='Unit Costs'!$AB$35 -> 0.014282062
A21: studio.prompt, studio.research | B21: WORKHORSE | C21: =IF(B21="PREMIUM",Inputs!$B$9,IF(B21="WORKHORSE",Inputs!$B$10,IF(B21="ECONOMY",Inputs!$B$11,B21))) -> google/gemini-3.8-flash | D21: low / medium | E21: =IF(B21="PREMIUM",Inputs!$B$12&" (high)",IF(B21="WORKHORSE",Inputs!$B$13,IF(B21="ECONOMY",Inputs!$B$14,""))) -> openai/gpt-5.6-terra
A22: campaign-generation | B22: PREMIUM | C22: =IF(B22="PREMIUM",Inputs!$B$9,IF(B22="WORKHORSE",Inputs!$B$10,IF(B22="ECONOMY",Inputs!$B$11,B22))) -> anthropic/claude-opus-5.5 | D22: low | E22: =IF(B22="PREMIUM",Inputs!$B$12&" (high)",IF(B22="WORKHORSE",Inputs!$B$13,IF(B22="ECONOMY",Inputs!$B$14,""))) -> google/gemini-3.8-flash (high) | G22: ='Unit Costs'!$AB$37 -> 0.10645082
A23: schedule.* | B23: WORKHORSE | C23: =IF(B23="PREMIUM",Inputs!$B$9,IF(B23="WORKHORSE",Inputs!$B$10,IF(B23="ECONOMY",Inputs!$B$11,B23))) -> google/gemini-3.8-flash | D23: medium | E23: =IF(B23="PREMIUM",Inputs!$B$12&" (high)",IF(B23="WORKHORSE",Inputs!$B$13,IF(B23="ECONOMY",Inputs!$B$14,""))) -> openai/gpt-5.6-terra
A24: coach, coach.briefing | B24: PREMIUM | C24: =IF(B24="PREMIUM",Inputs!$B$9,IF(B24="WORKHORSE",Inputs!$B$10,IF(B24="ECONOMY",Inputs!$B$11,B24))) -> anthropic/claude-opus-5.5 | D24: low | E24: =IF(B24="PREMIUM",Inputs!$B$12&" (high)",IF(B24="WORKHORSE",Inputs!$B$13,IF(B24="ECONOMY",Inputs!$B$14,""))) -> google/gemini-3.8-flash (high) | F24: High effort for deep strategy | G24: ='Unit Costs'!$AB$38 -> 0.19590927
A25: coach.research, coach.trends | B25: WORKHORSE | C25: =IF(B25="PREMIUM",Inputs!$B$9,IF(B25="WORKHORSE",Inputs!$B$10,IF(B25="ECONOMY",Inputs!$B$11,B25))) -> google/gemini-3.8-flash | D25: low | E25: =IF(B25="PREMIUM",Inputs!$B$12&" (high)",IF(B25="WORKHORSE",Inputs!$B$13,IF(B25="ECONOMY",Inputs!$B$14,""))) -> openai/gpt-5.6-terra | G25: ='Unit Costs'!$AB$9 -> 0.0079750088
A26: market-intelligence | B26: PREMIUM | C26: =IF(B26="PREMIUM",Inputs!$B$9,IF(B26="WORKHORSE",Inputs!$B$10,IF(B26="ECONOMY",Inputs!$B$11,B26))) -> anthropic/claude-opus-5.5 | D26: medium | E26: =IF(B26="PREMIUM",Inputs!$B$12&" (high)",IF(B26="WORKHORSE",Inputs!$B$13,IF(B26="ECONOMY",Inputs!$B$14,""))) -> google/gemini-3.8-flash (high) | F26: Keep the source-content cache | G26: ='Unit Costs'!$AB$40 -> 0.24343934
A27: analytics/insights | B27: WORKHORSE | C27: =IF(B27="PREMIUM",Inputs!$B$9,IF(B27="WORKHORSE",Inputs!$B$10,IF(B27="ECONOMY",Inputs!$B$11,B27))) -> google/gemini-3.8-flash | D27: medium | E27: =IF(B27="PREMIUM",Inputs!$B$12&" (high)",IF(B27="WORKHORSE",Inputs!$B$13,IF(B27="ECONOMY",Inputs!$B$14,""))) -> openai/gpt-5.6-terra | G27: ='Unit Costs'!$AB$45 -> 0.01680615
A28: agent.content-fit, analytics/insights-auto | B28: WORKHORSE | C28: =IF(B28="PREMIUM",Inputs!$B$9,IF(B28="WORKHORSE",Inputs!$B$10,IF(B28="ECONOMY",Inputs!$B$11,B28))) -> google/gemini-3.8-flash | D28: low | E28: =IF(B28="PREMIUM",Inputs!$B$12&" (high)",IF(B28="WORKHORSE",Inputs!$B$13,IF(B28="ECONOMY",Inputs!$B$14,""))) -> openai/gpt-5.6-terra
A29: competitors.discovery, competitors.profile | B29: WORKHORSE | C29: =IF(B29="PREMIUM",Inputs!$B$9,IF(B29="WORKHORSE",Inputs!$B$10,IF(B29="ECONOMY",Inputs!$B$11,B29))) -> google/gemini-3.8-flash | D29: low | E29: =IF(B29="PREMIUM",Inputs!$B$12&" (high)",IF(B29="WORKHORSE",Inputs!$B$13,IF(B29="ECONOMY",Inputs!$B$14,""))) -> openai/gpt-5.6-terra | F29: Grounded classification only | G29: ='Unit Costs'!$AB$41 -> 0.051391164
A30: competitors.updates | B30: ECONOMY | C30: =IF(B30="PREMIUM",Inputs!$B$9,IF(B30="WORKHORSE",Inputs!$B$10,IF(B30="ECONOMY",Inputs!$B$11,B30))) -> google/gemini-3.1-flash-lite | D30: low | E30: =IF(B30="PREMIUM",Inputs!$B$12&" (high)",IF(B30="WORKHORSE",Inputs!$B$13,IF(B30="ECONOMY",Inputs!$B$14,""))) -> openai/gpt-5.6-luna | F30: High volume | G30: ='Unit Costs'!$AB$43 -> 0.018390968
A31: competitor-intel | B31: WORKHORSE | C31: =IF(B31="PREMIUM",Inputs!$B$9,IF(B31="WORKHORSE",Inputs!$B$10,IF(B31="ECONOMY",Inputs!$B$11,B31))) -> google/gemini-3.8-flash | D31: medium | E31: =IF(B31="PREMIUM",Inputs!$B$12&" (high)",IF(B31="WORKHORSE",Inputs!$B$13,IF(B31="ECONOMY",Inputs!$B$14,""))) -> openai/gpt-5.6-terra | G31: ='Unit Costs'!$AB$44 -> 0.056768828
A32: geo.probe | B32: perplexity/sonar + openai/gpt-5.6-luna + google/gemini-3.8-flash | C32: =IF(B32="PREMIUM",Inputs!$B$9,IF(B32="WORKHORSE",Inputs!$B$10,IF(B32="ECONOMY",Inputs!$B$11,B32))) -> perplexity/sonar + openai/gpt-5.6-luna + google/gemini-3.8-flash | D32: default | E32: =IF(B32="PREMIUM",Inputs!$B$12&" (high)",IF(B32="WORKHORSE",Inputs!$B$13,IF(B32="ECONOMY",Inputs!$B$14,""))) | F32: Each engine probed separately | G32: ='Unit Costs'!$AB$50 -> 0.015917312
A33: geo.fix.propose, geo.fix.batch | B33: PREMIUM | C33: =IF(B33="PREMIUM",Inputs!$B$9,IF(B33="WORKHORSE",Inputs!$B$10,IF(B33="ECONOMY",Inputs!$B$11,B33))) -> anthropic/claude-opus-5.5 | D33: medium | E33: =IF(B33="PREMIUM",Inputs!$B$12&" (high)",IF(B33="WORKHORSE",Inputs!$B$13,IF(B33="ECONOMY",Inputs!$B$14,""))) -> google/gemini-3.8-flash (high) | G33: ='Unit Costs'!$AB$53 -> 0.28623442
A34: geo.cms.fix | B34: WORKHORSE | C34: =IF(B34="PREMIUM",Inputs!$B$9,IF(B34="WORKHORSE",Inputs!$B$10,IF(B34="ECONOMY",Inputs!$B$11,B34))) -> google/gemini-3.8-flash | D34: medium | E34: =IF(B34="PREMIUM",Inputs!$B$12&" (high)",IF(B34="WORKHORSE",Inputs!$B$13,IF(B34="ECONOMY",Inputs!$B$14,""))) -> openai/gpt-5.6-terra | F34: Retry once on PREMIUM when rejected | G34: ='Unit Costs'!$AB$54 -> 0.10706053
A35: GEO coding agent | B35: PREMIUM | C35: =IF(B35="PREMIUM",Inputs!$B$9,IF(B35="WORKHORSE",Inputs!$B$10,IF(B35="ECONOMY",Inputs!$B$11,B35))) -> anthropic/claude-opus-5.5 | D35: high / medium | E35: =IF(B35="PREMIUM",Inputs!$B$12&" (high)",IF(B35="WORKHORSE",Inputs!$B$13,IF(B35="ECONOMY",Inputs!$B$14,""))) -> google/gemini-3.8-flash (high) | F35: Investigate + implement high; self-review medium | G35: ='Unit Costs'!$AB$55 -> 1.6
A36: experiments.hypotheses | B36: PREMIUM | C36: =IF(B36="PREMIUM",Inputs!$B$9,IF(B36="WORKHORSE",Inputs!$B$10,IF(B36="ECONOMY",Inputs!$B$11,B36))) -> anthropic/claude-opus-5.5 | D36: low | E36: =IF(B36="PREMIUM",Inputs!$B$12&" (high)",IF(B36="WORKHORSE",Inputs!$B$13,IF(B36="ECONOMY",Inputs!$B$14,""))) -> google/gemini-3.8-flash (high) | G36: ='Unit Costs'!$AB$56 -> 0.14362084
A37: experiments.values | B37: WORKHORSE | C37: =IF(B37="PREMIUM",Inputs!$B$9,IF(B37="WORKHORSE",Inputs!$B$10,IF(B37="ECONOMY",Inputs!$B$11,B37))) -> google/gemini-3.8-flash | D37: medium | E37: =IF(B37="PREMIUM",Inputs!$B$12&" (high)",IF(B37="WORKHORSE",Inputs!$B$13,IF(B37="ECONOMY",Inputs!$B$14,""))) -> openai/gpt-5.6-terra | G37: ='Unit Costs'!$AB$11 -> 0.041971065
A38: links-topical-fit | B38: ECONOMY | C38: =IF(B38="PREMIUM",Inputs!$B$9,IF(B38="WORKHORSE",Inputs!$B$10,IF(B38="ECONOMY",Inputs!$B$11,B38))) -> google/gemini-3.1-flash-lite | D38: low | E38: =IF(B38="PREMIUM",Inputs!$B$12&" (high)",IF(B38="WORKHORSE",Inputs!$B$13,IF(B38="ECONOMY",Inputs!$B$14,""))) -> openai/gpt-5.6-luna | F38: Many calls | G38: ='Unit Costs'!$AB$58 -> 0.030085699
A39: links-relevance-pick | B39: WORKHORSE | C39: =IF(B39="PREMIUM",Inputs!$B$9,IF(B39="WORKHORSE",Inputs!$B$10,IF(B39="ECONOMY",Inputs!$B$11,B39))) -> google/gemini-3.8-flash | D39: low | E39: =IF(B39="PREMIUM",Inputs!$B$12&" (high)",IF(B39="WORKHORSE",Inputs!$B$13,IF(B39="ECONOMY",Inputs!$B$14,""))) -> openai/gpt-5.6-terra | G39: ='Unit Costs'!$AB$13 -> 0.0096366337
A40: ugc.product.extract / ugc.concepts / ugc.notes | B40: WORKHORSE | C40: =IF(B40="PREMIUM",Inputs!$B$9,IF(B40="WORKHORSE",Inputs!$B$10,IF(B40="ECONOMY",Inputs!$B$11,B40))) -> google/gemini-3.8-flash | D40: low / medium / low | E40: =IF(B40="PREMIUM",Inputs!$B$12&" (high)",IF(B40="WORKHORSE",Inputs!$B$13,IF(B40="ECONOMY",Inputs!$B$14,""))) -> openai/gpt-5.6-terra | G40: ='Unit Costs'!$AB$57 -> 0.051274582
A41: guardrails.image-moderation | B41: ECONOMY | C41: =IF(B41="PREMIUM",Inputs!$B$9,IF(B41="WORKHORSE",Inputs!$B$10,IF(B41="ECONOMY",Inputs!$B$11,B41))) -> google/gemini-3.1-flash-lite | D41: low | E41: =IF(B41="PREMIUM",Inputs!$B$12&" (high)",IF(B41="WORKHORSE",Inputs!$B$13,IF(B41="ECONOMY",Inputs!$B$14,""))) -> openai/gpt-5.6-luna | G41: ='Unit Costs'!$AB$7 -> 0.00086515275
A42: Images: default / premium | B42: openai/gpt-image-2.5-flare / sunburst | C42: =IF(B42="PREMIUM",Inputs!$B$9,IF(B42="WORKHORSE",Inputs!$B$10,IF(B42="ECONOMY",Inputs!$B$11,B42))) -> openai/gpt-image-2.5-flare / sunburst | D42: - | E42: =IF(B42="PREMIUM",Inputs!$B$12&" (high)",IF(B42="WORKHORSE",Inputs!$B$13,IF(B42="ECONOMY",Inputs!$B$14,""))) | F42: Each falls back to the other | G42: ='Unit Costs'!$AB$16 -> 0.036783699
A43: Video: standard, draft, variation | B43: KIE (Veo 3.1 Fast / Lite, Grok Imagine) | C43: =IF(B43="PREMIUM",Inputs!$B$9,IF(B43="WORKHORSE",Inputs!$B$10,IF(B43="ECONOMY",Inputs!$B$11,B43))) -> KIE (Veo 3.1 Fast / Lite, Grok Imagine) | D43: - | E43: =IF(B43="PREMIUM",Inputs!$B$12&" (high)",IF(B43="WORKHORSE",Inputs!$B$13,IF(B43="ECONOMY",Inputs!$B$14,""))) | F43: Fallback to OpenRouter Veo (variation falls back to Veo 3.1 Lite, never Grok on OpenRouter)
A44: Video: premium, cinematic, long take, Studio 6s | B44: OpenRouter (Hailuo 3, Seedance 2.0 Fast) | C44: =IF(B44="PREMIUM",Inputs!$B$9,IF(B44="WORKHORSE",Inputs!$B$10,IF(B44="ECONOMY",Inputs!$B$11,B44))) -> OpenRouter (Hailuo 3, Seedance 2.0 Fast) | D44: - | E44: =IF(B44="PREMIUM",Inputs!$B$12&" (high)",IF(B44="WORKHORSE",Inputs!$B$13,IF(B44="ECONOMY",Inputs!$B$14,""))) | F44: KIE prices for Gemini Omni / MiniMax H3 are unverified and Seedance is cheaper on OpenRouter

Sheet Vendor Prices
A1: Vendor price book for the OpenRouter-first stack (checked 2026-09-25)
A2: Blue = input. OR fee = 1 when the item is bought through OpenRouter credits (5.5% top-up fee applies). Kie rows: edit credits in column F.
A4: Key | B4: Category | C4: Vendor | D4: Item / where used | E4: Unit | F4: Native qty | G4: USD price (in / per unit) | H4: USD price (out) | I4: Cache read ($/1M) | J4: OR fee | K4: Status / notes | L4: Source
A5: anthropic/claude-opus-5.5 | B5: LLM | C5: OpenRouter (Anthropic) | D5: PREMIUM tier: Brand DNA, articles, Coach, Market Brain, GEO fixes, GEO agent, campaigns, Mellox Pro chat | E5: $ / 1M tokens | G5: 4 | H5: 20 | I5: 0.2 | J5: 1 | K5: Released 2026-09-22. Thinking cannot be disabled. Opus-family tokenizer ~1.0-1.35x. | L5: https://openrouter.ai/anthropic/claude-opus-5.5
A6: google/gemini-3.8-flash | B6: LLM | C6: OpenRouter (Google) | D6: WORKHORSE tier: chat (Flash), Studio posts, vision, research, competitors, UGC scripts; GEO probe engine | E6: $ / 1M tokens | G6: 0.75 | H6: 3.75 | I6: 0.1875 | J6: 1 | K6: Reasoning model: always send an effort. Cache read assumed 25% of input (verify). | L6: https://openrouter.ai/google/gemini-3.8-flash
A7: google/gemini-3.1-flash-lite | B7: LLM | C7: OpenRouter (Google) | D7: ECONOMY tier: history summaries, file extract, competitor sweeps, link fit, moderation | E7: $ / 1M tokens | G7: 0.25 | H7: 1.5 | I7: 0.0625 | J7: 1 | K7: GA | L7: https://openrouter.ai/google/gemini-3.1-flash-lite
A8: openai/gpt-5.6-terra | B8: LLM | C8: OpenRouter (OpenAI) | D8: WORKHORSE fallback | E8: $ / 1M tokens | G8: 2 | H8: 12 | I8: 0.2 | J8: 1 | K8: 2.7x input / 3.2x output of Gemini 3.8 Flash | L8: https://openrouter.ai/openai/gpt-5.6-terra
A9: openai/gpt-5.6-luna | B9: LLM | C9: OpenRouter (OpenAI) | D9: ECONOMY fallback; GEO probe engine ('ChatGPT') | E9: $ / 1M tokens | G9: 0.2 | H9: 1.2 | I9: 0.05 | J9: 1 | K9: No web search unless a search plugin is added | L9: https://openrouter.ai/openai/gpt-5.6-luna
A10: perplexity/sonar | B10: LLM | C10: OpenRouter (Perplexity) | D10: GEO probe engine (Perplexity) | E10: $ / 1M tokens | G10: 1 | H10: 1 | J10: 1 | K10: Plus per-request fee below | L10: https://openrouter.ai/perplexity/sonar
A11: sonar-request-low | B11: Search | C11: Perplexity via OpenRouter | D11: Sonar request fee, low search context | E11: $ / request | G11: 0.005 | J11: 1 | K11: $5 per 1,000 requests | L11: https://docs.perplexity.ai/docs/getting-started/pricing
A12: img-flare | B12: Image | C12: OpenRouter (OpenAI GPT Image 2.5 Flare) | D12: Default social image / quick edit; native qty = output tokens per image | E12: $ / image | F12: 600 | G12: =(F12*30+1000*8)/1000000 -> 0.026 | J12: 1 | K12: $8/M input, $30/M output. 1024px medium ~440 tokens; social 4:5 / 9:16 ~600 (estimate). | L12: https://openrouter.ai/openai/gpt-image-2.5-flare
A13: img-sunburst | B13: Image | C13: OpenRouter (OpenAI GPT Image 2.5 Sunburst) | D13: Premium / text-heavy / precise edit; native qty = output tokens per image | E13: $ / image | F13: 1800 | G13: =(F13*30+1000*8)/1000000 -> 0.062 | J13: 1 | K13: High quality 1024px ~1,756 output tokens | L13: https://openrouter.ai/openai/gpt-image-2.5-sunburst
A14: img-ref | B14: Image | C14: OpenRouter (OpenAI GPT Image 2.5) | D14: Reference image input for edits (per image); native qty = input tokens | E14: $ / reference | F14: 1300 | G14: =F14*8/1000000 -> 0.0104 | J14: 1 | K14: Up to 4 references per edit | L14: https://openrouter.ai/openai/gpt-image-2.5-flare
A15: or-veo31fast-720 | B15: Video | C15: OpenRouter (Google Veo 3.1 Fast) | D15: standard key, 720p with audio | E15: $ / second | G15: 0.1 | J15: 1 | K15: 4/6/8 s | L15: https://openrouter.ai/api/v1/videos/models
A16: or-veo31fast-1080 | B16: Video | C16: OpenRouter (Google Veo 3.1 Fast) | D16: standard key, 1080p with audio | E16: $ / second | G16: 0.12 | J16: 1 | K16: 4K = $0.30/s | L16: https://openrouter.ai/api/v1/videos/models
A17: or-veo31lite-720 | B17: Video | C17: OpenRouter (Google Veo 3.1 Lite) | D17: draft key, 720p with audio | E17: $ / second | G17: 0.05 | J17: 1 | L17: https://openrouter.ai/api/v1/videos/models
A18: or-veo31lite-1080 | B18: Video | C18: OpenRouter (Google Veo 3.1 Lite) | D18: draft key, 1080p with audio | E18: $ / second | G18: 0.08 | J18: 1 | L18: https://openrouter.ai/api/v1/videos/models
A19: or-hailuo3-s | B19: Video | C19: OpenRouter (MiniMax Hailuo 3) | D19: premium + cinematic keys, 2K with audio | E19: $ / second | G19: 0.13 | J19: 1 | K19: 5-15 s | L19: https://openrouter.ai/api/v1/videos/models
A20: or-hailuo3-ref | B20: Video | C20: OpenRouter (MiniMax Hailuo 3) | D20: Reference image | E20: $ / image | G20: 0.04 | J20: 1 | L20: https://openrouter.ai/api/v1/videos/models
A21: or-seedance2fast-480-s | B21: Video | C21: OpenRouter (Seedance 2.0 Fast) | D21: long key, 480p (854x480x24 fps video tokens) | E21: $ / second | G21: =0.0000042*854*480*24/1024 -> 0.0403515 | J21: 1 | K21: $0.0000042 per video token | L21: https://openrouter.ai/api/v1/videos/models
A22: or-seedance2fast-720-s | B22: Video | C22: OpenRouter (Seedance 2.0 Fast) | D22: long key, 720p | E22: $ / second | G22: =0.0000042*1280*720*24/1024 -> 0.09072 | J22: 1 | K22: 4-15 s | L22: https://openrouter.ai/api/v1/videos/models
A23: or-grok15-480-s | B23: Video | C23: OpenRouter (Grok Imagine Video 1.5) | D23: variation key, 480p | E23: $ / second | G23: 0.08 | J23: 1 | K23: +$0.01 per input image | L23: https://openrouter.ai/api/v1/videos/models
A24: or-grok15-720-s | B24: Video | C24: OpenRouter (Grok Imagine Video 1.5) | D24: variation key, 720p | E24: $ / second | G24: 0.14 | J24: 1 | K24: 1080p $0.25/s | L24: https://openrouter.ai/api/v1/videos/models
A25: or-grok15-img | B25: Video | C25: OpenRouter (Grok Imagine Video 1.5) | D25: Input image | E25: $ / image | G25: 0.01 | J25: 1 | L25: https://openrouter.ai/api/v1/videos/models
A26: kie-credit | B26: Video | C26: Kie.ai | D26: Kie credit | E26: $ / credit | G26: 0.005 | J26: 0 | K26: Kept for Veo 3.1 Fast/Lite and Grok Imagine; OpenRouter for the rest | L26: https://www.bitdoze.com/kie-ai-video-generation/
A27: kie-veo-fast-720 | B27: Video | C27: Kie.ai | D27: Veo 3.1 Fast 8s 720p (per video) | E27: Kie credits | F27: 60 | G27: =F27*$G$26 -> 0.3 | J27: 0 | K27: src/lib/ugc/models.ts, confirmed 2026-09-16 | L27: src/lib/ugc/models.ts
A28: kie-veo-fast-1080 | B28: Video | C28: Kie.ai | D28: Veo 3.1 Fast 8s 1080p (per video) | E28: Kie credits | F28: 65 | G28: =F28*$G$26 -> 0.325 | J28: 0 | L28: src/lib/ugc/models.ts
A29: kie-veo-lite-720 | B29: Video | C29: Kie.ai | D29: Veo 3.1 Lite 8s 720p (per video) | E29: Kie credits | F29: 30 | G29: =F29*$G$26 -> 0.15 | J29: 0 | L29: src/lib/ugc/models.ts
A30: kie-veo-lite-1080 | B30: Video | C30: Kie.ai | D30: Veo 3.1 Lite 8s 1080p (per video) | E30: Kie credits | F30: 35 | G30: =F30*$G$26 -> 0.175 | J30: 0 | L30: src/lib/ugc/models.ts
A31: kie-seedance2fast-480-s | B31: Video | C31: Kie.ai | D31: Seedance 2.0 Fast 480p (per second) | E31: Kie credits | F31: 11.7 | G31: =F31*$G$26 -> 0.0585 | J31: 0 | L31: src/lib/ugc/models.ts
A32: kie-seedance2fast-720-s | B32: Video | C32: Kie.ai | D32: Seedance 2.0 Fast 720p (per second) | E32: Kie credits | F32: 24.8 | G32: =F32*$G$26 -> 0.124 | J32: 0 | L32: src/lib/ugc/models.ts
A33: kie-grok-480 | B33: Video | C33: Kie.ai | D33: Grok Imagine 480p (per video) | E33: Kie credits | F33: 12 | G33: =F33*$G$26 -> 0.06 | J33: 0 | L33: src/lib/ugc/models.ts
A34: kie-grok-720 | B34: Video | C34: Kie.ai | D34: Grok Imagine 720p (per video) | E34: Kie credits | F34: 24 | G34: =F34*$G$26 -> 0.12 | J34: 0 | L34: src/lib/ugc/models.ts
A35: kie-omni-1080-s | B35: Video | C35: Kie.ai | D35: Gemini Omni Flash 1.1 1080p (per second) | E35: Kie credits | F35: 20 | G35: =F35*$G$26 -> 0.1 | J35: 0 | K35: ESTIMATE - VERIFY on Kie pricing page (Google direct ~$0.15/s) | L35: src/lib/ugc/models.ts
A36: kie-h3-s | B36: Video | C36: Kie.ai | D36: MiniMax H3 (per second) | E36: Kie credits | F36: 10 | G36: =F36*$G$26 -> 0.05 | J36: 0 | K36: ESTIMATE - VERIFY (Kie blog: H3 Max $0.05/s) | L36: https://kie.ai/blog/what-is-minimax-h3-max
A37: tavily-credit | B37: Search | C37: Tavily | D37: API credit (basic search 1) | E37: $ / credit | G37: 0.008 | J37: 0 | K37: 1,000 free credits/month | L37: https://www.tavily.com/pricing
A38: exa-search | B38: Search | C38: OpenRouter (Exa) | D38: Web search plugin request (adds search to Luna / Gemini probes) | E38: $ / request | G38: 0.007 | J38: 1 | L38: https://openrouter.ai/docs/guides/features/plugins/web-search
A39: dfs-llm-scraper-std | B39: GEO data | C39: DataForSEO | D39: Real ChatGPT / Gemini answer (LLM Scraper, standard queue) | E39: $ / result | G39: 0.0012 | J39: 0 | K39: Optional real-answer tracking | L39: https://dataforseo.com/pricing/ai-optimization/llm-scraper
A40: dfs-serp-std | B40: GEO data | C40: DataForSEO | D40: Google SERP incl. AI Overview (standard queue) | E40: $ / SERP | G40: 0.0006 | J40: 0 | K40: Google AI Overviews are not covered by the spec's probe engines | L40: https://dataforseo.com/pricing/serp/google-organic-serp-api
A41: postforme-starter | B41: Distribution | C41: Post for Me | D41: Starter plan (1,000 posts / month, unlimited accounts) | E41: $ / month | F41: 1000 | G41: 10 | J41: 0 | K41: Billed by monthly post volume; one post assumed per network published. Higher tiers are by volume and not published: assumed the same $0.01 a post (verify) | L41: https://www.postforme.dev/pricing
A42: rixot-link | B42: Backlinks | C42: Rixot | D42: Backlink placement, typical mid-range | E42: $ / link | G42: 25 | J42: 0 | K42: $1-$500 by DR | L42: https://rixot.com/pricing
A43: supabase-pro | B43: Infra | C43: Supabase | D43: Pro plan | E43: $ / month | G43: 25 | J43: 0 | L43: https://supabase.com/pricing
A44: supabase-small | B44: Infra | C44: Supabase | D44: Compute Small | E44: $ / month | G44: 15 | J44: 0 | L44: https://supabase.com/pricing
A45: supabase-medium | B45: Infra | C45: Supabase | D45: Compute Medium | E45: $ / month | G45: 60 | J45: 0 | L45: https://supabase.com/pricing
A46: supabase-large | B46: Infra | C46: Supabase | D46: Compute Large | E46: $ / month | G46: 110 | J46: 0 | L46: https://supabase.com/pricing
A47: compute-per-page | B47: Infra | C47: Mellox on Railway | D47: GEO crawl compute per page (estimate) | E47: $ / page | G47: 0.0003 | J47: 0 | L47: Internal estimate
A48: sentry-team | B48: Tools | C48: Sentry | D48: Team plan | E48: $ / month | G48: 26 | J48: 0 | L48: https://blog.struct.ai/sentry-pricing-error-monitoring-2026/
A49: resend-pro | B49: Tools | C49: Resend | D49: Email Pro | E49: $ / month | G49: 20 | J49: 0 | L49: https://resend.com/pricing
A50: gworkspace-user | B50: Tools | C50: Google Workspace | D50: Seat (estimate) | E50: $ / user-month | G50: 8.4 | J50: 0 | L50: https://workspace.google.com/pricing
A51: domain-ai-year | B51: Tools | C51: Registrar | D51: .ai domain (estimate) | E51: $ / year | G51: 80 | J51: 0 | L51: Internal estimate
A52: lightsail-2gb | B52: Infra | C52: AWS Lightsail | D52: SDR server (legacy) | E52: $ / month | G52: 12 | J52: 0 | L52: https://aws.amazon.com/lightsail/pricing/
A53: openrouter-fee | B53: Fees | C53: OpenRouter | D53: Credit purchase fee (now applies to ~all AI spend) | E53: % of top-up | G53: 0.055 | J53: 0 | K53: $0.80 minimum per purchase | L53: https://omidsaffari.com/blog/openrouter-pricing
A54: paddle-pct | B54: Fees | C54: Paddle | D54: Merchant of record % | E54: % of charge | G54: 0.05 | J54: 0 | L54: https://jawadhassan.dev/blog/paddle-vs-lemonsqueezy-pakistan
A55: paddle-fixed | B55: Fees | C55: Paddle | D55: Per transaction | E55: $ / transaction | G55: 0.5 | J55: 0 | L55: https://jawadhassan.dev/blog/paddle-vs-lemonsqueezy-pakistan
A56: payout-fx | B56: Fees | C56: Payoneer / bank | D56: USD to PKR spread (estimate) | E56: % of revenue | G56: 0.02 | J56: 0 | L56: https://jawadhassan.dev/blog/paddle-vs-lemonsqueezy-pakistan
A57: pk-tax-pseb | B57: Tax | C57: FBR Pakistan | D57: IT export tax, PSEB-registered | E57: % of export proceeds | G57: 0.0025 | J57: 0 | K57: 1% if not registered | L57: https://filing.pk/blog/freelancer-tax-pakistan
A58: usd-pkr | B58: FX | C58: Market | D58: USD to PKR | E58: PKR per USD | G58: 277.09 | J58: 0 | K58: 2026-09-23 | L58: https://www.poundsterlinglive.com/history/USD-PKR-2026

Sheet Fixed Costs
A1: Fixed monthly operating costs by stage (USD)
A2: Variable per-customer costs are on the Plans tab.
A4: Item | B4: Vendor / basis | C4: Launch | D4: Traction | E4: Growth | F4: Scale | G4: Notes
A5: Stage starts at paying customers | C5: 0 | D5: 26 | E5: 151 | F5: 601
A6: App hosting (Railway usage) | B6: Railway Pro | C6: 25 | D6: 60 | E6: 180 | F6: 450 | G6: Cron hooks keep it always on
A7: Redis cache | B7: Railway Redis | C7: 3 | D7: 5 | E7: 10 | F7: 20
A8: Supabase Pro | B8: Supabase | C8: ='Vendor Prices'!$G$43 -> 25 | D8: ='Vendor Prices'!$G$43 -> 25 | E8: ='Vendor Prices'!$G$43 -> 25 | F8: ='Vendor Prices'!$G$43 -> 25
A9: Supabase compute upgrade (net of $10 credit) | B9: Supabase | C9: 0 | D9: ='Vendor Prices'!$G$44-10 -> 5 | E9: ='Vendor Prices'!$G$45-10 -> 50 | F9: ='Vendor Prices'!$G$46-10 -> 100
A10: Supabase storage + egress (videos) | B10: Supabase | C10: 0 | D10: 8 | E10: 35 | F10: 120 | G10: More video now; OpenRouter files are downloaded and stored
A11: Post for Me base plan (minimum) | B11: Post for Me | C11: 10 | D11: 0 | E11: 0 | F11: 0 | G11: $10 covers 1,000 posts; usage above that is in cost to serve
A12: Error monitoring | B12: Sentry | C12: 0 | D12: ='Vendor Prices'!$G$48 -> 26 | E12: ='Vendor Prices'!$G$48 -> 26 | F12: 80
A13: Transactional email | B13: Resend | C13: 0 | D13: ='Vendor Prices'!$G$49 -> 20 | E13: ='Vendor Prices'!$G$49 -> 20 | F13: 90 | G13: Weekly briefings + reports raise email volume
A14: Google Workspace | B14: Google | C14: =2*'Vendor Prices'!$G$50 -> 16.8 | D14: =3*'Vendor Prices'!$G$50 -> 25.2 | E14: =6*'Vendor Prices'!$G$50 -> 50.4 | F14: =12*'Vendor Prices'!$G$50 -> 100.8
A15: .ai domain | B15: Registrar | C15: ='Vendor Prices'!$G$51/12 -> 6.6666667 | D15: ='Vendor Prices'!$G$51/12 -> 6.6666667 | E15: ='Vendor Prices'!$G$51/12 -> 6.6666667 | F15: ='Vendor Prices'!$G$51/12 -> 6.6666667
A16: Self-hosted Firecrawl / Helicone server | B16: VPS | C16: 0 | D16: 15 | E16: 30 | F16: 60
A17: SDR server (legacy) | B17: AWS Lightsail | C17: ='Vendor Prices'!$G$52 -> 12 | D17: 0 | E17: 0 | F17: 0 | G17: Turn off: Post for Me replaces it
A18: Internal AI use (dev, QA, evals, live tests) | B18: OpenRouter | C18: 80 | D18: 150 | E18: 300 | F18: 600 | G18: Opus 5.5 evals are pricier
A19: Uptime monitor + support desk | B19: Various | C19: 0 | D19: 0 | E19: 70 | F19: 175
A20: Accountant, FBR / SECP / PSEB | B20: Pakistan | C20: 36 | D20: 54 | E20: 108 | F20: 200
A21: Legal (terms, privacy, DPA) | B21: Lawyer | C21: 10 | D21: 20 | E21: 40 | F21: 80
A22: Founder dev tools | B22: Various | C22: 60 | D22: 100 | E22: 200 | F22: 400
A23: Baseline marketing | B23: Various | C23: 0 | D23: 200 | E23: 800 | F23: 2500
A24: Team, excluding founders | B24: Salaries | C24: 0 | D24: 900 | E24: 4000 | F24: 12000
A25: TOTAL FIXED COSTS (USD / month) | C25: =SUM(C6:C24) -> 284.46667 | D25: =SUM(D6:D24) -> 1619.8667 | E25: =SUM(E6:E24) -> 5951.0667 | F25: =SUM(F6:F24) -> 17007.467
A26: TOTAL FIXED COSTS (PKR / month) | C26: =C25*Inputs!$B$5 -> 78822.869 | D26: =D25*Inputs!$B$5 -> 448848.85 | E26: =E25*Inputs!$B$5 -> 1648981.1 | F26: =F25*Inputs!$B$5 -> 4712598.9
A27: Run cost (excluding team and marketing) | C27: =C25-C24-C23 -> 284.46667 | D27: =D25-D24-D23 -> 519.86667 | E27: =E25-E24-E23 -> 1151.0667 | F27: =F25-F24-F23 -> 2507.4667

Sheet Projection
A1: 24-month projection (three scenarios)
A2: Pick the scenario in B4. Drivers in rows 7-23; everything else is formula.
A4: Scenario in use (1 = Conservative, 2 = Base, 3 = Optimistic) | B4: 2
A6: Driver | B6: Conservative | C6: Base | D6: Optimistic | E6: In use
A7: New paying customers in month 1 | B7: 2 | C7: 3 | D7: 5 | E7: =INDEX(B7:D7,1,$B$4) -> 3
A8: Monthly growth in new customers, months 1-12 | B8: 0.1 | C8: 0.15 | D8: 0.22 | E8: =INDEX(B8:D8,1,$B$4) -> 0.15
A9: Monthly growth in new customers, months 13-24 | B9: 0.05 | C9: 0.07 | D9: 0.1 | E9: =INDEX(B9:D9,1,$B$4) -> 0.07
A10: Plan mix: Starter | B10: 0.6 | C10: 0.55 | D10: 0.45 | E10: =INDEX(B10:D10,1,$B$4) -> 0.55
A11: Plan mix: Growth | B11: 0.3 | C11: 0.32 | D11: 0.35 | E11: =INDEX(B11:D11,1,$B$4) -> 0.32
A12: Plan mix: Agency | B12: 0.09 | C12: 0.12 | D12: 0.17 | E12: =INDEX(B12:D12,1,$B$4) -> 0.12
A13: Plan mix: Scale | B13: 0.01 | C13: 0.01 | D13: 0.03 | E13: =INDEX(B13:D13,1,$B$4) -> 0.01
A14: Monthly churn: Starter | B14: 0.07 | C14: 0.055 | D14: 0.04 | E14: =INDEX(B14:D14,1,$B$4) -> 0.055
A15: Monthly churn: Growth | B15: 0.05 | C15: 0.038 | D15: 0.03 | E15: =INDEX(B15:D15,1,$B$4) -> 0.038
A16: Monthly churn: Agency | B16: 0.04 | C16: 0.03 | D16: 0.02 | E16: =INDEX(B16:D16,1,$B$4) -> 0.03
A17: Monthly churn: Scale | B17: 0.025 | C17: 0.02 | D17: 0.015 | E17: =INDEX(B17:D17,1,$B$4) -> 0.02
A18: Average discount (founding offers, promos) | B18: 0.25 | C18: 0.15 | D18: 0.1 | E18: =INDEX(B18:D18,1,$B$4) -> 0.15
... A22: Free users per paying customer | B22: 10 | C22: 8 | D22: 6 | E22: =INDEX(B22:D22,1,$B$4) -> 8
A23: Cost per free user per month (from Plans) | E23: =Plans!$C$54 -> 0.91778372
A25: Line | B25: Total / KPI | C25: Oct 2026 | D25: Nov 2026 | E25: Dec 2026 | F25: Jan 2027 | G25: Feb 2027 | H25: Mar 2027 | I25: Apr 2027 | J25: May 2027 | K25: Jun 2027 | L25: Jul 2027 | M25: Aug 2027 | N25: Sep 2027 | O25: Oct 2027 | P25: Nov 2027 | Q25: Dec 2027 | R25: Jan 2028 | S25: Feb 2028 | T25: Mar 2028 | U25: Apr 2028 | V25: May 2028 | W25: Jun 2028 | X25: Jul 2028 | Y25: Aug 2028 | Z25: Sep 2028
A26: New paying customers | B26: =SUM(C26:Z26) -> 354.15429 | C26: =$E$7 -> 3 | D26: =C26*(1+$E$8) -> 3.45 | E26: =D26*(1+$E$8) -> 3.9675 | F26: =E26*(1+$E$8) -> 4.562625 | G26: =F26*(1+$E$8) -> 5.2470187 | H26: =G26*(1+$E$8) -> 6.0340716 | I26: =H26*(1+$E$8) -> 6.9391823 | J26: =I26*(1+$E$8) -> 7.9800596 | K26: =J26*(1+$E$8) -> 9.1770686 | ... N26: =M26*(1+$E$8) -> 13.957174 | O26: =N26*(1+$E$9) -> 14.934176 | P26: =O26*(1+$E$9) -> 15.979569 | Q26: =P26*(1+$E$9) -> 17.098139 | R26: =Q26*(1+$E$9) -> 18.295008 | S26: =R26*(1+$E$9) -> 19.575659 | T26: =S26*(1+$E$9) -> 20.945955 | U26: =T26*(1+$E$9) -> 22.412172 | V26: =U26*(1+$E$9) -> 23.981024 | ... Z26: =Y26*(1+$E$9) -> 31.43423
A27: Active Starter | B27: =Z27 -> 134.43495 | C27: =C26*$E$10 -> 1.65 | D27: =C27*(1-$E$14)+D26*$E$10 -> 3.45675 | E27: =D27*(1-$E$14)+E26*$E$10 -> 5.4487537 | F27: =E27*(1-$E$14)+F26*$E$10 -> 7.658516 | G27: =F27*(1-$E$14)+G26*$E$10 -> 10.123158 | H27: =G27*(1-$E$14)+H26*$E$10 -> 12.885124 | I27: =H27*(1-$E$14)+I26*$E$10 -> 15.992992 | J27: =I27*(1-$E$14)+J26*$E$10 -> 19.50241 | K27: =J27*(1-$E$14)+K26*$E$10 -> 23.477165 | ... Z27: =Y27*(1-$E$14)+Z26*$E$10 -> 134.43495
A28: Active Growth | B28: =Z28 -> 87.008106 | C28: =C26*$E$11 -> 0.96 | D28: =C28*(1-$E$15)+D26*$E$11 -> 2.02752 | E28: =D28*(1-$E$15)+E26*$E$11 -> 3.2200742 | F28: =E28*(1-$E$15)+F26*$E$11 -> 4.5577514 | G28: =F28*(1-$E$15)+G26*$E$11 -> 6.0636029 | H28: =G28*(1-$E$15)+H26*$E$11 -> 7.7640889 | I28: =H28*(1-$E$15)+I26*$E$11 -> 9.6895918 | J28: =I28*(1-$E$15)+J26*$E$11 -> 11.875006 | K28: =J28*(1-$E$15)+K26*$E$11 -> 14.360418 | ... Z28: =Y28*(1-$E$15)+Z26*$E$11 -> 87.008106
A29: Active Agency | B29: =Z29 -> 34.388821 | C29: =C26*$E$12 -> 0.36 | D29: =C29*(1-$E$16)+D26*$E$12 -> 0.7632 | E29: =D29*(1-$E$16)+E26*$E$12 -> 1.216404 | F29: =E29*(1-$E$16)+F26*$E$12 -> 1.7274269 | G29: =F29*(1-$E$16)+G26*$E$12 -> 2.3052463 | H29: =G29*(1-$E$16)+H26*$E$12 -> 2.9601775 | I29: =H29*(1-$E$16)+I26*$E$12 -> 3.7040741 | J29: =I29*(1-$E$16)+J26*$E$12 -> 4.550559 | K29: =J29*(1-$E$16)+K26*$E$12 -> 5.5152905 | ... Z29: =Y29*(1-$E$16)+Z26*$E$12 -> 34.388821
